Workbook

Sheet 3wh sale 
H2: Days | I2: 10
C3: 3WH Daily Sale Monitoring
B4: Type | C4: Line | D4: 46143 | E4: Daily Plan | F4: Avg Par Day Sales Qty | G4: Total Sale Qty | H4: Bal Excess Short | I4: Daily Ach % | J4: Month Ach % | K4: =+L4+1 -> 46155 | L4: =+M4+1 -> 46154 | M4: =+N4+1 -> 46153 | N4: =+O4+1 -> 46152 | O4: =+P4+1 -> 46151 | P4: =+Q4+1 -> 46150 | Q4: =+R4+1 -> 46149 | R4: =+S4+1 -> 46148 | ... V4: =+W4+1 -> 46144 | W4: 46143
B5: Re Body Part | C5: RE STYLING | D5: =+Monthly!AD35 -> 24224.68 | E5: =+D5/26 -> 931.71846 | F5: =+G5/$I$2 -> 820.5 | G5: =SUM(K5:W5) -> 8205 | H5: FG body | I5: =+F5/E5 -> 0.88063083 | J5: =+G5/D5 -> 0.33870416 | K5: =VLOOKUP(C5,Sheet8!$A$5:$N$21,14,0) -> 807 | L5: =VLOOKUP(C5,Sheet8!$A$5:$M$21,13,0) -> 633 | M5: =VLOOKUP(C5,Sheet8!$A$5:$L$22,12,0) -> 759 | N5: =VLOOKUP(C5,Sheet8!$A$5:$K$20,11,0) -> 120 | O5: =VLOOKUP(C5,Sheet8!$A$5:$J$20,10,0) -> 846 | P5: =VLOOKUP(C5,Sheet8!$A$5:$I$20,9,0) -> 861 | Q5: =VLOOKUP(C5,Sheet8!$A$5:$H$20,8,0) -> 705 | R5: =VLOOKUP(C5,Sheet8!$A$5:$G$21,7,0) -> 822 | S5: =VLOOKUP(C5,Sheet8!$A$5:$F$20,6,0) -> 885 | T5: =VLOOKUP(C5,Sheet8!$A$5:$E$20,5,0) -> 516 | U5: =VLOOKUP(C5,Sheet8!$A$5:$D$20,4,0) -> 630 | V5: =VLOOKUP(C5,Sheet8!$A$5:$C$20,3,0) -> 501 | W5: =VLOOKUP(C5,Sheet8!$A$5:$B$20,2,0) -> 120
C6: FRONT MUDGAURD | D6: =+Monthly!AD47+Monthly!AD48 -> 63224 | E6: =+D6/26 -> 2431.6923 | F6: =+G6/$I$2 -> 2056.3 | G6: =SUM(K6:W6) -> 20563 | H6: =+G6-(G5*2+G12+G14) -> 1369 | I6: =+F6/E6 -> 0.84562508 | J6: =+G6/D6 -> 0.32524042 | K6: =VLOOKUP(C6,Sheet8!$A$5:$N$21,14,0) -> 2204 | L6: =VLOOKUP(C6,Sheet8!$A$5:$M$21,13,0) -> 2120 | M6: =VLOOKUP(C6,Sheet8!$A$5:$L$22,12,0) -> 2410 | N6: =VLOOKUP(C6,Sheet8!$A$5:$K$20,11,0) -> 0 | O6: =VLOOKUP(C6,Sheet8!$A$5:$J$20,10,0) -> 2080 | P6: =VLOOKUP(C6,Sheet8!$A$5:$I$20,9,0) -> 2350 | Q6: =VLOOKUP(C6,Sheet8!$A$5:$H$20,8,0) -> 1280 | R6: =VLOOKUP(C6,Sheet8!$A$5:$G$21,7,0) -> 2139 | S6: =VLOOKUP(C6,Sheet8!$A$5:$F$20,6,0) -> 2080 | T6: =VLOOKUP(C6,Sheet8!$A$5:$E$20,5,0) -> 1660 | U6: =VLOOKUP(C6,Sheet8!$A$5:$D$20,4,0) -> 1280 | V6: =VLOOKUP(C6,Sheet8!$A$5:$C$20,3,0) -> 960 | W6: =VLOOKUP(C6,Sheet8!$A$5:$B$20,2,0) -> 0
C7: FRONT MUDGAURD EV | D7: =+Monthly!AD49 -> 2596 | E7: =+D7/26 -> 99.846154 | F7: =+G7/$I$2 -> 35 | G7: =SUM(K7:W7) -> 350 | H7: =+(G7-E7*I2) -> -648.46154 | I7: =+F7/E7 -> 0.35053929 | J7: =+G7/D7 -> 0.1348228 | K7: =VLOOKUP(C7,Sheet8!$A$5:$N$21,14,0) -> 100 | L7: =VLOOKUP(C7,Sheet8!$A$5:$M$21,13,0) -> 100 | M7: =VLOOKUP(C7,Sheet8!$A$5:$L$22,12,0) -> 150 | N7: 0 | O7: 0 | P7: 0 | Q7: 0 | R7: 0 | S7: 0 | T7: 0 | U7: 0 | V7: 0 | W7: 0
C8: REAR MUDGAURD | D8: =+Monthly!AD46 -> 97110 | E8: =+D8/26 -> 3735 | F8: =+G8/$I$2 -> 4924.8 | G8: =SUM(K8:W8) -> 49248 | H8: =+(G8-G5*4) -> 16428 | I8: =+F8/E8 -> 1.3185542 | J8: =+G8/D8 -> 0.50713624 | K8: =VLOOKUP(C8,Sheet8!$A$5:$N$21,14,0) -> 3456 | L8: =VLOOKUP(C8,Sheet8!$A$5:$M$21,13,0) -> 3888 | M8: =VLOOKUP(C8,Sheet8!$A$5:$L$22,12,0) -> 4320 | N8: =VLOOKUP(C8,Sheet8!$A$5:$K$20,11,0) -> 2160 | O8: =VLOOKUP(C8,Sheet8!$A$5:$J$20,10,0) -> 2592 | P8: =VLOOKUP(C8,Sheet8!$A$5:$I$20,9,0) -> 4320 | Q8: =VLOOKUP(C8,Sheet8!$A$5:$H$20,8,0) -> 4752 | R8: =VLOOKUP(C8,Sheet8!$A$5:$G$21,7,0) -> 3888 | S8: =VLOOKUP(C8,Sheet8!$A$5:$F$20,6,0) -> 5184 | T8: =VLOOKUP(C8,Sheet8!$A$5:$E$20,5,0) -> 4320 | U8: =VLOOKUP(C8,Sheet8!$A$5:$D$20,4,0) -> 5184 | V8: =VLOOKUP(C8,Sheet8!$A$5:$C$20,3,0) -> 5184 | W8: =VLOOKUP(C8,Sheet8!$A$5:$B$20,2,0) -> 0
C9: DASH BOARD | D9: =+Monthly!AD45 -> 77736 | E9: =+D9/26 -> 2989.8462 | F9: =+G9/$I$2 -> 2328 | G9: =SUM(K9:W9) -> 23280 | H9: =G9-(G5*2+G12+G14+G15) -> 868 | I9: =+F9/E9 -> 0.77863538 | J9: =+G9/D9 -> 0.29947515 | K9: =VLOOKUP(C9,Sheet8!$A$5:$N$21,14,0) -> 2082 | L9: =VLOOKUP(C9,Sheet8!$A$5:$M$21,13,0) -> 2118 | M9: =VLOOKUP(C9,Sheet8!$A$5:$L$22,12,0) -> 2038 | N9: =VLOOKUP(C9,Sheet8!$A$5:$K$20,11,0) -> 920 | O9: =VLOOKUP(C9,Sheet8!$A$5:$J$20,10,0) -> 1792 | P9: =VLOOKUP(C9,Sheet8!$A$5:$I$20,9,0) -> 2152 | Q9: =VLOOKUP(C9,Sheet8!$A$5:$H$20,8,0) -> 2448 | R9: =VLOOKUP(C9,Sheet8!$A$5:$G$21,7,0) -> 1224 | S9: =VLOOKUP(C9,Sheet8!$A$5:$F$20,6,0) -> 2428 | T9: =VLOOKUP(C9,Sheet8!$A$5:$E$20,5,0) -> 2362 | U9: =VLOOKUP(C9,Sheet8!$A$5:$D$20,4,0) -> 1240 | V9: =VLOOKUP(C9,Sheet8!$A$5:$C$20,3,0) -> 1660 | W9: =VLOOKUP(C9,Sheet8!$A$5:$B$20,2,0) -> 816
C10: STARTING HANDLE | D10: =+Monthly!AD61 -> 48629 | E10: =+D10/26 -> 1870.3462 | F10: =+G10/$I$2 -> 1402.9 | G10: =SUM(K10:W10) -> 14029 | H10: =+G10-G5*2 -> -2381 | I10: =+F10/E10 -> 0.75007506 | J10: =+G10/D10 -> 0.28849041 | K10: =VLOOKUP(C10,Sheet8!$A$5:$N$21,14,0) -> 1080 | L10: =VLOOKUP(C10,Sheet8!$A$5:$M$21,13,0) -> 1380 | M10: =VLOOKUP(C10,Sheet8!$A$5:$L$22,12,0) -> 1530 | N10: =VLOOKUP(C10,Sheet8!$A$5:$K$20,11,0) -> 0 | O10: =VLOOKUP(C10,Sheet8!$A$5:$J$20,10,0) -> 1079 | P10: =VLOOKUP(C10,Sheet8!$A$5:$I$20,9,0) -> 1080 | Q10: =VLOOKUP(C10,Sheet8!$A$5:$H$20,8,0) -> 1350 | R10: =VLOOKUP(C10,Sheet8!$A$5:$G$21,7,0) -> 1620 | S10: =VLOOKUP(C10,Sheet8!$A$5:$F$20,6,0) -> 1350 | T10: =VLOOKUP(C10,Sheet8!$A$5:$E$20,5,0) -> 1080 | U10: =VLOOKUP(C10,Sheet8!$A$5:$D$20,4,0) -> 720 | V10: =VLOOKUP(C10,Sheet8!$A$5:$C$20,3,0) -> 1760 | W10: =VLOOKUP(C10,Sheet8!$A$5:$B$20,2,0) -> 0
C11: SUPPORT TOP | D11: =+Monthly!AD64 -> 51825 | E11: =+D11/26 -> 1993.2692 | F11: =+G11/$I$2 -> 1698.1 | G11: =SUM(K11:W11) -> 16981 | H11: =+G11-G5*2 -> 571 | I11: =+F11/E11 -> 0.85191703 | J11: =+G11/D11 -> 0.3276604 | K11: =VLOOKUP(C11,Sheet8!$A$5:$N$21,14,0) -> 1473 | L11: =VLOOKUP(C11,Sheet8!$A$5:$M$21,13,0) -> 916 | M11: =VLOOKUP(C11,Sheet8!$A$5:$L$22,12,0) -> 1344 | N11: =VLOOKUP(C11,Sheet8!$A$5:$K$20,11,0) -> 0 | O11: =VLOOKUP(C11,Sheet8!$A$5:$J$20,10,0) -> 1200 | P11: =VLOOKUP(C11,Sheet8!$A$5:$I$20,9,0) -> 1688 | Q11: =VLOOKUP(C11,Sheet8!$A$5:$H$20,8,0) -> 1248 | R11: =VLOOKUP(C11,Sheet8!$A$5:$G$21,7,0) -> 1688 | S11: =VLOOKUP(C11,Sheet8!$A$5:$F$20,6,0) -> 2160 | T11: =VLOOKUP(C11,Sheet8!$A$5:$E$20,5,0) -> 1200 | U11: =VLOOKUP(C11,Sheet8!$A$5:$D$20,4,0) -> 1688 | V11: =VLOOKUP(C11,Sheet8!$A$5:$C$20,3,0) -> 2376 | W11: =VLOOKUP(C11,Sheet8!$A$5:$B$20,2,0) -> 0
B12: HD | C12: MAXIMA HD | D12: =+Monthly!AD41 -> 5819 | E12: =+D12/26 -> 223.80769 | F12: =+G12/$I$2 -> 141.8 | G12: =SUM(K12:W12) -> 1418 | H12: FG body | I12: =+F12/E12 -> 0.63357965 | J12: =+G12/D12 -> 0.24368448 | K12: =VLOOKUP(C12,Sheet8!$A$5:$N$21,14,0) -> 144 | L12: =VLOOKUP(C12,Sheet8!$A$5:$M$21,13,0) -> 152 | M12: =VLOOKUP(C12,Sheet8!$A$5:$L$22,12,0) -> 230 | N12: =VLOOKUP(C12,Sheet8!$A$5:$K$20,11,0) -> 0 | O12: =VLOOKUP(C12,Sheet8!$A$5:$J$20,10,0) -> 42 | P12: =VLOOKUP(C12,Sheet8!$A$5:$I$20,9,0) -> 124 | Q12: =VLOOKUP(C12,Sheet8!$A$5:$H$20,8,0) -> 158 | R12: =VLOOKUP(C12,Sheet8!$A$5:$G$21,7,0) -> 90 | S12: =VLOOKUP(C12,Sheet8!$A$5:$F$20,6,0) -> 144 | T12: =VLOOKUP(C12,Sheet8!$A$5:$E$20,5,0) -> 138 | U12: =VLOOKUP(C12,Sheet8!$A$5:$D$20,4,0) -> 24 | V12: =VLOOKUP(C12,Sheet8!$A$5:$C$20,3,0) -> 172 | W12: =VLOOKUP(C12,Sheet8!$A$5:$B$20,2,0) -> 0
C13: REAR COVER | D13: =+Monthly!AD67 -> 21876 | E13: =+D13/26 -> 841.38462 | F13: =+G13/$I$2 -> 338 | G13: =SUM(K13:W13) -> 3380 | H13: =+(G13-G12*2)/2 -> 272 | I13: 1 | J13: =+G13/D13 -> 0.15450722 | K13: =VLOOKUP(C13,Sheet8!$A$5:$N$21,14,0) -> 330 | L13: =VLOOKUP(C13,Sheet8!$A$5:$M$21,13,0) -> 440 | M13: =VLOOKUP(C13,Sheet8!$A$5:$L$22,12,0) -> 0 | N13: =VLOOKUP(C13,Sheet8!$A$5:$K$20,11,0) -> 0 | O13: =VLOOKUP(C13,Sheet8!$A$5:$J$20,10,0) -> 110 | P13: =VLOOKUP(C13,Sheet8!$A$5:$I$20,9,0) -> 330 | Q13: =VLOOKUP(C13,Sheet8!$A$5:$H$20,8,0) -> 330 | R13: =VLOOKUP(C13,Sheet8!$A$5:$G$21,7,0) -> 330 | S13: =VLOOKUP(C13,Sheet8!$A$5:$F$20,6,0) -> 440 | T13: =VLOOKUP(C13,Sheet8!$A$5:$E$20,5,0) -> 520 | U13: =VLOOKUP(C13,Sheet8!$A$5:$D$20,4,0) -> 330 | V13: =VLOOKUP(C13,Sheet8!$A$5:$C$20,3,0) -> 220 | W13: =VLOOKUP(C13,Sheet8!$A$5:$B$20,2,0) -> 0
B14: MAX UG | C14: MAX UG NEW | D14: =+Monthly!AD36 -> 4936 | E14: =+D14/26 -> 189.84615 | F14: =+G14/$I$2 -> 136.6 | G14: =SUM(K14:W14) -> 1366 | H14: =+(G14+G15)/(D14+D15) -> 0.32964188 | I14: =+F14/E14 -> 0.71952998 | J14: =+G14/D14 -> 0.2767423 | K14: =VLOOKUP(C14,Sheet8!$A$5:$N$21,14,0) -> 200 | L14: =VLOOKUP(C14,Sheet8!$A$5:$M$21,13,0) -> 30 | M14: =VLOOKUP(C14,Sheet8!$A$5:$L$22,12,0) -> 90 | N14: =VLOOKUP(C14,Sheet8!$A$5:$K$20,11,0) -> 90 | O14: =VLOOKUP(C14,Sheet8!$A$5:$J$20,10,0) -> 0 | P14: =VLOOKUP(C14,Sheet8!$A$5:$I$20,9,0) -> 70 | Q14: =VLOOKUP(C14,Sheet8!$A$5:$H$20,8,0) -> 240 | R14: =VLOOKUP(C14,Sheet8!$A$5:$G$21,7,0) -> 88 | S14: =VLOOKUP(C14,Sheet8!$A$5:$F$20,6,0) -> 260 | T14: =VLOOKUP(C14,Sheet8!$A$5:$E$20,5,0) -> 60 | U14: =VLOOKUP(C14,Sheet8!$A$5:$D$20,4,0) -> 168 | V14: =VLOOKUP(C14,Sheet8!$A$5:$C$20,3,0) -> 70 | W14: =VLOOKUP(C14,Sheet8!$A$5:$B$20,2,0) -> 0
C15: MAX UG NEW EV | D15: =+Monthly!AD37 -> 8970 | E15: =+D15/26 -> 345 | F15: =+G15/$I$2 -> 321.8 | G15: =SUM(K15:W15) -> 3218 | I15: =+F15/E15 -> 0.93275362 | J15: =+G15/D15 -> 0.35875139 | K15: =VLOOKUP(C15,Sheet8!$A$5:$N$21,14,0) -> 280 | L15: =VLOOKUP(C15,Sheet8!$A$5:$M$21,13,0) -> 250 | M15: =VLOOKUP(C15,Sheet8!$A$5:$L$22,12,0) -> 200 | N15: =VLOOKUP(C15,Sheet8!$A$5:$K$20,11,0) -> 110 | O15: =VLOOKUP(C15,Sheet8!$A$5:$J$20,10,0) -> 380 | P15: =VLOOKUP(C15,Sheet8!$A$5:$I$20,9,0) -> 328 | Q15: =VLOOKUP(C15,Sheet8!$A$5:$H$20,8,0) -> 180 | R15: =VLOOKUP(C15,Sheet8!$A$5:$G$21,7,0) -> 330 | S15: =VLOOKUP(C15,Sheet8!$A$5:$F$20,6,0) -> 280 | T15: =VLOOKUP(C15,Sheet8!$A$5:$E$20,5,0) -> 338 | U15: =VLOOKUP(C15,Sheet8!$A$5:$D$20,4,0) -> 186 | V15: =VLOOKUP(C15,Sheet8!$A$5:$C$20,3,0) -> 150 | W15: =VLOOKUP(C15,Sheet8!$A$5:$B$20,2,0) -> 206
C16: FRONT MUDGARD GOGO | D16: =+D15 -> 8970 | E16: =+D16/26 -> 345 | F16: =+G16/$I$2 -> 357.6 | G16: =SUM(K16:W16) -> 3576 | H16: =+G16-G15 -> 358 | I16: =+F16/E16 -> 1.0365217 | J16: =+G16/D16 -> 0.39866221 | K16: =VLOOKUP(C16,Sheet8!$A$5:$N$21,14,0) -> 131 | L16: =VLOOKUP(C16,Sheet8!$A$5:$M$21,13,0) -> 190 | M16: =VLOOKUP(C16,Sheet8!$A$5:$L$22,12,0) -> 430 | N16: =VLOOKUP(C16,Sheet8!$A$5:$K$20,11,0) -> 0 | O16: =VLOOKUP(C16,Sheet8!$A$5:$J$20,10,0) -> 300 | P16: =VLOOKUP(C16,Sheet8!$A$5:$I$20,9,0) -> 430 | Q16: =VLOOKUP(C16,Sheet8!$A$5:$H$20,8,0) -> 370 | R16: =VLOOKUP(C16,Sheet8!$A$5:$G$21,7,0) -> 360 | S16: =VLOOKUP(C16,Sheet8!$A$5:$F$20,6,0) -> 230 | T16: =VLOOKUP(C16,Sheet8!$A$5:$E$20,5,0) -> 375 | U16: =VLOOKUP(C16,Sheet8!$A$5:$D$20,4,0) -> 280 | V16: =VLOOKUP(C16,Sheet8!$A$5:$C$20,3,0) -> 280 | W16: =VLOOKUP(C16,Sheet8!$A$5:$B$20,2,0) -> 200
C17: CRADEL | D17: =+Monthly!AD57 -> 8890 | E17: =+D17/26 -> 341.92308 | F17: =+G17/$I$2 -> 271.6 | G17: =SUM(K17:W17) -> 2716 | H17: =+(G17-E17)/I2 -> 237.40769 | I17: =+F17/E17 -> 0.79433071 | J17: =+G17/D17 -> 0.30551181 | K17: =VLOOKUP(C17,Sheet8!$A$5:$N$21,14,0) -> 192 | L17: =VLOOKUP(C17,Sheet8!$A$5:$M$21,13,0) -> 288 | M17: =VLOOKUP(C17,Sheet8!$A$5:$L$22,12,0) -> 268 | N17: =VLOOKUP(C17,Sheet8!$A$5:$K$20,11,0) -> 0 | O17: =VLOOKUP(C17,Sheet8!$A$5:$J$20,10,0) -> 192 | P17: =VLOOKUP(C17,Sheet8!$A$5:$I$20,9,0) -> 240 | Q17: =VLOOKUP(C17,Sheet8!$A$5:$H$20,8,0) -> 240 | R17: =VLOOKUP(C17,Sheet8!$A$5:$G$21,7,0) -> 192 | S17: =VLOOKUP(C17,Sheet8!$A$5:$F$20,6,0) -> 240 | T17: =VLOOKUP(C17,Sheet8!$A$5:$E$20,5,0) -> 288 | U17: =VLOOKUP(C17,Sheet8!$A$5:$D$20,4,0) -> 288 | V17: =VLOOKUP(C17,Sheet8!$A$5:$C$20,3,0) -> 288 | W17: =VLOOKUP(C17,Sheet8!$A$5:$B$20,2,0) -> 0
C18: INNER DOOR | D18: =+D14+D15 -> 13906 | E18: =+D18/26 -> 534.84615 | F18: =+G18/$I$2 -> 355.7 | G18: =SUM(K18:W18) -> 3557 | H18: =+G18-(G14+G15) -> -1027 | K18: 510 | L18: 424 | M18: 0 | N18: 0 | O18: 0 | P18: 210 | Q18: 0 | R18: 1221 | S18: 0 | T18: 931 | U18: 261 | V18: 0 | W18: 0
C19: ENG BKT | D19: =+Monthly!AD56 -> 3043 | E19: =+D19/26 -> 117.03846 | F19: =+G19/$I$2 -> 113.2 | G19: =SUM(K19:W19) -> 1132 | H19: =+G19-E19/I2 -> 1120.2962 | I19: =+F19/E19 -> 0.96720342 | J19: =+G19/D19 -> 0.37200131 | K19: =VLOOKUP(C19,Sheet8!$A$5:$N$21,14,0) -> 0 | L19: =VLOOKUP(C19,Sheet8!$A$5:$M$21,13,0) -> 400 | M19: =VLOOKUP(C19,Sheet8!$A$5:$L$22,12,0) -> 324 | N19: =VLOOKUP(C19,Sheet8!$A$5:$K$20,11,0) -> 0 | O19: 0 | P19: =VLOOKUP(C19,Sheet8!$A$5:$I$20,9,0) -> 84 | Q19: =VLOOKUP(C19,Sheet8!$A$5:$H$20,8,0) -> 84 | R19: =VLOOKUP(C19,Sheet8!$A$5:$G$21,7,0) -> 0 | S19: =VLOOKUP(C19,Sheet8!$A$5:$F$20,6,0) -> 84 | T19: =VLOOKUP(C19,Sheet8!$A$5:$E$20,5,0) -> 0 | U19: =VLOOKUP(C19,Sheet8!$A$5:$D$20,4,0) -> 72 | V19: =VLOOKUP(C19,Sheet8!$A$5:$C$20,3,0) -> 84 | W19: =VLOOKUP(C19,Sheet8!$A$5:$B$20,2,0) -> 0
C20: LOGISTICS | D20: 141241 | E20: =+D20/26 -> 5432.3462 | F20: =+G20/$I$2 -> 4221 | G20: =SUM(K20:W20) -> 42210 | I20: =+F20/E20 -> 0.77701234 | J20: =+G20/D20 -> 0.2988509 | K20: =VLOOKUP(C20,Sheet8!$A$5:$N$21,14,0) -> 15270 | L20: =VLOOKUP(C20,Sheet8!$A$5:$M$21,13,0) -> 3600 | M20: =VLOOKUP(C20,Sheet8!$A$5:$L$22,12,0) -> 2000 | N20: =VLOOKUP(C20,Sheet8!$A$5:$K$20,11,0) -> 0 | O20: 0 | P20: =VLOOKUP(C20,Sheet8!$A$5:$I$20,9,0) -> 2000 | Q20: =VLOOKUP(C20,Sheet8!$A$5:$H$20,8,0) -> 2084 | R20: =VLOOKUP(C20,Sheet8!$A$5:$G$21,7,0) -> 0 | S20: =VLOOKUP(C20,Sheet8!$A$5:$F$20,6,0) -> 84 | T20: =VLOOKUP(C20,Sheet8!$A$5:$E$20,5,0) -> 2000 | U20: =VLOOKUP(C20,Sheet8!$A$5:$D$20,4,0) -> 72 | V20: =VLOOKUP(C20,Sheet8!$A$5:$C$20,3,0) -> 15100 | W20: =VLOOKUP(C20,Sheet8!$A$5:$B$20,2,0) -> 0
C21: Re Side Door | D21: =+Monthly!AD70 -> 33800 | E21: =+D21/26 -> 1300 | F21: =+G21/$I$2 -> 1040 | G21: =SUM(K21:W21) -> 10400 | H21: =+G21-G5 -> 2195 | I21: =+F21/E21 -> 0.8 | J21: =+G21/D21 -> 0.30769231 | K21: =VLOOKUP(C21,Sheet8!$A$5:$N$21,14,0) -> 960 | L21: =VLOOKUP(C21,Sheet8!$A$5:$M$21,13,0) -> 720 | M21: =VLOOKUP(C21,Sheet8!$A$5:$L$22,12,0) -> 960 | N21: =VLOOKUP(C21,Sheet8!$A$5:$K$20,11,0) -> 0 | O21: =VLOOKUP(C21,Sheet8!$A$5:$J$20,10,0) -> 960 | P21: =VLOOKUP(C21,Sheet8!$A$5:$I$20,9,0) -> 960 | Q21: =VLOOKUP(C21,Sheet8!$A$5:$H$20,8,0) -> 1200 | R21: =VLOOKUP(C21,Sheet8!$A$5:$G$21,7,0) -> 1120 | S21: =VLOOKUP(C21,Sheet8!$A$5:$F$20,6,0) -> 1120 | T21: =VLOOKUP(C21,Sheet8!$A$5:$E$20,5,0) -> 720 | U21: =VLOOKUP(C21,Sheet8!$A$5:$D$20,4,0) -> 720 | V21: =VLOOKUP(C21,Sheet8!$A$5:$C$20,3,0) -> 960 | W21: =VLOOKUP(C21,Sheet8!$A$5:$B$20,2,0) -> 0
C22: Total | D22: =SUM(D5:D21) -> 616795.68 | E22: =SUM(E5:E21) -> 23722.911 | G22: =SUM(G5:G21) -> 205629 | I22: =AVERAGE(I5:I21) -> 0.83980677 | J22: =AVERAGE(J5:J21) -> 0.30862084 | P22: 0
E65459: =+D65459/25 -> 0

Sheet Monthly
A1: 3 Wh Production Plan - May - 26
D2: Month | G2: Prod In 3WH plant | M2: Prod in 4WH plant | Q2: Total Production plan
A3: Sr.No. | B3: Model | C3: Line | D3: Production Requirement | G3: Prod Plan | H3: Week 1--- 8 Days | I3: Week 2--- 6 Days | J3: Week 3--- 6 Days | K3: Week 4--- 6 Days | L3: Monthly Req. In 3WH plant | M3: Maxima & Cargo in 4WH Line (prod Plan) | N3: Monthly Req. In 4WH plant | O3: Net Vehicles production to be plan in May - 26 | W3: re styling
D4: Dom | E4: Export | F4: Total | H4: (2 to 9) | I4: (11 to 16) | J4: (18 to 23) | K4: (25 to 30) | V4: Total | W4: Yesh 50% | X4: Laxmi 50%
D5: BS VI | E5: BS IV | O5: BS IV | P5: BS VI | Q5: Total | S5: Veh. Type | T5: BS VI | U5: BS IV
A6: 1 | B6: RE 4S PETROL | C6: D | E6: 15050 | F6: =SUM(D6:E6) -> 15050 | G6: =F6/26 -> 578.84615 | H6: =$G6*3 -> 1736.5385 | I6: =$G6*6 -> 3473.0769 | J6: =$G6*6 -> 3473.0769 | K6: =$G6*6 -> 3473.0769 | L6: =F6 -> 15050 | O6: =L6 -> 15050 | Q6: =L6+N6 -> 15050 | S6: Re Petrol | T6: =+Q6+Q15+Q12 -> 26292 | V6: =+T6 -> 26292 | W6: =+Z6 -> 19456.08 | X6: =+AA6 -> 6835.92 | Z6: =+T6*74/100 -> 19456.08 | AA6: =T6*26/100 -> 6835.92
A7: 2 | B7: RE 4S CNG Bi-fuel | D7: 0 | E7: 900 | F7: =SUM(D7:E7) -> 900 | G7: =F7/26 -> 34.615385 | H7: =$G7*3 -> 103.84615 | I7: =$G7*6 -> 207.69231 | J7: =$G7*6 -> 207.69231 | K7: =$G7*6 -> 207.69231 | L7: =F7 -> 900 | O7: =E7 -> 900 | P7: =D7 -> 0 | Q7: =L7+N7 -> 900 | S7: Re CNG | T7: =+Q7+Q8+Q9+Q10+Q11 -> 17688 | V7: =+T7 -> 17688 | W7: =+Z7 -> 3537.6 | X7: =+AA7 -> 14150.4 | Z7: =V7*20/100 -> 3537.6 | AA7: =T7*80/100 -> 14150.4
A8: 3 | B8: RE 4S CNG Bi-fuel OBD 2B | D8: 13104 | E8: 608 | F8: =SUM(D8:E8) -> 13712 | G8: =F8/26 -> 527.38462 | H8: =$G8*3 -> 1582.1538 | I8: =$G8*6 -> 3164.3077 | J8: =$G8*6 -> 3164.3077 | K8: =$G8*6 -> 3164.3077 | L8: =F8 -> 13712 | O8: =E8 -> 608 | P8: =D8 -> 13104 | Q8: =L8+N8 -> 13712 | S8: PG MF 2s | T8: =+Q13+Q16 -> 748 | V8: =+T8 -> 748 | X8: =+V8 -> 748 | AA8: =T8 -> 748
A9: 4 | B9: RE 4S LPG MF OBD 2B | D9: 170 | F9: =SUM(D9:E9) -> 170 | G9: =F9/26 -> 6.5384615 | H9: =$G9*3 -> 19.615385 | I9: =$G9*6 -> 39.230769 | J9: =$G9*6 -> 39.230769 | K9: =$G9*6 -> 39.230769 | L9: =F9 -> 170 | P9: =D9 -> 170 | Q9: =L9+N9 -> 170 | S9: Re Disel | T9: =+Q19 -> 1231 | V9: =+T9 -> 1231 | W9: =+V9 -> 1231 | X9: 0 | Z9: =T9 -> 1231
A10: 5 | B10: RE 4S LPG Bi-fuel | D10: 0 | E10: 800 | F10: =SUM(D10:E10) -> 800 | G10: =F10/26 -> 30.769231 | H10: =$G10*3 -> 92.307692 | I10: =$G10*6 -> 184.61538 | J10: =$G10*6 -> 184.61538 | K10: =$G10*6 -> 184.61538 | L10: =F10 -> 800 | O10: =E10 -> 800 | P10: =D10 -> 0 | Q10: =L10+N10 -> 800 | S10: EV GOGO | T10: =+Q17+Q18 -> 2596 | V10: =+T10 -> 2596 | X10: =+V10 -> 2596 | AA10: =T10 -> 2596
A11: 6 | B11: RE 4S LPG Bi-fuel OBD 2B | D11: 430 | E11: =458+1155+63 -> 1676 | F11: =SUM(D11:E11) -> 2106 | G11: =F11/26 -> 81 | H11: =$G11*3 -> 243 | I11: =$G11*6 -> 486 | J11: =$G11*6 -> 486 | K11: =$G11*6 -> 486 | L11: =F11 -> 2106 | O11: =E11 -> 1676 | P11: =D11 -> 430 | Q11: =L11+N11 -> 2106 | S11: Total | T11: =SUM(T6:T10) -> 48555 | U11: =SUM(U6:U10) -> 0 | V11: =+T11 -> 48555 | W11: =+W6+W7+W8+W9+W10 -> 24224.68 | X11: =+X6+X7+X8+X9+X10 -> 24330.32 | Z11: =SUM(Z6:Z10) -> 24224.68 | AA11: =SUM(AA6:AA10) -> 24330.32
A12: 7 | B12: RE 4S PETROL OBD 2B | D12: 336 | F12: =SUM(D12:E12) -> 336 | G12: =F12/26 -> 12.923077 | H12: =$G12*3 -> 38.769231 | I12: =$G12*6 -> 77.538462 | J12: =$G12*6 -> 77.538462 | K12: =$G12*6 -> 77.538462 | L12: =F12 -> 336 | P12: =D12 -> 336 | Q12: =L12+N12 -> 336 | S12: Re max UG | T12: =+Q21+Q22+Q23+Q24+Q25+Q26 -> 4936 | V12: =+T12 -> 4936 | Z12: =V11/2 -> 24277.5 | AA12: =Z12 -> 24277.5
A13: 8 | B13: RE LPG 2S ES | D13: 0 | E13: 462 | F13: =SUM(D13:E13) -> 462 | G13: =F13/26 -> 17.769231 | H13: =$G13*3 -> 53.307692 | I13: =$G13*6 -> 106.61538 | J13: =$G13*6 -> 106.61538 | K13: =$G13*6 -> 106.61538 | L13: =F13 -> 462 | O13: =E13 -> 462 | P13: =D13 -> 0 | Q13: =L13+N13 -> 462 | S13: Re max UG EV GOGO | T13: =+Q28+Q27 -> 8970 | V13: =+T13 -> 8970
B14: Total D Line | D14: =SUM(D6:D13) -> 14040 | E14: =SUM(E6:E13) -> 19496 | F14: =SUM(F6:F13) -> 33536 | G14: =SUM(G6:G13) -> 1289.8462 | H14: =SUM(H6:H13) -> 3869.5385 | I14: =SUM(I6:I13) -> 7739.0769 | J14: =SUM(J6:J13) -> 7739.0769 | K14: =SUM(K6:K13) -> 7739.0769 | L14: =SUM(L6:L13) -> 33536 | O14: =SUM(O6:O13) -> 19496 | P14: =SUM(P6:P13) -> 14040 | Q14: =SUM(Q6:Q13) -> 33536 | S14: Max Wider | T14: =+Q20+Q30+Q31 -> 5469 | V14: =+T14 -> 5469
A15: 1 | B15: RE 4S PETROL | C15: E | E15: =25956-15050 -> 10906 | F15: =SUM(D15:E15) -> 10906 | G15: =F15/26+200 -> 619.46154 | H15: =$G15*3 -> 1858.3846 | I15: =$G15*6 -> 3716.7692 | J15: =$G15*6 -> 3716.7692 | K15: =$G15*6 -> 3716.7692 | L15: =F15 -> 10906 | O15: =L15 -> 10906 | P15: =D15 -> 0 | Q15: =L15+N15 -> 10906 | S15: Max Wider EV | T15: =+Q29 -> 350 | V15: =+T15 -> 350
A16: 2 | B16: RE PET 2S NES/ES EXP | E16: 286 | F16: =SUM(D16:E16) -> 286 | G16: =F16/26 -> 11 | H16: =$G16*3 -> 33 | I16: =$G16*6 -> 66 | J16: =$G16*6 -> 66 | K16: =$G16*6 -> 66 | L16: =F16 -> 286 | O16: =L16 -> 286 | P16: =D16 -> 0 | Q16: =L16+N16 -> 286 | S16: gc Cabin | T16: =+Q32+Q33+Q34+Q35+Q36+Q37+Q38+Q39+Q40 -> 6860 | V16: =+T16 -> 6860
A17: 3 | B17: RE EV 9.2 Kwh WEGO (Wider scudo) | D17: 1399 | E17: 735 | F17: =SUM(D17:E17) -> 2134 | G17: =F17/26 -> 82.076923 | H17: =$G17*3 -> 246.23077 | I17: =$G17*6 -> 492.46154 | J17: =$G17*6 -> 492.46154 | K17: =$G17*6 -> 492.46154 | L17: =F17 -> 2134 | O17: =E17 -> 735 | P17: =D17 -> 1399 | Q17: =L17+N17 -> 2134 | S17: E RIKI | T17: =+Q41+Q42+Q43 -> 544
A18: 4 | B18: RE EV 12.2 Kwh WEGO (Wider scudo) | D18: 462 | F18: =SUM(D18:E18) -> 462 | G18: =F18/26 -> 17.769231 | H18: =$G18*3 -> 53.307692 | I18: =$G18*6 -> 106.61538 | J18: =$G18*6 -> 106.61538 | K18: =$G18*6 -> 106.61538 | L18: =F18 -> 462 | P18: =D18 -> 462 | Q18: =L18+N18 -> 462
A19: 5 | B19: RE DIESEL OBD 2B | D19: 1231 | F19: =SUM(D19:E19) -> 1231 | G19: =F19/26 -> 47.346154 | H19: =$G19*3 -> 142.03846 | I19: =$G19*6 -> 284.07692 | J19: =$G19*6 -> 284.07692 | K19: =$G19*6 -> 284.07692 | L19: =F19 -> 1231 | O19: =E19 -> 0 | P19: =L19 -> 1231 | Q19: =L19+N19 -> 1231
A20: 6 | B20: BAJAJ MAXIMA X WIDE DIESEL OBD2B | D20: 3652 | F20: =SUM(D20:E20) -> 3652 | H20: =$G20*3 -> 0 | I20: =$G20*6 -> 0 | J20: =$G20*6 -> 0 | K20: =$G20*6 -> 0 | L20: 0 | M20: =N20/26 -> 140.46154 | N20: =F20 -> 3652 | P20: =D20 -> 3652 | Q20: =N20 -> 3652
A21: 7 | B21: BAJAJ MAXIMA Z CNG Bi-fuel OBD 2B | D21: 3622 | F21: =SUM(D21:E21) -> 3622 | H21: =$G21*3 -> 0 | I21: =$G21*6 -> 0 | J21: =$G21*6 -> 0 | K21: =$G21*6 -> 0 | L21: 0 | M21: =N21/26 -> 139.30769 | N21: =F21 -> 3622 | P21: =N21 -> 3622 | Q21: =N21 -> 3622 | T21: =+T12+T14+T16 -> 17265
A22: 8 | B22: BAJAJ MAXIMA Z LPG MF OBD 2B | D22: 8 | F22: =SUM(D22:E22) -> 8 | H22: =$G22*3 -> 0 | I22: =$G22*6 -> 0 | J22: =$G22*6 -> 0 | K22: =$G22*6 -> 0 | L22: 0 | M22: =N22/26 -> 0.30769231 | N22: =F22 -> 8 | P22: =N22 -> 8 | Q22: =N22 -> 8
A23: 9 | B23: BAJAJ MAXIMA Z LPG Bi-fuel | D23: 0 | E23: 120 | F23: =SUM(D23:E23) -> 120 | H23: =$G23*3 -> 0 | I23: =$G23*6 -> 0 | J23: =$G23*6 -> 0 | K23: =$G23*6 -> 0 | L23: 0 | M23: =N23/26 -> 4.6153846 | N23: =F23 -> 120 | O23: =E23 -> 120 | P23: 0 | Q23: =N23 -> 120
A24: 10 | B24: BAJAJ MAXIMA Z LPG Bi-fuel OBD 2B | D24: 293 | F24: =SUM(D24:E24) -> 293 | H24: =$G24*3 -> 0 | I24: =$G24*6 -> 0 | J24: =$G24*6 -> 0 | K24: =$G24*6 -> 0 | L24: 0 | M24: =N24/26 -> 11.269231 | N24: =F24 -> 293 | P24: =N24 -> 293 | Q24: =N24 -> 293
A25: 11 | B25: BAJAJ MAXIMA Z DIESEL OBD 2B | D25: 581 | F25: =SUM(D25:E25) -> 581 | H25: =$G25*3 -> 0 | I25: =$G25*6 -> 0 | J25: =$G25*6 -> 0 | K25: =$G25*6 -> 0 | L25: 0 | M25: =N25/26 -> 22.346154 | N25: =F25 -> 581 | P25: =N25 -> 581 | Q25: =N25 -> 581
A26: 12 | B26: BAJAJ MAXIMA Z PET | D26: 0 | E26: 312 | F26: =SUM(D26:E26) -> 312 | H26: =$G26*3 -> 0 | I26: =$G26*6 -> 0 | J26: =$G26*6 -> 0 | K26: =$G26*6 -> 0 | L26: 0 | M26: =N26/26 -> 12 | N26: =F26 -> 312 | O26: =E26 -> 312 | P26: 0 | Q26: =N26 -> 312
A27: 13 | B27: WEGO P7009 | D27: 805 | F27: =SUM(D27:E27) -> 805 | H27: =$G27*3 -> 0 | I27: =$G27*6 -> 0 | J27: =$G27*6 -> 0 | K27: =$G27*6 -> 0 | L27: 0 | M27: =N27/26 -> 30.961538 | N27: =F27 -> 805 | O27: =E27 -> 0 | P27: =N27 -> 805 | Q27: =N27 -> 805 | AA27: 3wh Production plan May 2026
A28: 14 | B28: BAJAJA MAXIMA Z EV WEGO P7012 (Wider scudo) | D28: 8165 | F28: =SUM(D28:E28) -> 8165 | H28: =$G28*3 -> 0 | I28: =$G28*6 -> 0 | J28: =$G28*6 -> 0 | K28: =$G28*6 -> 0 | L28: 0 | M28: =N28/26 -> 314.03846 | N28: =F28 -> 8165 | O28: =E28 -> 0 | P28: =N28 -> 8165 | Q28: =N28 -> 8165
A29: 15 | B29: BAJAJ MAXIMA X WIDE WEGO P9018 | D29: 350 | F29: =SUM(D29:E29) -> 350 | H29: =$G29*3 -> 0 | I29: =$G29*6 -> 0 | J29: =$G29*6 -> 0 | K29: =$G29*6 -> 0 | L29: 0 | M29: =N29/26 -> 13.461538 | N29: =F29 -> 350 | P29: =N29 -> 350 | Q29: =N29 -> 350
A30: 16 | B30: BAJAJ MAXIMA X WIDE CNG Bi-fuel OBD 2B | D30: 1813 | F30: =SUM(D30:E30) -> 1813 | H30: =$G30*3 -> 0 | I30: =$G30*6 -> 0 | J30: =$G30*6 -> 0 | K30: =$G30*6 -> 0 | L30: 0 | M30: =N30/26 -> 69.730769 | N30: =F30 -> 1813 | P30: =N30 -> 1813 | Q30: =N30 -> 1813 | AD30: Working Days | AE30: 26
A31: 17 | B31: BAJAJ MAXIMA X WIDE LPG Bi-fuel OBD 2B | D31: 4 | F31: =SUM(D31:E31) -> 4 | H31: =$G31*3 -> 0 | I31: =$G31*6 -> 0 | J31: =$G31*6 -> 0 | K31: =$G31*6 -> 0 | L31: 0 | M31: =N31/26 -> 0.15384615 | N31: =F31 -> 4 | P31: =N31 -> 4 | Q31: =N31 -> 4 | AA31: Line | AB31: Material | AC31: Description | AD31: Production plan | AE31: Per day
A32: 18 | B32: BAJAJ MAXIMA C PET | D32: 0 | E32: 232 | F32: =SUM(D32:E32) -> 232 | H32: =$G32*3 -> 0 | I32: =$G32*6 -> 0 | J32: =$G32*6 -> 0 | K32: =$G32*6 -> 0 | L32: 0 | M32: =N32/26 -> 8.9230769 | N32: =F32 -> 232 | O32: =E32 -> 232 | P32: 0 | Q32: =N32 -> 232 | AA32: RE Styling | AB32: 1502020125 | AC32: 52AF1050 BODY ASSLY RE AIR COOLED BI-FUE | AD32: =+W7 -> 3537.6 | AE32: =+AD32/$AE$30 -> 136.06154
A33: 19 | B33: BAJAJ MAXIMA C CNG Bi-fuel Longer tray OBD 2B | D33: 2504 | F33: =SUM(D33:E33) -> 2504 | H33: =$G33*3 -> 0 | I33: =$G33*6 -> 0 | J33: =$G33*6 -> 0 | K33: =$G33*6 -> 0 | L33: 0 | M33: =N33/26 -> 96.307692 | N33: =F33 -> 2504 | P33: =N33 -> 2504 | Q33: =N33 -> 2504 | AB33: 1502020101 | AC33: 52BA0852 ASSLY BODY COMPACT DIESEL | AD33: =+W9 -> 1231 | AE33: =+AD33/$AE$30 -> 47.346154
A34: 20 | B34: BAJAJ MAXIMA C CNG Bi-fuel shorter tray OBD 2B | D34: 0 | F34: =SUM(D34:E34) -> 0 | H34: =$G34*3 -> 0 | I34: =$G34*6 -> 0 | J34: =$G34*6 -> 0 | K34: =$G34*6 -> 0 | L34: 0 | M34: =N34/26 -> 0 | N34: =F34 -> 0 | O34: =E34 -> 0 | P34: =N34 -> 0 | Q34: =N34 -> 0 | AB34: 1502020104 | AC34: AA231532 BODY ASSLY PETROL | AD34: =+W6 -> 19456.08 | AE34: =+AD34/$AE$30 -> 748.31077
A35: 21 | B35: BAJAJ MAXIMA C EV 9.2 Kwh LT WEGO | D35: 48 | F35: =SUM(D35:E35) -> 48 | H35: =$G35*3 -> 0 | I35: =$G35*6 -> 0 | J35: =$G35*6 -> 0 | K35: =$G35*6 -> 0 | L35: 0 | M35: =N35/26 -> 1.8461538 | N35: =F35 -> 48 | P35: =N35 -> 48 | Q35: =N35 -> 48 | AC35: Total | AD35: =SUM(AD32:AD34) -> 24224.68 | AE35: =SUM(AE32:AE34) -> 931.71846
A36: 22 | B36: BAJAJ MAXIMA C EV 12.2 Kwh WEGO | D36: 570 | F36: =SUM(D36:E36) -> 570 | H36: =$G36*3 -> 0 | I36: =$G36*6 -> 0 | J36: =$G36*6 -> 0 | K36: =$G36*6 -> 0 | L36: 0 | M36: =N36/26 -> 21.923077 | N36: =F36 -> 570 | P36: =N36 -> 570 | Q36: =N36 -> 570 | AA36: Re MAX UG NEW | AB36: 1502020074 | AC36: 52AZ0184 BODY ASSLY MAX Z WTH REGU. HOOD | AD36: =+T12 -> 4936 | AE36: =+AD36/$AE$30 -> 189.84615
A37: 23 | B37: BAJAJ MAXIMA C LPG | D37: 0 | E37: 80 | F37: =SUM(D37:E37) -> 80 | H37: =$G37*3 -> 0 | I37: =$G37*6 -> 0 | J37: =$G37*6 -> 0 | K37: =$G37*6 -> 0 | L37: 0 | M37: =N37/26 -> 3.0769231 | N37: =F37 -> 80 | O37: =E37 -> 80 | P37: 0 | Q37: =N37 -> 80 | AB37: 1502020122 | AC37: 52AH0692 BODY ASSLY MAXIMA Z EV | AD37: =+T13 -> 8970 | AE37: =+AD37/$AE$30 -> 345
A38: 24 | B38: BAJAJ MAXIMA C DIESEL | D38: 0 | F38: =SUM(D38:E38) -> 0 | H38: =$G38*3 -> 0 | I38: =$G38*6 -> 0 | J38: =$G38*6 -> 0 | K38: =$G38*6 -> 0 | L38: =SUM(H38:K38)*0.963 -> 0 | M38: =N38/26 -> 0 | N38: =F38 -> 0 | O38: =E38 -> 0 | P38: =D38 -> 0 | Q38: =L38+N38 -> 0 | AD38: =+AD37+AD36 -> 13906 | AE38: =+AE36+AE37 -> 534.84615
A39: 25 | B39: BAJAJ MAXIMA C DIESEL Longer tray OBD2B | D39: 3206 | E39: 120 | F39: =SUM(D39:E39) -> 3326 | H39: =$G39*3 -> 0 | I39: =$G39*6 -> 0 | J39: =$G39*6 -> 0 | K39: =$G39*6 -> 0 | L39: 0 | M39: =N39/26 -> 127.92308 | N39: =F39 -> 3326 | O39: =E39 -> 120 | P39: =D39 -> 3206 | Q39: =N39 -> 3326 | AA39: MAXIMA HD Wider | AB39: 1502020102 | AC39: AT211332 BODY ASSLY MAXIMA HD | AD39: =+T14 -> 5469 | AE39: =+AD39/$AE$30 -> 210.34615
A40: 26 | B40: BAJAJ MAXIMA C DIESEL shorter tray OBD 2B | D40: 100 | F40: =SUM(D40:E40) -> 100 | H40: =$G40*3 -> 0 | I40: =$G40*6 -> 0 | J40: =$G40*6 -> 0 | K40: =$G40*6 -> 0 | L40: 0 | M40: =N40/26 -> 3.8461538 | N40: =F40 -> 100 | O40: =E40 -> 0 | P40: =D40 -> 100 | Q40: =N40 -> 100 | AB40: 1502020117 | AC40: 52BK0023 BODY ASSLY MAXIMA HD EV | AD40: =+T15 -> 350 | AE40: =+AD40/$AE$30 -> 13.461538
A41: 27 | B41: RIKI P4005 (Base) | D41: 498 | F41: =SUM(D41:E41) -> 498 | H41: =$G41*3 -> 0 | I41: =$G41*6 -> 0 | J41: =$G41*6 -> 0 | K41: =$G41*6 -> 0 | L41: 0 | M41: =N41/26 -> 19.153846 | N41: =F41 -> 498 | O41: =E41 -> 0 | P41: =D41 -> 498 | Q41: =N41 -> 498 | AD41: =+AD40+AD39 -> 5819 | AE41: =+AE40+AE39 -> 223.80769
A42: 28 | B42: RIKI P4006 (Premium) | D42: 7 | F42: =SUM(D42:E42) -> 7 | H42: =$G42*3 -> 0 | I42: =$G42*6 -> 0 | J42: =$G42*6 -> 0 | K42: =$G42*6 -> 0 | L42: 0 | M42: =N42/26 -> 0.26923077 | N42: =F42 -> 7 | P42: =D42 -> 7 | Q42: =N42 -> 7 | AA42: DASH BOARD | AB42: 1502040267 | AC42: AZ111331_06 SUPPORT ASSLY DASHBOARD EV | AD42: =+T11+T12+T14+T16 -> 65820 | AE42: =+AD42/$AE$30 -> 2531.5385
A43: 29 | B43: RIKI C4005 | D43: 39 | F43: =SUM(D43:E43) -> 39 | H43: =$G43*3 -> 0 | I43: =$G43*6 -> 0 | J43: =$G43*6 -> 0 | K43: =$G43*6 -> 0 | L43: 0 | M43: =N43/26 -> 1.5 | N43: =F43 -> 39 | P43: =D43 -> 39 | Q43: =N43 -> 39 | AB43: 1502040322 | AC43: AH115161 SUPPORT ASSLY DASHBOARD | AD43: =+T10+T13+T15 -> 11916 | AE43: =+AD43/$AE$30 -> 458.30769
B44: Total E Line | D44: =SUM(D15:D43) -> 29357 | E44: =SUM(E15:E43) -> 12791 | F44: =SUM(F15:F24) -> 22714 | G44: =SUM(G15:G43) -> 777.65385 | H44: =SUM(H15:H43) -> 2332.9615 | I44: =SUM(I15:I43) -> 4665.9231 | J44: =SUM(J15:J43) -> 4665.9231 | K44: =SUM(K15:K43) -> 4665.9231 | L44: =SUM(L15:L43) -> 15019 | M44: =SUM(M15:M43) -> 1043.4231 | N44: =SUM(N15:N43) -> 27129 | ... Q44: =SUM(Q15:Q43) -> 42148 | AB44: 1502040202 | AC44: AT111120 ASSLY SUPPORT PLASTIC DASHBOARD | AD44: 0 | AE44: =+AD44/$AE$30 -> 0
B45: Grand Total | D45: =D44+D14 -> 43397 | E45: =E44+E14 -> 32287 | F45: =D45+E45 -> 75684 | G45: =G44+G14 -> 2067.5 | H45: =H44+H14 -> 6202.5 | I45: =I44+I14 -> 12405 | J45: =J44+J14 -> 12405 | K45: =K44+K14 -> 12405 | L45: =L44+L14 -> 48555 | M45: =M44+M14 -> 1043.4231 | N45: =N44+N14 -> 27129 | ... Q45: =Q44+Q14 -> 75684 | AD45: =+AD44+AD43+AD42 -> 77736 | AE45: =SUM(AE42:AE44) -> 2989.8462
AA46: MUDGUARD | AB46: 1502010011 | AC46: REAR MUDGUARD ASSEMBLY | AD46: =+T11*2 -> 97110 | AE46: =+AD46/$AE$30 -> 3735
B47: Qute Petrol | E47: 1822 | F47: =SUM(D47:E47) -> 1822 | G47: =F47/26 -> 70.076923 | N47: =F47 -> 1822 | O47: =E47 -> 1822 | P47: =D47 -> 0 | Q47: =N47 -> 1822 | AB47: 1502040216 | AC47: AA161183 MUDGUARD ASSLY FRONT W/O HOLE | AD47: =+T6+T7+T8+T9 -> 45959 | AE47: =+AD47/$AE$30 -> 1767.6538
P48: Total | Q48: =Q45+Q47 -> 77506 | AB48: 1502040233 | AC48: BB161099 MUDGUARD FRONT REFL | AD48: =+T12+T14+T16 -> 17265 | AE48: =+AD48/$AE$30 -> 664.03846
I49: Engine Line setting | M49: Vehicle Line Setting | AB49: 1502040217 | AC49: AH111571 MUDGUARD ASSEMBLY FORNT EV | AD49: =+T10 -> 2596 | AE49: =+AD49/$AE$30 -> 99.846154
C50: Qute | D50: 2S | E50: 4S | F50: Dsl | G50: EV | I50: 2S | J50: 40 | M50: RE | N50: 2042 | AB50: 1502040271 | AC50: AH181418_03 MUDGUARD ASSLY FRONT EV | AD50: =+T13+T15 -> 9320 | AE50: =+AD50/$AE$30 -> 358.46154
B51: TOTAL | C51: =Q47 -> 1822 | D51: =L13+L16 -> 748 | E51: =L6+L7+L15+N15+N32+N26+L8+L10+N23+N34+N37+L9+L11+N21+N22+N24+N30+N31+N33+L12 -> 52968 | F51: =L40+N40+N39+N20+L19+N25+N38 -> 8890 | G51: =N28+L17+N41+N43+N29+N42+N27+N35+N36+L18 -> 13078 | I51: 4S | J51: 2410 | M51: Maxima | N51: 720 | AB51: 1502040307 | AC51: AH181432 MUDGUARD | AD51: =+T17 -> 544 | AE51: =+AD51/$AE$30 -> 20.923077
B52: PER DAY | C52: =C51/C53 -> 70.076923 | D52: =D51/D53 -> 28.769231 | E52: =E51/E53 -> 2037.2308 | F52: =F51/F53 -> 341.92308 | G52: =G51/G53 -> 503 | I52: DSL | J52: 350 | M52: EV Plant | N52: 525 | AD52: =SUM(AD46:AD51) -> 172794 | AE52: =SUM(AE46:AE51) -> 6645.9231
B53: Working days | C53: 26 | D53: 26 | E53: 26 | F53: 26 | G53: 26 | I53: EV | J53: 400 | M53: Total | N53: =SUM(N50:N52) -> 3287 | AA53: ENG BKT | AB53: 1502040061 | AC53: ASSLY FOR ISOLATOR BLOCK LH | AD53: =+Q19 -> 1231 | AE53: =+AD53/$AE$30 -> 47.346154
I54: Total | J54: =SUM(J50:J53) -> 3200 | AB54: 1502040068 | AC54: PART FOR ENG FOUNDATION BKT RH | AD54: =+AD53 -> 1231 | AE54: =+AD54/$AE$30 -> 47.346154
AB55: 1502010024 | AC55: BH113408 BKT ENG MTG REAR RH | AD55: =+Q25 -> 581 | AE55: =+AD55/$AE$30 -> 22.346154
AD56: =SUM(AD53:AD55) -> 3043 | AE56: =SUM(AE53:AE55) -> 117.03846
AA57: CRADEL | AB57: 1502040194 | AC57: AL161775 HYDROFORM CRADEL BSIV | AD57: =+Q39+Q40+Q19+Q25+Q20 -> 8890 | AE57: =+AD57/$AE$30 -> 341.92308
AE58: =SUM(AE57) -> 341.92308
AA59: STARTING HANDEL | AB59: 1502040119 | AC59: AZ621019 ASSEMBLY STARTING HANDLE FL | AD59: 2670 | AE59: =+AD59/$AE$30 -> 102.69231
AB60: 1502040235 | AC60: AA102281_ASSLY HANDLE STARTING | AD60: =+T6+T7+T8+T9 -> 45959 | AE60: =+AD60/$AE$30 -> 1767.6538
AD61: =SUM(AD59:AD60) -> 48629 | AE61: =SUM(AE59:AE60) -> 1870.3462
AA62: SUPPORT TOP | AB62: 1502040289 | AC62: AF232042 TUBE ASSLY SUPPORT BACKREST | AD62: 3270 | AE62: =+AD62/$AE$30 -> 125.76923
AB63: 1502040236 | AC63: AF231720 TUBE ASSLY SUPPORT BACKREST | AD63: =+T11 -> 48555 | AE63: =+AD63/$AE$30 -> 1867.5
AD64: =SUM(AD62:AD63) -> 51825 | AE64: =SUM(AE62:AE63) -> 1993.2692
AA65: REAR COVER | AB65: 1502040125 | AC65: BB231370-COVER REAR RH FL | AD65: =+T14*2 -> 10938 | AE65: =+AD65/$AE$30 -> 420.69231
AB66: 1502040126 | AC66: BB231369-COVER REAR LH FL | AD66: =+AD65 -> 10938 | AE66: =+AD66/$AE$30 -> 420.69231
AD67: =SUM(AD65:AD66) -> 21876 | AE67: =SUM(AE65:AE66) -> 841.38462
AA68: Side Door | AB68: 1502040287 | AC68: AF231688 DOOR ASSLY LH | AD68: =650*26 -> 16900 | AE68: =+AD68/$AE$30 -> 650
AB69: 1502040288 | AC69: AF231689 DOOR ASSLY RH | AD69: =+AD68 -> 16900 | AE69: =+AD69/$AE$30 -> 650
AD70: =+AD68+AD69 -> 33800 | AE70: =+AD70/$AE$30 -> 1300

Sheet Sheet3
B3: 5356
B4: 5000

Sheet Sheet4
A4: Material | B4: Line
A5: 1502040194 | B5: CRADEL
A6: 1502040198 | B6: CRADEL
A7: 1502040199 | B7: CRADEL
A8: 1502040114 | B8: DASH BOARD
A9: 1502040267 | B9: DASH BOARD
A10: 1402010204 | B10: ENG BKT
A11: 1502010023 | B11: ENG BKT
A12: 1502010024 | B12: ENG BKT
A13: 1502040068 | B13: ENG BKT
A14: 1502040127 | B14: ENG BKT
A15: 1502040216 | B15: FRONT MUDGAURD
A16: 1502040217 | B16: FRONT MUDGARD GOGO
... A72: 1104040829 | B72: INNER DOOR

Sheet Sheet8
A3: Sum of Billing Qty | B3: Billling Date
A4: Line | B4: 01.05.2026 | C4: 02.05.2026 | D4: 03.05.2026 | E4: 04.05.2026 | F4: 05.05.2026 | G4: 06.05.2026 | H4: 07.05.2026 | I4: 08.05.2026 | J4: 09.05.2026 | K4: 10.05.2026 | L4: 11.05.2026 | M4: 12.05.2026 | N4: 13.05.2026 | O4: Grand Total
A5: CRADEL | C5: 288 | D5: 288 | E5: 288 | F5: 240 | G5: 192 | H5: 240 | I5: 240 | J5: 192 | L5: 268 | M5: 288 | N5: 192 | O5: 2716
A6: DASH BOARD | B6: 816 | C6: 1660 | D6: 1240 | E6: 2362 | F6: 2428 | G6: 1224 | H6: 2448 | I6: 2152 | J6: 1792 | K6: 920 | L6: 2038 | M6: 2118 | N6: 2082 | O6: 23280
A7: ENG BKT | C7: 84 | D7: 72 | F7: 84 | H7: 84 | I7: 84 | J7: -3 | L7: 324 | M7: 400 | O7: 1129
A8: FRONT MUDGARD GOGO | B8: 200 | C8: 280 | D8: 280 | E8: 375 | F8: 230 | G8: 360 | H8: 370 | I8: 430 | J8: 300 | L8: 430 | M8: 190 | N8: 131 | O8: 3576
A9: FRONT MUDGAURD | C9: 960 | D9: 1280 | E9: 1660 | F9: 2080 | G9: 2139 | H9: 1280 | I9: 2350 | J9: 2080 | L9: 2410 | M9: 2120 | N9: 2204 | O9: 20563
A10: LOGISTICS | C10: 15100 | D10: 72 | E10: 2000 | F10: 84 | H10: 2084 | I10: 2000 | J10: -3 | L10: 2000 | M10: 3600 | N10: 15270 | O10: 42207
A11: MAX UG NEW | C11: 70 | D11: 168 | E11: 60 | F11: 260 | G11: 88 | H11: 240 | I11: 70 | K11: 90 | L11: 90 | M11: 30 | N11: 200 | O11: 1366
A12: MAX UG NEW EV | B12: 206 | C12: 150 | D12: 186 | E12: 338 | F12: 280 | G12: 330 | H12: 180 | I12: 328 | J12: 380 | K12: 110 | L12: 200 | M12: 250 | N12: 280 | O12: 3218
A13: MAXIMA HD | C13: 172 | D13: 24 | E13: 138 | F13: 144 | G13: 90 | H13: 158 | I13: 124 | J13: 42 | L13: 230 | M13: 152 | N13: 144 | O13: 1418
A14: Re Side Door | C14: 960 | D14: 720 | E14: 720 | F14: 1120 | G14: 1120 | H14: 1200 | I14: 960 | J14: 960 | L14: 960 | M14: 720 | N14: 960 | O14: 10400
A15: RE STYLING | B15: 120 | C15: 501 | D15: 630 | E15: 516 | F15: 885 | G15: 822 | H15: 705 | I15: 861 | J15: 846 | K15: 120 | L15: 759 | M15: 633 | N15: 807 | O15: 8205
A16: REAR COVER | C16: 220 | D16: 330 | E16: 520 | F16: 440 | G16: 330 | H16: 330 | I16: 330 | J16: 110 | M16: 440 | N16: 330 | O16: 3380
A17: REAR MUDGAURD | C17: 5184 | D17: 5184 | E17: 4320 | F17: 5184 | G17: 3888 | H17: 4752 | I17: 4320 | J17: 2592 | K17: 2160 | L17: 4320 | M17: 3888 | N17: 3456 | O17: 49248
A18: STARTING HANDLE | C18: 1760 | D18: 720 | E18: 1080 | F18: 1350 | G18: 1620 | H18: 1350 | I18: 1080 | J18: 1079 | L18: 1530 | M18: 1380 | N18: 1080 | O18: 14029
A19: SUPPORT TOP | C19: 2376 | D19: 1688 | E19: 1200 | F19: 2160 | G19: 1688 | H19: 1248 | I19: 1688 | J19: 1200 | L19: 1344 | M19: 916 | N19: 1473 | O19: 16981
A20: DOOR INNER | D20: 931 | E20: 261 | G20: 1221 | I20: 210 | J20: 598 | M20: 510 | N20: 424 | O20: 4155
A21: FRONT MUDGAURD EV | L21: 150 | M21: 100 | N21: 100 | O21: 350
A22: Grand Total | B22: 1342 | C22: 29765 | D22: 13813 | E22: 15838 | F22: 16969 | G22: 15112 | H22: 16669 | I22: 17227 | J22: 12165 | K22: 3400 | L22: 17053 | M22: 17735 | N22: 29133 | O22: 206221

Sheet Sheet2
A1: Plant | B1: Profit Centre | C1: Dist.Channel | D1: Division | E1: Division text | F1: Billing Type | G1: Billing Type Desc | H1: Billing Doc | I1: Accounting Doc | J1: Status | K1: Excise Invoice No | L1: Billling Date | M1: Sales Order No | N1: Sales Doc.Type | O1: Sales Type Text | P1: Cust-PO-No | Q1: Cust-PO-Date | R1: Customer | S1: Customer Name | T1: ShipToParty | U1: STP-Name | V1: Customer TIN No | W1: Material | X1: Material Desc | Y1: Line | Z1: Chapter ID | AA1: Billing Qty | AB1: UoM | AC1: Sale Rate | AD1: Currency | AE1: Basic Value | AF1: Amort.Cost | AG1: Assessable Value | AH1: BED | AI1: ECS | AJ1: HECS | AK1: AED | AL1: Sub Total | AM1: VAT % | AN1: VAT | AO1: CST | AP1: AED | AQ1: TCS | AR1: Srchg on TCS | AS1: ECess on TCS | AT1: SHCess on TCS | AU1: Total Value | AV1: TlCost Rate | AW1: ToolCost Value | AX1: G/L Acoount | AY1: G/L Acoount Desc | AZ1: Gross-Wt | BA1: Net-Wt | BB1: Scrap-Wt | BC1: Old-Material | BD1: Mat-Group | BE1: Mat-Group-Name | BF1: RCIA No | BG1: RCIA Date
A2: 1115 | B2: 1115 | C2: 10 | D2: 2 | E2: Three Wheelers | F2: F2 | G2: COMMERCIAL INVOICE | H2: 1526005946 | I2: 1000006208 | L2: 04.05.2026 | M2: 5100001227 | N2: ZSCH | O2: Normal Sales | P2: 4110011319 | Q2: 18.12.2017 | R2: 5000 | S2: BAJAJ AUTO LIMITED (WALUJ) | V2: 27340676530V | W2: 1502020074 | X2: 52AZ0184 BODY ASSLY MAX Z WTH REGU. HOOD | Y2: =VLOOKUP(W2,Sheet4!$A$5:$B$71,2,0) -> MAX UG NEW | Z2: 87082900 | AA2: 10 | AB2: EA | AC2: 9397.5 | AD2: INR | AE2: 93975 | AF2: 0 | AG2: 93975 | AH2: 0 | AI2: 0 | AJ2: 0 | AK2: 0 | AL2: 93975 | AM2: 0 | AN2: 0 | AO2: 0 | AP2: 0 | AQ2: 0 | AR2: 0 | AS2: 0 | AT2: 0 | AU2: 93975 | AV2: 0 | AW2: 0 | AX2: 311000 | AY2: SALE FINISHED GOODS | AZ2: 69.5 | BA2: 69.5 | BB2: 0 | BC2: 52AZ0184 | BD2: 1509 | BE2: FG Body | BF2: 5094107222 | BG2: 05.05.2026
A3: 1115 | B3: 1115 | C3: 10 | D3: 2 | E3: Three Wheelers | F3: F2 | G3: COMMERCIAL INVOICE | H3: 1526005945 | I3: 1000006207 | L3: 04.05.2026 | M3: 5100001227 | N3: ZSCH | O3: Normal Sales | P3: 4110011319 | Q3: 18.12.2017 | R3: 5000 | S3: BAJAJ AUTO LIMITED (WALUJ) | V3: 27340676530V | W3: 1502020074 | X3: 52AZ0184 BODY ASSLY MAX Z WTH REGU. HOOD | Y3: =VLOOKUP(W3,Sheet4!$A$5:$B$71,2,0) -> MAX UG NEW | Z3: 87082900 | AA3: 10 | AB3: EA | AC3: 9397.5 | AD3: INR | AE3: 93975 | AF3: 0 | AG3: 93975 | AH3: 0 | AI3: 0 | AJ3: 0 | AK3: 0 | AL3: 93975 | AM3: 0 | AN3: 0 | AO3: 0 | AP3: 0 | AQ3: 0 | AR3: 0 | AS3: 0 | AT3: 0 | AU3: 93975 | AV3: 0 | AW3: 0 | AX3: 311000 | AY3: SALE FINISHED GOODS | AZ3: 69.5 | BA3: 69.5 | BB3: 0 | BC3: 52AZ0184 | BD3: 1509 | BE3: FG Body | BF3: 5094106025 | BG3: 05.05.2026
A4: 1115 | B4: 1115 | C4: 10 | D4: 2 | E4: Three Wheelers | F4: F2 | G4: COMMERCIAL INVOICE | H4: 1526005947 | I4: 1000006209 | L4: 04.05.2026 | M4: 5100001227 | N4: ZSCH | O4: Normal Sales | P4: 4110011319 | Q4: 18.12.2017 | R4: 5000 | S4: BAJAJ AUTO LIMITED (WALUJ) | V4: 27340676530V | W4: 1502020074 | X4: 52AZ0184 BODY ASSLY MAX Z WTH REGU. HOOD | Y4: =VLOOKUP(W4,Sheet4!$A$5:$B$71,2,0) -> MAX UG NEW | Z4: 87082900 | AA4: 10 | AB4: EA | AC4: 9397.5 | AD4: INR | AE4: 93975 | AF4: 0 | AG4: 93975 | AH4: 0 | AI4: 0 | AJ4: 0 | AK4: 0 | AL4: 93975 | AM4: 0 | AN4: 0 | AO4: 0 | AP4: 0 | AQ4: 0 | AR4: 0 | AS4: 0 | AT4: 0 | AU4: 93975 | AV4: 0 | AW4: 0 | AX4: 311000 | AY4: SALE FINISHED GOODS | AZ4: 69.5 | BA4: 69.5 | BB4: 0 | BC4: 52AZ0184 | BD4: 1509 | BE4: FG Body | BF4: 5094107378 | BG4: 05.05.2026
A5: 1115 | B5: 1115 | C5: 10 | D5: 2 | E5: Three Wheelers | F5: F2 | G5: COMMERCIAL INVOICE | H5: 1526005948 | I5: 1000006210 | L5: 04.05.2026 | M5: 5100001666 | N5: ZSCH | O5: Normal Sales | P5: 4110027035 | Q5: 03.09.2020 | R5: 5000 | S5: BAJAJ AUTO LIMITED (WALUJ) | V5: 27340676530V | W5: 1502020105 | X5: 52AU0123 BODY ASSLY 4S PETROL | Y5: =VLOOKUP(W5,Sheet4!$A$5:$B$71,2,0) -> RE STYLING | Z5: 87082900 | AA5: 15 | AB5: EA | AC5: 6570.77 | AD5: INR | AE5: 98561.55 | AF5: 0 | AG5: 98561.55 | AH5: 0 | AI5: 0 | AJ5: 0 | AK5: 0 | AL5: 98561.55 | AM5: 0 | AN5: 0 | AO5: 0 | AP5: 0 | AQ5: 0 | AR5: 0 | AS5: 0 | AT5: 0 | AU5: 98561.55 | AV5: 0 | AW5: 0 | AX5: 311000 | AY5: SALE FINISHED GOODS | AZ5: 49.75 | BA5: 49.75 | BB5: 0 | BC5: 52AU0123 | BD5: 1509 | BE5: FG Body | BF5: 5094107126 | BG5: 05.05.2026
A6: 1115 | B6: 1115 | C6: 10 | D6: 2 | E6: Three Wheelers | F6: F2 | G6: COMMERCIAL INVOICE | H6: 1526005944 | I6: 1000006206 | L6: 04.05.2026 | M6: 5100001227 | N6: ZSCH | O6: Normal Sales | P6: 4110011319 | Q6: 18.12.2017 | R6: 5000 | S6: BAJAJ AUTO LIMITED (WALUJ) | V6: 27340676530V | W6: 1502020074 | X6: 52AZ0184 BODY ASSLY MAX Z WTH REGU. HOOD | Y6: =VLOOKUP(W6,Sheet4!$A$5:$B$71,2,0) -> MAX UG NEW | Z6: 87082900 | AA6: 10 | AB6: EA | AC6: 9397.5 | AD6: INR | AE6: 93975 | AF6: 0 | AG6: 93975 | AH6: 0 | AI6: 0 | AJ6: 0 | AK6: 0 | AL6: 93975 | AM6: 0 | AN6: 0 | AO6: 0 | AP6: 0 | AQ6: 0 | AR6: 0 | AS6: 0 | AT6: 0 | AU6: 93975 | AV6: 0 | AW6: 0 | AX6: 311000 | AY6: SALE FINISHED GOODS | AZ6: 69.5 | BA6: 69.5 | BB6: 0 | BC6: 52AZ0184 | BD6: 1509 | BE6: FG Body | BF6: 5094107376 | BG6: 05.05.2026
A7: 1115 | B7: 1115 | C7: 10 | D7: 2 | E7: Three Wheelers | F7: F2 | G7: COMMERCIAL INVOICE | H7: 1526005942 | I7: 1000006204 | L7: 04.05.2026 | M7: 5100001928 | N7: ZSCH | O7: Normal Sales | P7: 4110057393 | Q7: 28.11.2024 | R7: 5000 | S7: BAJAJ AUTO LIMITED (WALUJ) | V7: 27340676530V | W7: 1502020122 | X7: 52AH0692 BODY ASSLY MAXIMA Z EV | Y7: =VLOOKUP(W7,Sheet4!$A$5:$B$71,2,0) -> MAX UG NEW EV | Z7: 87082900 | AA7: 10 | AB7: EA | AC7: 9566.51 | AD7: INR | AE7: 95665.1 | AF7: 0 | AG7: 95665.1 | AH7: 0 | AI7: 0 | AJ7: 0 | AK7: 0 | AL7: 95665.1 | AM7: 0 | AN7: 0 | AO7: 0 | AP7: 0 | AQ7: 0 | AR7: 0 | AS7: 0 | AT7: 0 | AU7: 95665.1 | AV7: 0 | AW7: 0 | AX7: 311000 | AY7: SALE FINISHED GOODS | AZ7: 0 | BA7: 61 | BB7: -61 | BC7: 52AH0692 | BD7: 1509 | BE7: FG Body | BF7: 5094104692 | BG7: 04.05.2026
A8: 1115 | B8: 1115 | C8: 10 | D8: 2 | E8: Three Wheelers | F8: F2 | G8: COMMERCIAL INVOICE | H8: 1526005941 | I8: 1000006203 | L8: 04.05.2026 | M8: 5100001636 | N8: ZSCH | O8: Normal Sales | P8: 4110026445 | Q8: 23.07.2020 | R8: 5000 | S8: BAJAJ AUTO LIMITED (WALUJ) | V8: 27340676530V | W8: 1502020104 | X8: AA231532 BODY ASSLY PETROL | Y8: =VLOOKUP(W8,Sheet4!$A$5:$B$71,2,0) -> RE STYLING | Z8: 87082900 | AA8: 6 | AB8: EA | AC8: 6585.55 | AD8: INR | AE8: 39513.3 | AF8: 0 | AG8: 39513.3 | AH8: 0 | AI8: 0 | AJ8: 0 | AK8: 0 | AL8: 39513.3 | AM8: 0 | AN8: 0 | AO8: 0 | AP8: 0 | AQ8: 0 | AR8: 0 | AS8: 0 | AT8: 0 | AU8: 39513.3 | AV8: 0 | AW8: 0 | AX8: 311000 | AY8: SALE FINISHED GOODS | AZ8: 49.75 | BA8: 49.75 | BB8: 0 | BC8: AA231532 | BD8: 1509 | BE8: FG Body | BF8: 5094107251 | BG8: 05.05.2026
A9: 1115 | B9: 1115 | C9: 10 | D9: 2 | E9: Three Wheelers | F9: F2 | G9: COMMERCIAL INVOICE | H9: 1526005940 | I9: 1000006202 | L9: 04.05.2026 | M9: 5100001407 | N9: ZSCH | O9: Normal Sales | P9: 4110019623 | Q9: 06.05.2019 | R9: 5000 | S9: BAJAJ AUTO LIMITED (WALUJ) | V9: 27340676530V | W9: 1502040216 | X9: AA161289_ ASSEMBLY MUDGUARD FRONT | Y9: =VLOOKUP(W9,Sheet4!$A$5:$B$71,2,0) -> FRONT MUDGAURD | Z9: 87082900 | AA9: 960 | AB9: EA | AC9: 174.11 | AD9: INR | AE9: 167145.6 | AF9: 0 | AG9: 167145.6 | AH9: 0 | AI9: 0 | AJ9: 0 | AK9: 0 | AL9: 167145.6 | AM9: 0 | AN9: 0 | AO9: 0 | AP9: 0 | AQ9: 0 | AR9: 0 | AS9: 0 | AT9: 0 | AU9: 167145.6 | AV9: 0 | AW9: 0 | AX9: 311000 | AY9: SALE FINISHED GOODS | AZ9: 2.573 | BA9: 1.491 | BB9: 1.082 | BC9: AA161289 | BD9: 1511 | BE9: FG Loose 3WH | BF9: 5094107252 | BG9: 05.05.2026
A10: 1115 | B10: 1115 | C10: 10 | D10: 2 | E10: Three Wheelers | F10: F2 | G10: COMMERCIAL INVOICE | H10: 1526005939 | I10: 1000006201 | L10: 04.05.2026 | M10: 5100001924 | N10: ZSCH | O10: Normal Sales | P10: 4110055642 | Q10: 09.09.2024 | R10: 5000 | S10: BAJAJ AUTO LIMITED (WALUJ) | V10: 27340676530V | W10: 1502040314 | X10: 52BA0835 RE DOOR ASSLY LH YELLOW | Y10: =VLOOKUP(W10,Sheet4!$A$5:$B$71,2,0) -> Re Side Door | Z10: 87082900 | AA10: 120 | AB10: EA | AC10: 504.46 | AD10: INR | AE10: 60535.2 | AF10: 0 | AG10: 60535.2 | AH10: 0 | AI10: 0 | AJ10: 0 | AK10: 0 | AL10: 60535.2 | AM10: 0 | AN10: 0 | AO10: 0 | AP10: 0 | AQ10: 0 | AR10: 0 | AS10: 0 | AT10: 0 | AU10: 60535.2 | AV10: 0 | AW10: 0 | AX10: 311000 | AY10: SALE FINISHED GOODS | AZ10: 2.27 | BA10: 2.27 | BB10: 0 | BC10: 52BA0835 | BD10: 1511 | BE10: FG Loose 3WH | BF10: 5094113616 | BG10: 05.05.2026
A11: 1115 | B11: 1115 | C11: 10 | D11: 2 | E11: Three Wheelers | F11: F2 | G11: COMMERCIAL INVOICE | H11: 1526005949 | I11: 1000006211 | L11: 04.05.2026 | M11: 5100001666 | N11: ZSCH | O11: Normal Sales | P11: 4110027035 | Q11: 03.09.2020 | R11: 5000 | S11: BAJAJ AUTO LIMITED (WALUJ) | V11: 27340676530V | W11: 1502020105 | X11: 52AU0123 BODY ASSLY 4S PETROL | Y11: =VLOOKUP(W11,Sheet4!$A$5:$B$71,2,0) -> RE STYLING | Z11: 87082900 | AA11: 15 | AB11: EA | AC11: 6570.77 | AD11: INR | AE11: 98561.55 | AF11: 0 | AG11: 98561.55 | AH11: 0 | AI11: 0 | AJ11: 0 | AK11: 0 | AL11: 98561.55 | AM11: 0 | AN11: 0 | AO11: 0 | AP11: 0 | AQ11: 0 | AR11: 0 | AS11: 0 | AT11: 0 | AU11: 98561.55 | AV11: 0 | AW11: 0 | AX11: 311000 | AY11: SALE FINISHED GOODS | AZ11: 49.75 | BA11: 49.75 | BB11: 0 | BC11: 52AU0123 | BD11: 1509 | BE11: FG Body | BF11: 5094107045 | BG11: 05.05.2026
A12: 1115 | B12: 1115 | C12: 10 | D12: 2 | E12: Three Wheelers | F12: F2 | G12: COMMERCIAL INVOICE | H12: 1526005950 | I12: 1000006212 | L12: 04.05.2026 | M12: 5100001666 | N12: ZSCH | O12: Normal Sales | P12: 4110027035 | Q12: 03.09.2020 | R12: 5000 | S12: BAJAJ AUTO LIMITED (WALUJ) | V12: 27340676530V | W12: 1502020105 | X12: 52AU0123 BODY ASSLY 4S PETROL | Y12: =VLOOKUP(W12,Sheet4!$A$5:$B$71,2,0) -> RE STYLING | Z12: 87082900 | AA12: 15 | AB12: EA | AC12: 6570.77 | AD12: INR | AE12: 98561.55 | AF12: 0 | AG12: 98561.55 | AH12: 0 | AI12: 0 | AJ12: 0 | AK12: 0 | AL12: 98561.55 | AM12: 0 | AN12: 0 | AO12: 0 | AP12: 0 | AQ12: 0 | AR12: 0 | AS12: 0 | AT12: 0 | AU12: 98561.55 | AV12: 0 | AW12: 0 | AX12: 311000 | AY12: SALE FINISHED GOODS | AZ12: 49.75 | BA12: 49.75 | BB12: 0 | BC12: 52AU0123 | BD12: 1509 | BE12: FG Body | BF12: 5094107035 | BG12: 05.05.2026
A13: 1115 | B13: 1115 | C13: 10 | D13: 2 | E13: Three Wheelers | F13: F2 | G13: COMMERCIAL INVOICE | H13: 1526005951 | I13: 1000006213 | L13: 04.05.2026 | M13: 5100001666 | N13: ZSCH | O13: Normal Sales | P13: 4110027035 | Q13: 03.09.2020 | R13: 5000 | S13: BAJAJ AUTO LIMITED (WALUJ) | V13: 27340676530V | W13: 1502020105 | X13: 52AU0123 BODY ASSLY 4S PETROL | Y13: =VLOOKUP(W13,Sheet4!$A$5:$B$71,2,0) -> RE STYLING | Z13: 87082900 | AA13: 15 | AB13: EA | AC13: 6570.77 | AD13: INR | AE13: 98561.55 | AF13: 0 | AG13: 98561.55 | AH13: 0 | AI13: 0 | AJ13: 0 | AK13: 0 | AL13: 98561.55 | AM13: 0 | AN13: 0 | AO13: 0 | AP13: 0 | AQ13: 0 | AR13: 0 | AS13: 0 | AT13: 0 | AU13: 98561.55 | AV13: 0 | AW13: 0 | AX13: 311000 | AY13: SALE FINISHED GOODS | AZ13: 49.75 | BA13: 49.75 | BB13: 0 | BC13: 52AU0123 | BD13: 1509 | BE13: FG Body | BF13: 5094107203 | BG13: 05.05.2026
... A87: 1115 | B87: 1115 | C87: 10 | D87: 2 | E87: Three Wheelers | F87: F2 | G87: COMMERCIAL INVOICE | H87: 1526005856 | I87: 1000006122 | L87: 04.05.2026 | M87: 5100001100 | N87: ZSCH | O87: Normal Sales | P87: 4110004652 | Q87: 01.07.2017 | R87: 5000 | S87: BAJAJ AUTO LIMITED (WALUJ) | V87: 27340676530V | W87: 1502040164 | X87: 52BB0125 REAR COVER ASSLY GREEN LH | Y87: =VLOOKUP(W87,Sheet4!$A$5:$B$71,2,0) -> REAR COVER | Z87: 87082900 | AA87: 55 | AB87: EA | AC87: 160.52 | AD87: INR | AE87: 8828.6 | AF87: 0 | AG87: 8828.6 | AH87: 0 | AI87: 0 | AJ87: 0 | AK87: 0 | AL87: 8828.6 | AM87: 0 | AN87: 0 | AO87: 0 | AP87: 0 | AQ87: 0 | AR87: 0 | AS87: 0 | AT87: 0 | AU87: 8828.6 | AV87: 0 | AW87: 0 | AX87: 311000 | AY87: SALE FINISHED GOODS | AZ87: 1.166 | BA87: 1.166 | BB87: 0 | BC87: 52BB0125 | BD87: 1511 | BE87: FG Loose 3WH | BF87: 5094094589 | BG87: 04.05.2026
A88: 1115 | B88: 1115 | C88: 10 | D88: 2 | E88: Three Wheelers | F88: F2 | G88: COMMERCIAL INVOICE | H88: 1526005855 | I88: 1000006121 | L88: 04.05.2026 | M88: 5100001100 | N88: ZSCH | O88: Normal Sales | P88: 4110004652 | Q88: 01.07.2017 | R88: 5000 | S88: BAJAJ AUTO LIMITED (WALUJ) | V88: 27340676530V | W88: 1502040164 | X88: 52BB0125 REAR COVER ASSLY GREEN LH | Y88: =VLOOKUP(W88,Sheet4!$A$5:$B$71,2,0) -> REAR COVER | Z88: 87082900 | AA88: 80 | AB88: EA | AC88: 160.52 | AD88: INR | AE88: 12841.6 | AF88: 0 | AG88: 12841.6 | AH88: 0 | AI88: 0 | AJ88: 0 | AK88: 0 | AL88: 12841.6 | AM88: 0 | AN88: 0 | AO88: 0 | AP88: 0 | AQ88: 0 | AR88: 0 | AS88: 0 | AT88: 0 | AU88: 12841.6 | AV88: 0 | AW88: 0 | AX88: 311000 | AY88: SALE FINISHED GOODS | AZ88: 1.166 | BA88: 1.166 | BB88: 0 | BC88: 52BB0125 | BD88: 1511 | BE88: FG Loose 3WH | BF88: PENDING | BG88: Pending
A89: 1115 | B89: 1115 | C89: 10 | D89: 2 | E89: Three Wheelers | F89: F2 | G89: COMMERCIAL INVOICE | H89: 1526005854 | I89: 1000006118 | L89: 04.05.2026 | M89: 5100001636 | N89: ZSCH | O89: Normal Sales | P89: 4110026445 | Q89: 23.07.2020 | R89: 5000 | S89: BAJAJ AUTO LIMITED (WALUJ) | V89: 27340676530V | W89: 1502020101 | X89: 52BA0852 ASSLY BODY COMPACT DIESEL | Y89: =VLOOKUP(W89,Sheet4!$A$5:$B$71,2,0) -> RE STYLING | Z89: 87082900 | AA89: 15 | AB89: EA | AC89: 6240.88 | AD89: INR | AE89: 93613.2 | AF89: 0 | AG89: 93613.2 | AH89: 0 | AI89: 0 | AJ89: 0 | AK89: 0 | AL89: 93613.2 | AM89: 0 | AN89: 0 | AO89: 0 | AP89: 0 | AQ89: 0 | AR89: 0 | AS89: 0 | AT89: 0 | AU89: 93613.2 | AV89: 0 | AW89: 0 | AX89: 311000 | AY89: SALE FINISHED GOODS | AZ89: 58 | BA89: 58 | BB89: 0 | BC89: 52BA0852 | BD89: 1509 | BE89: FG Body | BF89: 5094107388 | BG89: 05.05.2026
A90: 1115 | B90: 1115 | C90: 10 | D90: 2 | E90: Three Wheelers | F90: F2 | G90: COMMERCIAL INVOICE | H90: 1526005853 | I90: 1000006117 | L90: 04.05.2026 | M90: 5100001636 | N90: ZSCH | O90: Normal Sales | P90: 4110026445 | Q90: 23.07.2020 | R90: 5000 | S90: BAJAJ AUTO LIMITED (WALUJ) | V90: 27340676530V | W90: 1502020101 | X90: 52BA0852 ASSLY BODY COMPACT DIESEL | Y90: =VLOOKUP(W90,Sheet4!$A$5:$B$71,2,0) -> RE STYLING | Z90: 87082900 | AA90: 15 | AB90: EA | AC90: 6240.88 | AD90: INR | AE90: 93613.2 | AF90: 0 | AG90: 93613.2 | AH90: 0 | AI90: 0 | AJ90: 0 | AK90: 0 | AL90: 93613.2 | AM90: 0 | AN90: 0 | AO90: 0 | AP90: 0 | AQ90: 0 | AR90: 0 | AS90: 0 | AT90: 0 | AU90: 93613.2 | AV90: 0 | AW90: 0 | AX90: 311000 | AY90: SALE FINISHED GOODS | AZ90: 58 | BA90: 58 | BB90: 0 | BC90: 52BA0852 | BD90: 1509 | BE90: FG Body | BF90: 5094107316 | BG90: 05.05.2026
A91: 1115 | B91: 1115 | C91: 10 | D91: 2 | E91: Three Wheelers | F91: F2 | G91: COMMERCIAL INVOICE | H91: 1526005852 | I91: 1000006116 | L91: 04.05.2026 | M91: 5100001666 | N91: ZSCH | O91: Normal Sales | P91: 4110027035 | Q91: 03.09.2020 | R91: 5000 | S91: BAJAJ AUTO LIMITED (WALUJ) | V91: 27340676530V | W91: 1502020105 | X91: 52AU0123 BODY ASSLY 4S PETROL | Y91: =VLOOKUP(W91,Sheet4!$A$5:$B$71,2,0) -> RE STYLING | Z91: 87082900 | AA91: 15 | AB91: EA | AC91: 6570.77 | AD91: INR | AE91: 98561.55 | AF91: 0 | AG91: 98561.55 | AH91: 0 | AI91: 0 | AJ91: 0 | AK91: 0 | AL91: 98561.55 | AM91: 0 | AN91: 0 | AO91: 0 | AP91: 0 | AQ91: 0 | AR91: 0 | AS91: 0 | AT91: 0 | AU91: 98561.55 | AV91: 0 | AW91: 0 | AX91: 311000 | AY91: SALE FINISHED GOODS | AZ91: 49.75 | BA91: 49.75 | BB91: 0 | BC91: 52AU0123 | BD91: 1509 | BE91: FG Body | BF91: 5094098565 | BG91: 04.05.2026
A92: 1115 | B92: 1115 | C92: 10 | D92: 2 | E92: Three Wheelers | F92: F2 | G92: COMMERCIAL INVOICE | H92: 1526005851 | I92: 1000006115 | L92: 04.05.2026 | M92: 5100001899 | N92: ZSCH | O92: Normal Sales | P92: 4110041854 | Q92: 03.03.2023 | R92: 5000 | S92: BAJAJ AUTO LIMITED (WALUJ) | V92: 27340676530V | W92: 1502040267 | X92: AZ111331_06 SUPPORT ASSLY DASHBOARD | Y92: =VLOOKUP(W92,Sheet4!$A$5:$B$71,2,0) -> DASH BOARD | Z92: 87082900 | AA92: 416 | AB92: EA | AC92: 290.9 | AD92: INR | AE92: 121014.4 | AF92: 0 | AG92: 121014.4 | AH92: 0 | AI92: 0 | AJ92: 0 | AK92: 0 | AL92: 121014.4 | AM92: 0 | AN92: 0 | AO92: 0 | AP92: 0 | AQ92: 0 | AR92: 0 | AS92: 0 | AT92: 0 | AU92: 121014.4 | AV92: 0 | AW92: 0 | AX92: 311000 | AY92: SALE FINISHED GOODS | AZ92: 4.5 | BA92: 4.5 | BB92: 0 | BC92: AZ111331 | BD92: 1511 | BE92: FG Loose 3WH | BF92: 5094127541 | BG92: 05.05.2026
A93: 1115 | B93: 1115 | C93: 10 | D93: 2 | E93: Three Wheelers | F93: F2 | G93: COMMERCIAL INVOICE | H93: 1526005850 | I93: 1000006111 | L93: 04.05.2026 | M93: 5100001666 | N93: ZSCH | O93: Normal Sales | P93: 4110027035 | Q93: 03.09.2020 | R93: 5000 | S93: BAJAJ AUTO LIMITED (WALUJ) | V93: 27340676530V | W93: 1502020105 | X93: 52AU0123 BODY ASSLY 4S PETROL | Y93: =VLOOKUP(W93,Sheet4!$A$5:$B$71,2,0) -> RE STYLING | Z93: 87082900 | AA93: 15 | AB93: EA | AC93: 6570.77 | AD93: INR | AE93: 98561.55 | AF93: 0 | AG93: 98561.55 | AH93: 0 | AI93: 0 | AJ93: 0 | AK93: 0 | AL93: 98561.55 | AM93: 0 | AN93: 0 | AO93: 0 | AP93: 0 | AQ93: 0 | AR93: 0 | AS93: 0 | AT93: 0 | AU93: 98561.55 | AV93: 0 | AW93: 0 | AX93: 311000 | AY93: SALE FINISHED GOODS | AZ93: 49.75 | BA93: 49.75 | BB93: 0 | BC93: 52AU0123 | BD93: 1509 | BE93: FG Body | BF93: 5094098393 | BG93: 04.05.2026
A94: 1115 | B94: 1115 | C94: 10 | D94: 2 | E94: Three Wheelers | F94: F2 | G94: COMMERCIAL INVOICE | H94: 1526005849 | I94: 1000006110 | L94: 04.05.2026 | M94: 5100001928 | N94: ZSCH | O94: Normal Sales | P94: 4110057393 | Q94: 28.11.2024 | R94: 5000 | S94: BAJAJ AUTO LIMITED (WALUJ) | V94: 27340676530V | W94: 1502020122 | X94: 52AH0692 BODY ASSLY MAXIMA Z EV | Y94: =VLOOKUP(W94,Sheet4!$A$5:$B$71,2,0) -> MAX UG NEW EV | Z94: 87082900 | AA94: 10 | AB94: EA | AC94: 9566.51 | AD94: INR | AE94: 95665.1 | AF94: 0 | AG94: 95665.1 | AH94: 0 | AI94: 0 | AJ94: 0 | AK94: 0 | AL94: 95665.1 | AM94: 0 | AN94: 0 | AO94: 0 | AP94: 0 | AQ94: 0 | AR94: 0 | AS94: 0 | AT94: 0 | AU94: 95665.1 | AV94: 0 | AW94: 0 | AX94: 311000 | AY94: SALE FINISHED GOODS | AZ94: 0 | BA94: 61 | BB94: -61 | BC94: 52AH0692 | BD94: 1509 | BE94: FG Body | BF94: 5094094564 | BG94: 04.05.2026
A95: 1115 | B95: 1115 | C95: 10 | D95: 2 | E95: Three Wheelers | F95: F2 | G95: COMMERCIAL INVOICE | H95: 1526005848 | I95: 1000006109 | L95: 04.05.2026 | M95: 5100001928 | N95: ZSCH | O95: Normal Sales | P95: 4110057393 | Q95: 28.11.2024 | R95: 5000 | S95: BAJAJ AUTO LIMITED (WALUJ) | V95: 27340676530V | W95: 1502020122 | X95: 52AH0692 BODY ASSLY MAXIMA Z EV | Y95: =VLOOKUP(W95,Sheet4!$A$5:$B$71,2,0) -> MAX UG NEW EV | Z95: 87082900 | AA95: 10 | AB95: EA | AC95: 9566.51 | AD95: INR | AE95: 95665.1 | AF95: 0 | AG95: 95665.1 | AH95: 0 | AI95: 0 | AJ95: 0 | AK95: 0 | AL95: 95665.1 | AM95: 0 | AN95: 0 | AO95: 0 | AP95: 0 | AQ95: 0 | AR95: 0 | AS95: 0 | AT95: 0 | AU95: 95665.1 | AV95: 0 | AW95: 0 | AX95: 311000 | AY95: SALE FINISHED GOODS | AZ95: 0 | BA95: 61 | BB95: -61 | BC95: 52AH0692 | BD95: 1509 | BE95: FG Body | BF95: 5094096326 | BG95: 04.05.2026
A96: 1115 | B96: 1115 | C96: 10 | D96: 2 | E96: Three Wheelers | F96: F2 | G96: COMMERCIAL INVOICE | H96: 1526005846 | I96: 1000006107 | L96: 04.05.2026 | M96: 5100001666 | N96: ZSCH | O96: Normal Sales | P96: 4110027035 | Q96: 03.09.2020 | R96: 5000 | S96: BAJAJ AUTO LIMITED (WALUJ) | V96: 27340676530V | W96: 1502020105 | X96: 52AU0123 BODY ASSLY 4S PETROL | Y96: =VLOOKUP(W96,Sheet4!$A$5:$B$71,2,0) -> RE STYLING | Z96: 87082900 | AA96: 15 | AB96: EA | AC96: 6570.77 | AD96: INR | AE96: 98561.55 | AF96: 0 | AG96: 98561.55 | AH96: 0 | AI96: 0 | AJ96: 0 | AK96: 0 | AL96: 98561.55 | AM96: 0 | AN96: 0 | AO96: 0 | AP96: 0 | AQ96: 0 | AR96: 0 | AS96: 0 | AT96: 0 | AU96: 98561.55 | AV96: 0 | AW96: 0 | AX96: 311000 | AY96: SALE FINISHED GOODS | AZ96: 49.75 | BA96: 49.75 | BB96: 0 | BC96: 52AU0123 | BD96: 1509 | BE96: FG Body | BF96: 5094098122 | BG96: 04.05.2026
A97: 1115 | B97: 1115 | C97: 10 | D97: 2 | E97: Three Wheelers | F97: F2 | G97: COMMERCIAL INVOICE | H97: 1526005845 | I97: 1000006106 | L97: 04.05.2026 | M97: 5100001666 | N97: ZSCH | O97: Normal Sales | P97: 4110027035 | Q97: 03.09.2020 | R97: 5000 | S97: BAJAJ AUTO LIMITED (WALUJ) | V97: 27340676530V | W97: 1502020105 | X97: 52AU0123 BODY ASSLY 4S PETROL | Y97: =VLOOKUP(W97,Sheet4!$A$5:$B$71,2,0) -> RE STYLING | Z97: 87082900 | AA97: 15 | AB97: EA | AC97: 6570.77 | AD97: INR | AE97: 98561.55 | AF97: 0 | AG97: 98561.55 | AH97: 0 | AI97: 0 | AJ97: 0 | AK97: 0 | AL97: 98561.55 | AM97: 0 | AN97: 0 | AO97: 0 | AP97: 0 | AQ97: 0 | AR97: 0 | AS97: 0 | AT97: 0 | AU97: 98561.55 | AV97: 0 | AW97: 0 | AX97: 311000 | AY97: SALE FINISHED GOODS | AZ97: 49.75 | BA97: 49.75 | BB97: 0 | BC97: 52AU0123 | BD97: 1509 | BE97: FG Body | BF97: 5094097830 | BG97: 04.05.2026
A98: 1115 | B98: 1115 | C98: 10 | D98: 2 | E98: Three Wheelers | F98: F2 | G98: COMMERCIAL INVOICE | H98: 1526005844 | I98: 1000006105 | L98: 04.05.2026 | M98: 5100001666 | N98: ZSCH | O98: Normal Sales | P98: 4110027035 | Q98: 03.09.2020 | R98: 5000 | S98: BAJAJ AUTO LIMITED (WALUJ) | V98: 27340676530V | W98: 1502020105 | X98: 52AU0123 BODY ASSLY 4S PETROL | Y98: =VLOOKUP(W98,Sheet4!$A$5:$B$71,2,0) -> RE STYLING | Z98: 87082900 | AA98: 15 | AB98: EA | AC98: 6570.77 | AD98: INR | AE98: 98561.55 | AF98: 0 | AG98: 98561.55 | AH98: 0 | AI98: 0 | AJ98: 0 | AK98: 0 | AL98: 98561.55 | AM98: 0 | AN98: 0 | AO98: 0 | AP98: 0 | AQ98: 0 | AR98: 0 | AS98: 0 | AT98: 0 | AU98: 98561.55 | AV98: 0 | AW98: 0 | AX98: 311000 | AY98: SALE FINISHED GOODS | AZ98: 49.75 | BA98: 49.75 | BB98: 0 | BC98: 52AU0123 | BD98: 1509 | BE98: FG Body | BF98: 5094097995 | BG98: 04.05.2026
A99: 1115 | B99: 1115 | C99: 10 | D99: 2 | E99: Three Wheelers | F99: F2 | G99: COMMERCIAL INVOICE | H99: 1526005843 | I99: 1000006098 | L99: 04.05.2026 | M99: 5100001928 | N99: ZSCH | O99: Normal Sales | P99: 4110057393 | Q99: 28.11.2024 | R99: 5000 | S99: BAJAJ AUTO LIMITED (WALUJ) | V99: 27340676530V | W99: 1502020122 | X99: 52AH0692 BODY ASSLY MAXIMA Z EV | Y99: =VLOOKUP(W99,Sheet4!$A$5:$B$71,2,0) -> MAX UG NEW EV | Z99: 87082900 | AA99: 10 | AB99: EA | AC99: 9566.51 | AD99: INR | AE99: 95665.1 | AF99: 0 | AG99: 95665.1 | AH99: 0 | AI99: 0 | AJ99: 0 | AK99: 0 | AL99: 95665.1 | AM99: 0 | AN99: 0 | AO99: 0 | AP99: 0 | AQ99: 0 | AR99: 0 | AS99: 0 | AT99: 0 | AU99: 95665.1 | AV99: 0 | AW99: 0 | AX99: 311000 | AY99: SALE FINISHED GOODS | AZ99: 0 | BA99: 61 | BB99: -61 | BC99: 52AH0692 | BD99: 1509 | BE99: FG Body | BF99: 5094092904 | BG99: 04.05.2026
A100: 1115 | B100: 1115 | C100: 10 | D100: 2 | E100: Three Wheelers | F100: F2 | G100: COMMERCIAL INVOICE | H100: 1526005842 | I100: 1000006097 | L100: 04.05.2026 | M100: 5100001603 | N100: ZSCH | O100: Normal Sales | P100: 4110025468 | Q100: 19.03.2020 | R100: 5000 | S100: BAJAJ AUTO LIMITED (WALUJ) | V100: 27340676530V | W100: 1502020102 | X100: 52BB0638 BODY ASSLY MAXIMA X WIDE | Y100: =VLOOKUP(W100,Sheet4!$A$5:$B$71,2,0) -> MAXIMA HD | Z100: 87082900 | AA100: 8 | AB100: EA | AC100: 8593.51 | AD100: INR | AE100: 68748.08 | AF100: 0 | AG100: 68748.08 | AH100: 0 | AI100: 0 | AJ100: 0 | AK100: 0 | AL100: 68748.08 | AM100: 0 | AN100: 0 | AO100: 0 | AP100: 0 | AQ100: 0 | AR100: 0 | AS100: 0 | AT100: 0 | AU100: 68748.08 | AV100: 0 | AW100: 0 | AX100: 311000 | AY100: SALE FINISHED GOODS | AZ100: 93.34 | BA100: 75.43 | BB100: 17.91 | BC100: 52BB0638 | BD100: 1509 | BE100: FG Body | BF100: 5094101747 | BG100: 04.05.2026
... A118: 1115 | B118: 1115 | C118: 10 | D118: 2 | E118: Three Wheelers | F118: F2 | G118: COMMERCIAL INVOICE | H118: 1526005820 | I118: 1000006076 | L118: 04.05.2026 | M118: 5100001928 | N118: ZSCH | O118: Normal Sales | P118: 4110057393 | Q118: 28.11.2024 | R118: 5000 | S118: BAJAJ AUTO LIMITED (WALUJ) | V118: 27340676530V | W118: 1502020122 | X118: 52AH0692 BODY ASSLY MAXIMA Z EV | Y118: =VLOOKUP(W118,Sheet4!$A$5:$B$71,2,0) -> MAX UG NEW EV | Z118: 87082900 | AA118: 10 | AB118: EA | AC118: 9566.51 | AD118: INR | AE118: 95665.1 | AF118: 0 | AG118: 95665.1 | AH118: 0 | AI118: 0 | AJ118: 0 | AK118: 0 | AL118: 95665.1 | AM118: 0 | AN118: 0 | AO118: 0 | AP118: 0 | AQ118: 0 | AR118: 0 | AS118: 0 | AT118: 0 | AU118: 95665.1 | AV118: 0 | AW118: 0 | AX118: 311000 | AY118: SALE FINISHED GOODS | AZ118: 0 | BA118: 61 | BB118: -61 | BC118: 52AH0692 | BD118: 1509 | BE118: FG Body | BF118: 5094090904 | BG118: 04.05.2026
A119: 1115 | B119: 1115 | C119: 10 | D119: 2 | E119: Three Wheelers | F119: F2 | G119: COMMERCIAL INVOICE | H119: 1526005818 | I119: 1000006075 | L119: 04.05.2026 | M119: 5100001899 | N119: ZSCH | O119: Normal Sales | P119: 4110041854 | Q119: 03.03.2023 | R119: 5000 | S119: BAJAJ AUTO LIMITED (WALUJ) | V119: 27340676530V | W119: 1502040267 | X119: AZ111331_06 SUPPORT ASSLY DASHBOARD | Y119: =VLOOKUP(W119,Sheet4!$A$5:$B$71,2,0) -> DASH BOARD | Z119: 87082900 | AA119: 416 | AB119: EA | AC119: 290.9 | AD119: INR | AE119: 121014.4 | AF119: 0 | AG119: 121014.4 | AH119: 0 | AI119: 0 | AJ119: 0 | AK119: 0 | AL119: 121014.4 | AM119: 0 | AN119: 0 | AO119: 0 | AP119: 0 | AQ119: 0 | AR119: 0 | AS119: 0 | AT119: 0 | AU119: 121014.4 | AV119: 0 | AW119: 0 | AX119: 311000 | AY119: SALE FINISHED GOODS | AZ119: 4.5 | BA119: 4.5 | BB119: 0 | BC119: AZ111331 | BD119: 1511 | BE119: FG Loose 3WH | BF119: PENDING | BG119: Pending
A120: 1115 | B120: 1115 | C120: 10 | D120: 2 | E120: Three Wheelers | F120: F2 | G120: COMMERCIAL INVOICE | H120: 1526005817 | I120: 1000006074 | L120: 04.05.2026 | M120: 5100001899 | N120: ZSCH | O120: Normal Sales | P120: 4110041854 | Q120: 03.03.2023 | R120: 5000 | S120: BAJAJ AUTO LIMITED (WALUJ) | V120: 27340676530V | W120: 1502040267 | X120: AZ111331_06 SUPPORT ASSLY DASHBOARD | Y120: =VLOOKUP(W120,Sheet4!$A$5:$B$71,2,0) -> DASH BOARD | Z120: 87082900 | AA120: 416 | AB120: EA | AC120: 290.9 | AD120: INR | AE120: 121014.4 | AF120: 0 | AG120: 121014.4 | AH120: 0 | AI120: 0 | AJ120: 0 | AK120: 0 | AL120: 121014.4 | AM120: 0 | AN120: 0 | AO120: 0 | AP120: 0 | AQ120: 0 | AR120: 0 | AS120: 0 | AT120: 0 | AU120: 121014.4 | AV120: 0 | AW120: 0 | AX120: 311000 | AY120: SALE FINISHED GOODS | AZ120: 4.5 | BA120: 4.5 | BB120: 0 | BC120: AZ111331 | BD120: 1511 | BE120: FG Loose 3WH | BF120: 5094097397 | BG120: 04.05.2026
A121: 1115 | B121: 1115 | C121: 10 | D121: 2 | E121: Three Wheelers | F121: F2 | G121: COMMERCIAL INVOICE | H121: 1526005864 | I121: 1000006128 | L121: 04.05.2026 | M121: 5100001903 | N121: ZSCH | O121: Normal Sales | P121: 4110043907 | Q121: 03.07.2023 | R121: 5000 | S121: BAJAJ AUTO LIMITED (WALUJ) | V121: 27340676530V | W121: 1502040216 | X121: AA161289- ASSEMBLY MUDGUARD FRONT | Y121: =VLOOKUP(W121,Sheet4!$A$5:$B$71,2,0) -> FRONT MUDGAURD | Z121: 87082900 | AA121: 300 | AB121: EA | AC121: 174.11 | AD121: INR | AE121: 52233 | AF121: 0 | AG121: 52233 | AH121: 0 | AI121: 0 | AJ121: 0 | AK121: 0 | AL121: 52233 | AM121: 0 | AN121: 0 | AO121: 0 | AP121: 0 | AQ121: 0 | AR121: 0 | AS121: 0 | AT121: 0 | AU121: 52233 | AV121: 0 | AW121: 0 | AX121: 311000 | AY121: SALE FINISHED GOODS | AZ121: 2.573 | BA121: 1.491 | BB121: 1.082 | BC121: AA161289 | BD121: 1511 | BE121: FG Loose 3WH | BF121: 5094101162 | BG121: 04.05.2026
A122: 1115 | B122: 1115 | C122: 10 | D122: 2 | E122: Three Wheelers | F122: F2 | G122: COMMERCIAL INVOICE | H122: 1526005911 | I122: 1000006174 | L122: 04.05.2026 | M122: 5100001636 | N122: ZSCH | O122: Normal Sales | P122: 4110026445 | Q122: 23.07.2020 | R122: 5000 | S122: BAJAJ AUTO LIMITED (WALUJ) | V122: 27340676530V | W122: 1502020101 | X122: 52BA0852 ASSLY BODY COMPACT DIESEL | Y122: =VLOOKUP(W122,Sheet4!$A$5:$B$71,2,0) -> RE STYLING | Z122: 87082900 | AA122: 15 | AB122: EA | AC122: 6240.88 | AD122: INR | AE122: 93613.2 | AF122: 0 | AG122: 93613.2 | AH122: 0 | AI122: 0 | AJ122: 0 | AK122: 0 | AL122: 93613.2 | AM122: 0 | AN122: 0 | AO122: 0 | AP122: 0 | AQ122: 0 | AR122: 0 | AS122: 0 | AT122: 0 | AU122: 93613.2 | AV122: 0 | AW122: 0 | AX122: 311000 | AY122: SALE FINISHED GOODS | AZ122: 58 | BA122: 58 | BB122: 0 | BC122: 52BA0852 | BD122: 1509 | BE122: FG Body | BF122: 5094107312 | BG122: 05.05.2026
A123: 1115 | B123: 1115 | C123: 10 | D123: 2 | E123: Three Wheelers | F123: F2 | G123: COMMERCIAL INVOICE | H123: 1526005910 | I123: 1000006173 | L123: 04.05.2026 | M123: 5100001928 | N123: ZSCH | O123: Normal Sales | P123: 4110057393 | Q123: 28.11.2024 | R123: 5000 | S123: BAJAJ AUTO LIMITED (WALUJ) | V123: 27340676530V | W123: 1502020122 | X123: 52AH0692 BODY ASSLY MAXIMA Z EV | Y123: =VLOOKUP(W123,Sheet4!$A$5:$B$71,2,0) -> MAX UG NEW EV | Z123: 87082900 | AA123: 10 | AB123: EA | AC123: 9566.51 | AD123: INR | AE123: 95665.1 | AF123: 0 | AG123: 95665.1 | AH123: 0 | AI123: 0 | AJ123: 0 | AK123: 0 | AL123: 95665.1 | AM123: 0 | AN123: 0 | AO123: 0 | AP123: 0 | AQ123: 0 | AR123: 0 | AS123: 0 | AT123: 0 | AU123: 95665.1 | AV123: 0 | AW123: 0 | AX123: 311000 | AY123: SALE FINISHED GOODS | AZ123: 0 | BA123: 61 | BB123: -61 | BC123: 52AH0692 | BD123: 1509 | BE123: FG Body | BF123: 5094104403 | BG123: 04.05.2026
A124: 1115 | B124: 1115 | C124: 10 | D124: 2 | E124: Three Wheelers | F124: F2 | G124: COMMERCIAL INVOICE | H124: 1526005909 | I124: 1000006172 | L124: 04.05.2026 | M124: 5100001928 | N124: ZSCH | O124: Normal Sales | P124: 4110057393 | Q124: 28.11.2024 | R124: 5000 | S124: BAJAJ AUTO LIMITED (WALUJ) | V124: 27340676530V | W124: 1502020122 | X124: 52AH0692 BODY ASSLY MAXIMA Z EV | Y124: =VLOOKUP(W124,Sheet4!$A$5:$B$71,2,0) -> MAX UG NEW EV | Z124: 87082900 | AA124: 10 | AB124: EA | AC124: 9566.51 | AD124: INR | AE124: 95665.1 | AF124: 0 | AG124: 95665.1 | AH124: 0 | AI124: 0 | AJ124: 0 | AK124: 0 | AL124: 95665.1 | AM124: 0 | AN124: 0 | AO124: 0 | AP124: 0 | AQ124: 0 | AR124: 0 | AS124: 0 | AT124: 0 | AU124: 95665.1 | AV124: 0 | AW124: 0 | AX124: 311000 | AY124: SALE FINISHED GOODS | AZ124: 0 | BA124: 61 | BB124: -61 | BC124: 52AH0692 | BD124: 1509 | BE124: FG Body | BF124: 5094101114 | BG124: 04.05.2026
A125: 1115 | B125: 1115 | C125: 10 | D125: 2 | E125: Three Wheelers | F125: F2 | G125: COMMERCIAL INVOICE | H125: 1526005907 | I125: 1000006170 | L125: 04.05.2026 | M125: 5100001928 | N125: ZSCH | O125: Normal Sales | P125: 4110057393 | Q125: 28.11.2024 | R125: 5000 | S125: BAJAJ AUTO LIMITED (WALUJ) | V125: 27340676530V | W125: 1502020122 | X125: 52AH0692 BODY ASSLY MAXIMA Z EV | Y125: =VLOOKUP(W125,Sheet4!$A$5:$B$71,2,0) -> MAX UG NEW EV | Z125: 87082900 | AA125: 10 | AB125: EA | AC125: 9566.51 | AD125: INR | AE125: 95665.1 | AF125: 0 | AG125: 95665.1 | AH125: 0 | AI125: 0 | AJ125: 0 | AK125: 0 | AL125: 95665.1 | AM125: 0 | AN125: 0 | AO125: 0 | AP125: 0 | AQ125: 0 | AR125: 0 | AS125: 0 | AT125: 0 | AU125: 95665.1 | AV125: 0 | AW125: 0 | AX125: 311000 | AY125: SALE FINISHED GOODS | AZ125: 0 | BA125: 61 | BB125: -61 | BC125: 52AH0692 | BD125: 1509 | BE125: FG Body | BF125: 5094103567 | BG125: 04.05.2026
A126: 1115 | B126: 1115 | C126: 10 | D126: 2 | E126: Three Wheelers | F126: F2 | G126: COMMERCIAL INVOICE | H126: 1526005906 | I126: 1000006169 | L126: 04.05.2026 | M126: 5100001603 | N126: ZSCH | O126: Normal Sales | P126: 4110025468 | Q126: 19.03.2020 | R126: 5000 | S126: BAJAJ AUTO LIMITED (WALUJ) | V126: 27340676530V | W126: 1502020102 | X126: 52BB0638 BODY ASSLY MAXIMA X WIDE | Y126: =VLOOKUP(W126,Sheet4!$A$5:$B$71,2,0) -> MAXIMA HD | Z126: 87082900 | AA126: 8 | AB126: EA | AC126: 8593.51 | AD126: INR | AE126: 68748.08 | AF126: 0 | AG126: 68748.08 | AH126: 0 | AI126: 0 | AJ126: 0 | AK126: 0 | AL126: 68748.08 | AM126: 0 | AN126: 0 | AO126: 0 | AP126: 0 | AQ126: 0 | AR126: 0 | AS126: 0 | AT126: 0 | AU126: 68748.08 | AV126: 0 | AW126: 0 | AX126: 311000 | AY126: SALE FINISHED GOODS | AZ126: 93.34 | BA126: 75.43 | BB126: 17.91 | BC126: 52BB0638 | BD126: 1509 | BE126: FG Body | BF126: 5094102205 | BG126: 04.05.2026
A127: 1115 | B127: 1115 | C127: 10 | D127: 2 | E127: Three Wheelers | F127: F2 | G127: COMMERCIAL INVOICE | H127: 1526005905 | I127: 1000006168 | L127: 04.05.2026 | M127: 5100001603 | N127: ZSCH | O127: Normal Sales | P127: 4110025468 | Q127: 19.03.2020 | R127: 5000 | S127: BAJAJ AUTO LIMITED (WALUJ) | V127: 27340676530V | W127: 1502020102 | X127: 52BB0638 BODY ASSLY MAXIMA X WIDE | Y127: =VLOOKUP(W127,Sheet4!$A$5:$B$71,2,0) -> MAXIMA HD | Z127: 87082900 | AA127: 8 | AB127: EA | AC127: 8593.51 | AD127: INR | AE127: 68748.08 | AF127: 0 | AG127: 68748.08 | AH127: 0 | AI127: 0 | AJ127: 0 | AK127: 0 | AL127: 68748.08 | AM127: 0 | AN127: 0 | AO127: 0 | AP127: 0 | AQ127: 0 | AR127: 0 | AS127: 0 | AT127: 0 | AU127: 68748.08 | AV127: 0 | AW127: 0 | AX127: 311000 | AY127: SALE FINISHED GOODS | AZ127: 93.34 | BA127: 75.43 | BB127: 17.91 | BC127: 52BB0638 | BD127: 1509 | BE127: FG Body | BF127: 5094107108 | BG127: 05.05.2026
A128: 1115 | B128: 1115 | C128: 10 | D128: 2 | E128: Three Wheelers | F128: F2 | G128: COMMERCIAL INVOICE | H128: 1526005904 | I128: 1000006167 | L128: 04.05.2026 | M128: 5100001603 | N128: ZSCH | O128: Normal Sales | P128: 4110025468 | Q128: 19.03.2020 | R128: 5000 | S128: BAJAJ AUTO LIMITED (WALUJ) | V128: 27340676530V | W128: 1502020102 | X128: 52BB0638 BODY ASSLY MAXIMA X WIDE | Y128: =VLOOKUP(W128,Sheet4!$A$5:$B$71,2,0) -> MAXIMA HD | Z128: 87082900 | AA128: 8 | AB128: EA | AC128: 8593.51 | AD128: INR | AE128: 68748.08 | AF128: 0 | AG128: 68748.08 | AH128: 0 | AI128: 0 | AJ128: 0 | AK128: 0 | AL128: 68748.08 | AM128: 0 | AN128: 0 | AO128: 0 | AP128: 0 | AQ128: 0 | AR128: 0 | AS128: 0 | AT128: 0 | AU128: 68748.08 | AV128: 0 | AW128: 0 | AX128: 311000 | AY128: SALE FINISHED GOODS | AZ128: 93.34 | BA128: 75.43 | BB128: 17.91 | BC128: 52BB0638 | BD128: 1509 | BE128: FG Body | BF128: 5094104399 | BG128: 04.05.2026
A129: 1115 | B129: 1115 | C129: 10 | D129: 2 | E129: Three Wheelers | F129: F2 | G129: COMMERCIAL INVOICE | H129: 1526005903 | I129: 1000006166 | L129: 04.05.2026 | M129: 5100001101 | N129: ZSCH | O129: Normal Sales | P129: 4110004653 | Q129: 01.07.2017 | R129: 5000 | S129: BAJAJ AUTO LIMITED (WALUJ) | V129: 27340676530V | W129: 1502040194 | X129: AL161775 HYDROFORM CRADEL BSIV | Y129: =VLOOKUP(W129,Sheet4!$A$5:$B$71,2,0) -> CRADEL | Z129: 87082900 | AA129: 48 | AB129: EA | AC129: 956.92 | AD129: INR | AE129: 45932.16 | AF129: 0 | AG129: 45932.16 | AH129: 0 | AI129: 0 | AJ129: 0 | AK129: 0 | AL129: 45932.16 | AM129: 0 | AN129: 0 | AO129: 0 | AP129: 0 | AQ129: 0 | AR129: 0 | AS129: 0 | AT129: 0 | AU129: 45932.16 | AV129: 0 | AW129: 0 | AX129: 311000 | AY129: SALE FINISHED GOODS | AZ129: 6.377 | BA129: 6.377 | BB129: 0 | BC129: AL161775 | BD129: 1511 | BE129: FG Loose 3WH | BF129: 5094096702 | BG129: 04.05.2026
A130: 1115 | B130: 1115 | C130: 10 | D130: 2 | E130: Three Wheelers | F130: F2 | G130: COMMERCIAL INVOICE | H130: 1526005902 | I130: 1000006165 | L130: 04.05.2026 | M130: 5100001101 | N130: ZSCH | O130: Normal Sales | P130: 4110004653 | Q130: 01.07.2017 | R130: 5000 | S130: BAJAJ AUTO LIMITED (WALUJ) | V130: 27340676530V | W130: 1502040194 | X130: AL161775 HYDROFORM CRADEL BSIV | Y130: =VLOOKUP(W130,Sheet4!$A$5:$B$71,2,0) -> CRADEL | Z130: 87082900 | AA130: 48 | AB130: EA | AC130: 956.92 | AD130: INR | AE130: 45932.16 | AF130: 0 | AG130: 45932.16 | AH130: 0 | AI130: 0 | AJ130: 0 | AK130: 0 | AL130: 45932.16 | AM130: 0 | AN130: 0 | AO130: 0 | AP130: 0 | AQ130: 0 | AR130: 0 | AS130: 0 | AT130: 0 | AU130: 45932.16 | AV130: 0 | AW130: 0 | AX130: 311000 | AY130: SALE FINISHED GOODS | AZ130: 6.377 | BA130: 6.377 | BB130: 0 | BC130: AL161775 | BD130: 1511 | BE130: FG Loose 3WH | BF130: 5094096771 | BG130: 04.05.2026
A131: 1115 | B131: 1115 | C131: 10 | D131: 2 | E131: Three Wheelers | F131: F2 | G131: COMMERCIAL INVOICE | H131: 1526005901 | I131: 1000006164 | L131: 04.05.2026 | M131: 5100001636 | N131: ZSCH | O131: Normal Sales | P131: 4110026445 | Q131: 23.07.2020 | R131: 5000 | S131: BAJAJ AUTO LIMITED (WALUJ) | V131: 27340676530V | W131: 1502020104 | X131: AA231532 BODY ASSLY PETROL | Y131: =VLOOKUP(W131,Sheet4!$A$5:$B$71,2,0) -> RE STYLING | Z131: 87082900 | AA131: 15 | AB131: EA | AC131: 6585.55 | AD131: INR | AE131: 98783.25 | AF131: 0 | AG131: 98783.25 | AH131: 0 | AI131: 0 | AJ131: 0 | AK131: 0 | AL131: 98783.25 | AM131: 0 | AN131: 0 | AO131: 0 | AP131: 0 | AQ131: 0 | AR131: 0 | AS131: 0 | AT131: 0 | AU131: 98783.25 | AV131: 0 | AW131: 0 | AX131: 311000 | AY131: SALE FINISHED GOODS | AZ131: 49.75 | BA131: 49.75 | BB131: 0 | BC131: AA231532 | BD131: 1509 | BE131: FG Body | BF131: 5094107369 | BG131: 05.05.2026
... A139: 1115 | B139: 1115 | C139: 10 | D139: 2 | E139: Three Wheelers | F139: F2 | G139: COMMERCIAL INVOICE | H139: 1526005888 | I139: 1000006152 | L139: 04.05.2026 | M139: 5100001928 | N139: ZSCH | O139: Normal Sales | P139: 4110057393 | Q139: 28.11.2024 | R139: 5000 | S139: BAJAJ AUTO LIMITED (WALUJ) | V139: 27340676530V | W139: 1502020122 | X139: 52AH0692 BODY ASSLY MAXIMA Z EV | Y139: =VLOOKUP(W139,Sheet4!$A$5:$B$71,2,0) -> MAX UG NEW EV | Z139: 87082900 | AA139: 10 | AB139: EA | AC139: 9566.51 | AD139: INR | AE139: 95665.1 | AF139: 0 | AG139: 95665.1 | AH139: 0 | AI139: 0 | AJ139: 0 | AK139: 0 | AL139: 95665.1 | AM139: 0 | AN139: 0 | AO139: 0 | AP139: 0 | AQ139: 0 | AR139: 0 | AS139: 0 | AT139: 0 | AU139: 95665.1 | AV139: 0 | AW139: 0 | AX139: 311000 | AY139: SALE FINISHED GOODS | AZ139: 0 | BA139: 61 | BB139: -61 | BC139: 52AH0692 | BD139: 1509 | BE139: FG Body | BF139: 5094103524 | BG139: 04.05.2026
A140: 1115 | B140: 1115 | C140: 10 | D140: 2 | E140: Three Wheelers | F140: F2 | G140: COMMERCIAL INVOICE | H140: 1526005887 | I140: 1000006151 | L140: 04.05.2026 | M140: 5100001919 | N140: ZSCH | O140: Normal Sales | P140: 5500000930 | Q140: 23.07.2024 | R140: 5356 | S140: LUMINAZ SAFETY GLASS PVT. LTD. | W140: 1502010011 | X140: REAR MUDGUARD ASSEMBLY | Y140: =VLOOKUP(W140,Sheet4!$A$5:$B$71,2,0) -> REAR MUDGAURD | Z140: 87082900 | AA140: 432 | AB140: EA | AC140: 89.25 | AD140: INR | AE140: 38556 | AF140: 0 | AG140: 38556 | AH140: 0 | AI140: 0 | AJ140: 0 | AK140: 0 | AL140: 38556 | AM140: 0 | AN140: 0 | AO140: 0 | AP140: 0 | AQ140: 0 | AR140: 0 | AS140: 0 | AT140: 0 | AU140: 38556 | AV140: 0 | AW140: 0 | AX140: 311000 | AY140: SALE FINISHED GOODS | AZ140: 1.32 | BA140: 0.724 | BB140: 0.596 | BC140: 2000001017 | BD140: 1508 | BE140: FG Attached Vendor Components 3 WH | BF140: PENDING | BG140: Pending
A141: 1115 | B141: 1115 | C141: 10 | D141: 2 | E141: Three Wheelers | F141: F2 | G141: COMMERCIAL INVOICE | H141: 1526005886 | I141: 1000006150 | L141: 04.05.2026 | M141: 5100001919 | N141: ZSCH | O141: Normal Sales | P141: 5500000930 | Q141: 23.07.2024 | R141: 5356 | S141: LUMINAZ SAFETY GLASS PVT. LTD. | W141: 1502010011 | X141: REAR MUDGUARD ASSEMBLY | Y141: =VLOOKUP(W141,Sheet4!$A$5:$B$71,2,0) -> REAR MUDGAURD | Z141: 87082900 | AA141: 432 | AB141: EA | AC141: 89.25 | AD141: INR | AE141: 38556 | AF141: 0 | AG141: 38556 | AH141: 0 | AI141: 0 | AJ141: 0 | AK141: 0 | AL141: 38556 | AM141: 0 | AN141: 0 | AO141: 0 | AP141: 0 | AQ141: 0 | AR141: 0 | AS141: 0 | AT141: 0 | AU141: 38556 | AV141: 0 | AW141: 0 | AX141: 311000 | AY141: SALE FINISHED GOODS | AZ141: 1.32 | BA141: 0.724 | BB141: 0.596 | BC141: 2000001017 | BD141: 1508 | BE141: FG Attached Vendor Components 3 WH | BF141: PENDING | BG141: Pending
A142: 1115 | B142: 1115 | C142: 10 | D142: 2 | E142: Three Wheelers | F142: F2 | G142: COMMERCIAL INVOICE | H142: 1526005885 | I142: 1000006149 | L142: 04.05.2026 | M142: 5100001795 | N142: ZSCH | O142: Normal Sales | P142: 4110032503 | Q142: 31.08.2021 | R142: 5000 | S142: BAJAJ AUTO LIMITED (WALUJ) | V142: 27340676530V | W142: 1502010016 | X142: PLATE CHECK FRONT MUD MOUNTING | Y142: =VLOOKUP(W142,Sheet4!$A$5:$B$71,2,0) -> LOGISTICS | Z142: 87082900 | AA142: 2000 | AB142: EA | AC142: 8.46 | AD142: INR | AE142: 16920 | AF142: 0 | AG142: 16920 | AH142: 0 | AI142: 0 | AJ142: 0 | AK142: 0 | AL142: 16920 | AM142: 0 | AN142: 0 | AO142: 0 | AP142: 0 | AQ142: 0 | AR142: 0 | AS142: 0 | AT142: 0 | AU142: 16920 | AV142: 0 | AW142: 0 | AX142: 311000 | AY142: SALE FINISHED GOODS | AZ142: 0.08 | BA142: 0.063 | BB142: 0.017 | BC142: AB161182 | BD142: 1508 | BE142: FG Attached Vendor Components 3 WH | BF142: 5094095857 | BG142: 04.05.2026
A143: 1115 | B143: 1115 | C143: 10 | D143: 2 | E143: Three Wheelers | F143: F2 | G143: COMMERCIAL INVOICE | H143: 1526005884 | I143: 1000006148 | L143: 04.05.2026 | M143: 5100001955 | N143: ZSCH | O143: Normal Sales | P143: 5500001432 | Q143: 27.04.2026 | R143: 5356 | S143: LUMINAZ SAFETY GLASS PVT. LTD. | W143: 1104040829 | X143: AZ244025 DOOR INNER ENGINE ACC CVR UG | Y143: DOOR INNER | Z143: 87141090 | AA143: 261 | AB143: EA | AC143: 136.6 | AD143: INR | AE143: 35652.6 | AF143: 0 | AG143: 35652.6 | AH143: 0 | AI143: 0 | AJ143: 0 | AK143: 0 | AL143: 35652.6 | AM143: 0 | AN143: 0 | AO143: 0 | AP143: 0 | AQ143: 0 | AR143: 0 | AS143: 0 | AT143: 0 | AU143: 35652.6 | AV143: 0 | AW143: 0 | AX143: 311003 | AY143: SALE RAW MATERIAL | AZ143: 2.62 | BA143: 2.62 | BB143: 0 | BC143: 2000000894 | BD143: 1123 | BE143: RM Comp. Press | BF143: PENDING | BG143: Pending
A144: 1115 | B144: 1115 | C144: 10 | D144: 2 | E144: Three Wheelers | F144: F2 | G144: COMMERCIAL INVOICE | H144: 1526005883 | I144: 1000006147 | L144: 04.05.2026 | M144: 5100001588 | N144: ZSCH | O144: Normal Sales | P144: 4110025058 | Q144: 18.02.2020 | R144: 5000 | S144: BAJAJ AUTO LIMITED (WALUJ) | V144: 27340676530V | W144: 1502040235 | X144: AA102281_ASSLY HANDLE STARTING | Y144: =VLOOKUP(W144,Sheet4!$A$5:$B$71,2,0) -> STARTING HANDLE | Z144: 87082900 | AA144: 540 | AB144: EA | AC144: 217.33 | AD144: INR | AE144: 117358.2 | AF144: 0 | AG144: 117358.2 | AH144: 0 | AI144: 0 | AJ144: 0 | AK144: 0 | AL144: 117358.2 | AM144: 0 | AN144: 0 | AO144: 0 | AP144: 0 | AQ144: 0 | AR144: 0 | AS144: 0 | AT144: 0 | AU144: 117358.2 | AV144: 0 | AW144: 0 | AX144: 311000 | AY144: SALE FINISHED GOODS | AZ144: 1.19 | BA144: 1.19 | BB144: 0 | BC144: AA102281 | BD144: 1511 | BE144: FG Loose 3WH | BF144: 5094095727 | BG144: 04.05.2026
A145: 1115 | B145: 1115 | C145: 10 | D145: 2 | E145: Three Wheelers | F145: F2 | G145: COMMERCIAL INVOICE | H145: 1526005882 | I145: 1000006146 | L145: 04.05.2026 | M145: 5100001568 | N145: ZSCH | O145: Normal Sales | P145: 4110023868 | Q145: 07.01.2020 | R145: 5000 | S145: BAJAJ AUTO LIMITED (WALUJ) | V145: 27340676530V | W145: 1502040236 | X145: AF231720 TUBE ASSLY SUPPORT BACKREST | Y145: =VLOOKUP(W145,Sheet4!$A$5:$B$71,2,0) -> SUPPORT TOP | Z145: 87082900 | AA145: 720 | AB145: EA | AC145: 134.2 | AD145: INR | AE145: 96624 | AF145: 0 | AG145: 96624 | AH145: 0 | AI145: 0 | AJ145: 0 | AK145: 0 | AL145: 96624 | AM145: 0 | AN145: 0 | AO145: 0 | AP145: 0 | AQ145: 0 | AR145: 0 | AS145: 0 | AT145: 0 | AU145: 96624 | AV145: 0 | AW145: 0 | AX145: 311000 | AY145: SALE FINISHED GOODS | AZ145: 1.19 | BA145: 1.19 | BB145: 0 | BC145: AF231720 | BD145: 1511 | BE145: FG Loose 3WH | BF145: 5094096020 | BG145: 04.05.2026
A146: 1115 | B146: 1115 | C146: 10 | D146: 2 | E146: Three Wheelers | F146: F2 | G146: COMMERCIAL INVOICE | H146: 1526005881 | I146: 1000006145 | L146: 04.05.2026 | M146: 5100001919 | N146: ZSCH | O146: Normal Sales | P146: 5500000930 | Q146: 23.07.2024 | R146: 5356 | S146: LUMINAZ SAFETY GLASS PVT. LTD. | W146: 1502010011 | X146: REAR MUDGUARD ASSEMBLY | Y146: =VLOOKUP(W146,Sheet4!$A$5:$B$71,2,0) -> REAR MUDGAURD | Z146: 87082900 | AA146: 432 | AB146: EA | AC146: 89.25 | AD146: INR | AE146: 38556 | AF146: 0 | AG146: 38556 | AH146: 0 | AI146: 0 | AJ146: 0 | AK146: 0 | AL146: 38556 | AM146: 0 | AN146: 0 | AO146: 0 | AP146: 0 | AQ146: 0 | AR146: 0 | AS146: 0 | AT146: 0 | AU146: 38556 | AV146: 0 | AW146: 0 | AX146: 311000 | AY146: SALE FINISHED GOODS | AZ146: 1.32 | BA146: 0.724 | BB146: 0.596 | BC146: 2000001017 | BD146: 1508 | BE146: FG Attached Vendor Components 3 WH | BF146: PENDING | BG146: Pending
A147: 1115 | B147: 1115 | C147: 10 | D147: 2 | E147: Three Wheelers | F147: F2 | G147: COMMERCIAL INVOICE | H147: 1526005880 | I147: 1000006144 | L147: 04.05.2026 | M147: 5100001919 | N147: ZSCH | O147: Normal Sales | P147: 5500000930 | Q147: 23.07.2024 | R147: 5356 | S147: LUMINAZ SAFETY GLASS PVT. LTD. | W147: 1502010011 | X147: REAR MUDGUARD ASSEMBLY | Y147: =VLOOKUP(W147,Sheet4!$A$5:$B$71,2,0) -> REAR MUDGAURD | Z147: 87082900 | AA147: 432 | AB147: EA | AC147: 89.25 | AD147: INR | AE147: 38556 | AF147: 0 | AG147: 38556 | AH147: 0 | AI147: 0 | AJ147: 0 | AK147: 0 | AL147: 38556 | AM147: 0 | AN147: 0 | AO147: 0 | AP147: 0 | AQ147: 0 | AR147: 0 | AS147: 0 | AT147: 0 | AU147: 38556 | AV147: 0 | AW147: 0 | AX147: 311000 | AY147: SALE FINISHED GOODS | AZ147: 1.32 | BA147: 0.724 | BB147: 0.596 | BC147: 2000001017 | BD147: 1508 | BE147: FG Attached Vendor Components 3 WH | BF147: PENDING | BG147: Pending
A148: 1115 | B148: 1115 | C148: 10 | D148: 2 | E148: Three Wheelers | F148: F2 | G148: COMMERCIAL INVOICE | H148: 1526005879 | I148: 1000006143 | L148: 04.05.2026 | M148: 5100001919 | N148: ZSCH | O148: Normal Sales | P148: 5500000930 | Q148: 23.07.2024 | R148: 5356 | S148: LUMINAZ SAFETY GLASS PVT. LTD. | W148: 1502010011 | X148: REAR MUDGUARD ASSEMBLY | Y148: =VLOOKUP(W148,Sheet4!$A$5:$B$71,2,0) -> REAR MUDGAURD | Z148: 87082900 | AA148: 432 | AB148: EA | AC148: 89.25 | AD148: INR | AE148: 38556 | AF148: 0 | AG148: 38556 | AH148: 0 | AI148: 0 | AJ148: 0 | AK148: 0 | AL148: 38556 | AM148: 0 | AN148: 0 | AO148: 0 | AP148: 0 | AQ148: 0 | AR148: 0 | AS148: 0 | AT148: 0 | AU148: 38556 | AV148: 0 | AW148: 0 | AX148: 311000 | AY148: SALE FINISHED GOODS | AZ148: 1.32 | BA148: 0.724 | BB148: 0.596 | BC148: 2000001017 | BD148: 1508 | BE148: FG Attached Vendor Components 3 WH | BF148: PENDING | BG148: Pending
A149: 1115 | B149: 1115 | C149: 10 | D149: 2 | E149: Three Wheelers | F149: F2 | G149: COMMERCIAL INVOICE | H149: 1526005878 | I149: 1000006142 | L149: 04.05.2026 | M149: 5100001925 | N149: ZSCH | O149: Normal Sales | P149: 4110055667 | Q149: 10.09.2024 | R149: 5000 | S149: BAJAJ AUTO LIMITED (WALUJ) | V149: 27340676530V | W149: 1502040318 | X149: 52BA0833 RE DOOR ASSLY LH GREEN | Y149: =VLOOKUP(W149,Sheet4!$A$5:$B$71,2,0) -> Re Side Door | Z149: 87082900 | AA149: 120 | AB149: EA | AC149: 506.59 | AD149: INR | AE149: 60790.8 | AF149: 0 | AG149: 60790.8 | AH149: 0 | AI149: 0 | AJ149: 0 | AK149: 0 | AL149: 60790.8 | AM149: 0 | AN149: 0 | AO149: 0 | AP149: 0 | AQ149: 0 | AR149: 0 | AS149: 0 | AT149: 0 | AU149: 60790.8 | AV149: 0 | AW149: 0 | AX149: 311000 | AY149: SALE FINISHED GOODS | AZ149: 2.27 | BA149: 2.27 | BB149: 0 | BC149: 52BA0833 | BD149: 1511 | BE149: FG Loose 3WH | BF149: 5094100726 | BG149: 04.05.2026
A150: 1115 | B150: 1115 | C150: 10 | D150: 2 | E150: Three Wheelers | F150: F2 | G150: COMMERCIAL INVOICE | H150: 1526005876 | I150: 1000006140 | L150: 04.05.2026 | M150: 5100001928 | N150: ZSCH | O150: Normal Sales | P150: 4110057393 | Q150: 28.11.2024 | R150: 5000 | S150: BAJAJ AUTO LIMITED (WALUJ) | V150: 27340676530V | W150: 1502020122 | X150: 52AH0692 BODY ASSLY MAXIMA Z EV | Y150: =VLOOKUP(W150,Sheet4!$A$5:$B$71,2,0) -> MAX UG NEW EV | Z150: 87082900 | AA150: 10 | AB150: EA | AC150: 9566.51 | AD150: INR | AE150: 95665.1 | AF150: 0 | AG150: 95665.1 | AH150: 0 | AI150: 0 | AJ150: 0 | AK150: 0 | AL150: 95665.1 | AM150: 0 | AN150: 0 | AO150: 0 | AP150: 0 | AQ150: 0 | AR150: 0 | AS150: 0 | AT150: 0 | AU150: 95665.1 | AV150: 0 | AW150: 0 | AX150: 311000 | AY150: SALE FINISHED GOODS | AZ150: 0 | BA150: 61 | BB150: -61 | BC150: 52AH0692 | BD150: 1509 | BE150: FG Body | BF150: 5094103263 | BG150: 04.05.2026
A151: 1115 | B151: 1115 | C151: 10 | D151: 2 | E151: Three Wheelers | F151: F2 | G151: COMMERCIAL INVOICE | H151: 1526005875 | I151: 1000006139 | L151: 04.05.2026 | M151: 5100001925 | N151: ZSCH | O151: Normal Sales | P151: 4110055667 | Q151: 10.09.2024 | R151: 5000 | S151: BAJAJ AUTO LIMITED (WALUJ) | V151: 27340676530V | W151: 1502040317 | X151: 52BA0832 RE DOOR ASSLY RH GREEN | Y151: =VLOOKUP(W151,Sheet4!$A$5:$B$71,2,0) -> Re Side Door | Z151: 87082900 | AA151: 120 | AB151: EA | AC151: 506.59 | AD151: INR | AE151: 60790.8 | AF151: 0 | AG151: 60790.8 | AH151: 0 | AI151: 0 | AJ151: 0 | AK151: 0 | AL151: 60790.8 | AM151: 0 | AN151: 0 | AO151: 0 | AP151: 0 | AQ151: 0 | AR151: 0 | AS151: 0 | AT151: 0 | AU151: 60790.8 | AV151: 0 | AW151: 0 | AX151: 311000 | AY151: SALE FINISHED GOODS | AZ151: 2.27 | BA151: 2.27 | BB151: 0 | BC151: 52BA0832 | BD151: 1511 | BE151: FG Loose 3WH | BF151: 5094100727 | BG151: 04.05.2026
A152: 1115 | B152: 1115 | C152: 10 | D152: 2 | E152: Three Wheelers | F152: F2 | G152: COMMERCIAL INVOICE | H152: 1526005874 | I152: 1000006138 | L152: 04.05.2026 | M152: 5100001928 | N152: ZSCH | O152: Normal Sales | P152: 4110057393 | Q152: 28.11.2024 | R152: 5000 | S152: BAJAJ AUTO LIMITED (WALUJ) | V152: 27340676530V | W152: 1502020122 | X152: 52AH0692 BODY ASSLY MAXIMA Z EV | Y152: =VLOOKUP(W152,Sheet4!$A$5:$B$71,2,0) -> MAX UG NEW EV | Z152: 87082900 | AA152: 10 | AB152: EA | AC152: 9566.51 | AD152: INR | AE152: 95665.1 | AF152: 0 | AG152: 95665.1 | AH152: 0 | AI152: 0 | AJ152: 0 | AK152: 0 | AL152: 95665.1 | AM152: 0 | AN152: 0 | AO152: 0 | AP152: 0 | AQ152: 0 | AR152: 0 | AS152: 0 | AT152: 0 | AU152: 95665.1 | AV152: 0 | AW152: 0 | AX152: 311000 | AY152: SALE FINISHED GOODS | AZ152: 0 | BA152: 61 | BB152: -61 | BC152: 52AH0692 | BD152: 1509 | BE152: FG Body | BF152: 5094101035 | BG152: 04.05.2026
A153: 1115 | B153: 1115 | C153: 10 | D153: 2 | E153: Three Wheelers | F153: F2 | G153: COMMERCIAL INVOICE | H153: 1526005873 | I153: 1000006137 | L153: 04.05.2026 | M153: 5100001919 | N153: ZSCH | O153: Normal Sales | P153: 5500000930 | Q153: 23.07.2024 | R153: 5356 | S153: LUMINAZ SAFETY GLASS PVT. LTD. | W153: 1502010011 | X153: REAR MUDGUARD ASSEMBLY | Y153: =VLOOKUP(W153,Sheet4!$A$5:$B$71,2,0) -> REAR MUDGAURD | Z153: 87082900 | AA153: 432 | AB153: EA | AC153: 89.25 | AD153: INR | AE153: 38556 | AF153: 0 | AG153: 38556 | AH153: 0 | AI153: 0 | AJ153: 0 | AK153: 0 | AL153: 38556 | AM153: 0 | AN153: 0 | AO153: 0 | AP153: 0 | AQ153: 0 | AR153: 0 | AS153: 0 | AT153: 0 | AU153: 38556 | AV153: 0 | AW153: 0 | AX153: 311000 | AY153: SALE FINISHED GOODS | AZ153: 1.32 | BA153: 0.724 | BB153: 0.596 | BC153: 2000001017 | BD153: 1508 | BE153: FG Attached Vendor Components 3 WH | BF153: PENDING | BG153: Pending
A154: 1115 | B154: 1115 | C154: 10 | D154: 2 | E154: Three Wheelers | F154: F2 | G154: COMMERCIAL INVOICE | H154: 1526005872 | I154: 1000006136 | L154: 04.05.2026 | M154: 5100001636 | N154: ZSCH | O154: Normal Sales | P154: 4110026445 | Q154: 23.07.2020 | R154: 5000 | S154: BAJAJ AUTO LIMITED (WALUJ) | V154: 27340676530V | W154: 1502020104 | X154: AA231532 BODY ASSLY PETROL | Y154: =VLOOKUP(W154,Sheet4!$A$5:$B$71,2,0) -> RE STYLING | Z154: 87082900 | AA154: 15 | AB154: EA | AC154: 6585.55 | AD154: INR | AE154: 98783.25 | AF154: 0 | AG154: 98783.25 | AH154: 0 | AI154: 0 | AJ154: 0 | AK154: 0 | AL154: 98783.25 | AM154: 0 | AN154: 0 | AO154: 0 | AP154: 0 | AQ154: 0 | AR154: 0 | AS154: 0 | AT154: 0 | AU154: 98783.25 | AV154: 0 | AW154: 0 | AX154: 311000 | AY154: SALE FINISHED GOODS | AZ154: 49.75 | BA154: 49.75 | BB154: 0 | BC154: AA231532 | BD154: 1509 | BE154: FG Body | BF154: 5094100090 | BG154: 04.05.2026
A155: 1115 | B155: 1115 | C155: 10 | D155: 2 | E155: Three Wheelers | F155: F2 | G155: COMMERCIAL INVOICE | H155: 1526005871 | I155: 1000006135 | L155: 04.05.2026 | M155: 5100001919 | N155: ZSCH | O155: Normal Sales | P155: 5500000930 | Q155: 23.07.2024 | R155: 5356 | S155: LUMINAZ SAFETY GLASS PVT. LTD. | W155: 1502010011 | X155: REAR MUDGUARD ASSEMBLY | Y155: =VLOOKUP(W155,Sheet4!$A$5:$B$71,2,0) -> REAR MUDGAURD | Z155: 87082900 | AA155: 432 | AB155: EA | AC155: 89.25 | AD155: INR | AE155: 38556 | AF155: 0 | AG155: 38556 | AH155: 0 | AI155: 0 | AJ155: 0 | AK155: 0 | AL155: 38556 | AM155: 0 | AN155: 0 | AO155: 0 | AP155: 0 | AQ155: 0 | AR155: 0 | AS155: 0 | AT155: 0 | AU155: 38556 | AV155: 0 | AW155: 0 | AX155: 311000 | AY155: SALE FINISHED GOODS | AZ155: 1.32 | BA155: 0.724 | BB155: 0.596 | BC155: 2000001017 | BD155: 1508 | BE155: FG Attached Vendor Components 3 WH | BF155: PENDING | BG155: Pending
A156: 1115 | B156: 1115 | C156: 10 | D156: 2 | E156: Three Wheelers | F156: F2 | G156: COMMERCIAL INVOICE | H156: 1526005870 | I156: 1000006134 | L156: 04.05.2026 | M156: 5100001636 | N156: ZSCH | O156: Normal Sales | P156: 4110026445 | Q156: 23.07.2020 | R156: 5000 | S156: BAJAJ AUTO LIMITED (WALUJ) | V156: 27340676530V | W156: 1502020104 | X156: AA231532 BODY ASSLY PETROL | Y156: =VLOOKUP(W156,Sheet4!$A$5:$B$71,2,0) -> RE STYLING | Z156: 87082900 | AA156: 15 | AB156: EA | AC156: 6585.55 | AD156: INR | AE156: 98783.25 | AF156: 0 | AG156: 98783.25 | AH156: 0 | AI156: 0 | AJ156: 0 | AK156: 0 | AL156: 98783.25 | AM156: 0 | AN156: 0 | AO156: 0 | AP156: 0 | AQ156: 0 | AR156: 0 | AS156: 0 | AT156: 0 | AU156: 98783.25 | AV156: 0 | AW156: 0 | AX156: 311000 | AY156: SALE FINISHED GOODS | AZ156: 49.75 | BA156: 49.75 | BB156: 0 | BC156: AA231532 | BD156: 1509 | BE156: FG Body | BF156: 5094098632 | BG156: 04.05.2026
A157: 1115 | B157: 1115 | C157: 10 | D157: 2 | E157: Three Wheelers | F157: F2 | G157: COMMERCIAL INVOICE | H157: 1526005868 | I157: 1000006132 | L157: 04.05.2026 | M157: 5100001919 | N157: ZSCH | O157: Normal Sales | P157: 5500000930 | Q157: 23.07.2024 | R157: 5356 | S157: LUMINAZ SAFETY GLASS PVT. LTD. | W157: 1502010011 | X157: REAR MUDGUARD ASSEMBLY | Y157: =VLOOKUP(W157,Sheet4!$A$5:$B$71,2,0) -> REAR MUDGAURD | Z157: 87082900 | AA157: 432 | AB157: EA | AC157: 89.25 | AD157: INR | AE157: 38556 | AF157: 0 | AG157: 38556 | AH157: 0 | AI157: 0 | AJ157: 0 | AK157: 0 | AL157: 38556 | AM157: 0 | AN157: 0 | AO157: 0 | AP157: 0 | AQ157: 0 | AR157: 0 | AS157: 0 | AT157: 0 | AU157: 38556 | AV157: 0 | AW157: 0 | AX157: 311000 | AY157: SALE FINISHED GOODS | AZ157: 1.32 | BA157: 0.724 | BB157: 0.596 | BC157: 2000001017 | BD157: 1508 | BE157: FG Attached Vendor Components 3 WH | BF157: PENDING | BG157: Pending
A158: 1115 | B158: 1115 | C158: 10 | D158: 2 | E158: Three Wheelers | F158: F2 | G158: COMMERCIAL INVOICE | H158: 1526005867 | I158: 1000006131 | L158: 04.05.2026 | M158: 5100001919 | N158: ZSCH | O158: Normal Sales | P158: 5500000930 | Q158: 23.07.2024 | R158: 5356 | S158: LUMINAZ SAFETY GLASS PVT. LTD. | W158: 1502010011 | X158: REAR MUDGUARD ASSEMBLY | Y158: =VLOOKUP(W158,Sheet4!$A$5:$B$71,2,0) -> REAR MUDGAURD | Z158: 87082900 | AA158: 432 | AB158: EA | AC158: 89.25 | AD158: INR | AE158: 38556 | AF158: 0 | AG158: 38556 | AH158: 0 | AI158: 0 | AJ158: 0 | AK158: 0 | AL158: 38556 | AM158: 0 | AN158: 0 | AO158: 0 | AP158: 0 | AQ158: 0 | AR158: 0 | AS158: 0 | AT158: 0 | AU158: 38556 | AV158: 0 | AW158: 0 | AX158: 311000 | AY158: SALE FINISHED GOODS | AZ158: 1.32 | BA158: 0.724 | BB158: 0.596 | BC158: 2000001017 | BD158: 1508 | BE158: FG Attached Vendor Components 3 WH | BF158: PENDING | BG158: Pending
A159: 1115 | B159: 1115 | C159: 10 | D159: 2 | E159: Three Wheelers | F159: F2 | G159: COMMERCIAL INVOICE | H159: 1526005866 | I159: 1000006130 | L159: 04.05.2026 | M159: 5100001919 | N159: ZSCH | O159: Normal Sales | P159: 5500000930 | Q159: 23.07.2024 | R159: 5356 | S159: LUMINAZ SAFETY GLASS PVT. LTD. | W159: 1502010011 | X159: REAR MUDGUARD ASSEMBLY | Y159: =VLOOKUP(W159,Sheet4!$A$5:$B$71,2,0) -> REAR MUDGAURD | Z159: 87082900 | AA159: 432 | AB159: EA | AC159: 89.25 | AD159: INR | AE159: 38556 | AF159: 0 | AG159: 38556 | AH159: 0 | AI159: 0 | AJ159: 0 | AK159: 0 | AL159: 38556 | AM159: 0 | AN159: 0 | AO159: 0 | AP159: 0 | AQ159: 0 | AR159: 0 | AS159: 0 | AT159: 0 | AU159: 38556 | AV159: 0 | AW159: 0 | AX159: 311000 | AY159: SALE FINISHED GOODS | AZ159: 1.32 | BA159: 0.724 | BB159: 0.596 | BC159: 2000001017 | BD159: 1508 | BE159: FG Attached Vendor Components 3 WH | BF159: PENDING | BG159: Pending
A160: 1115 | B160: 1115 | C160: 10 | D160: 2 | E160: Three Wheelers | F160: F2 | G160: COMMERCIAL INVOICE | H160: 1526005865 | I160: 1000006129 | L160: 04.05.2026 | M160: 5100001927 | N160: ZSCH | O160: Normal Sales | P160: 4110053962 | Q160: 10.07.2024 | R160: 5000 | S160: BAJAJ AUTO LIMITED (WALUJ) | V160: 27340676530V | W160: 1502040267 | X160: AZ111331_06 SUPPORT ASSLY DASHBOARD | Y160: =VLOOKUP(W160,Sheet4!$A$5:$B$71,2,0) -> DASH BOARD | Z160: 87082900 | AA160: 300 | AB160: EA | AC160: 290.9 | AD160: INR | AE160: 87270 | AF160: 0 | AG160: 87270 | AH160: 0 | AI160: 0 | AJ160: 0 | AK160: 0 | AL160: 87270 | AM160: 0 | AN160: 0 | AO160: 0 | AP160: 0 | AQ160: 0 | AR160: 0 | AS160: 0 | AT160: 0 | AU160: 87270 | AV160: 0 | AW160: 0 | AX160: 311000 | AY160: SALE FINISHED GOODS | AZ160: 4.5 | BA160: 4.5 | BB160: 0 | BC160: AZ111331 | BD160: 1511 | BE160: FG Loose 3WH | BF160: 5094101826 | BG160: 04.05.2026
A161: 1115 | B161: 1115 | C161: 10 | D161: 2 | E161: Three Wheelers | F161: F2 | G161: COMMERCIAL INVOICE | H161: 1526006140 | I161: 1000006411 | L161: 05.05.2026 | M161: 5100001924 | N161: ZSCH | O161: Normal Sales | P161: 4110055642 | Q161: 09.09.2024 | R161: 5000 | S161: BAJAJ AUTO LIMITED (WALUJ) | V161: 27340676530V | W161: 1502040314 | X161: 52BA0835 RE DOOR ASSLY LH YELLOW | Y161: =VLOOKUP(W161,Sheet4!$A$5:$B$71,2,0) -> Re Side Door | Z161: 87082900 | AA161: 120 | AB161: EA | AC161: 504.46 | AD161: INR | AE161: 60535.2 | AF161: 0 | AG161: 60535.2 | AH161: 0 | AI161: 0 | AJ161: 0 | AK161: 0 | AL161: 60535.2 | AM161: 0 | AN161: 0 | AO161: 0 | AP161: 0 | AQ161: 0 | AR161: 0 | AS161: 0 | AT161: 0 | AU161: 60535.2 | AV161: 0 | AW161: 0 | AX161: 311000 | AY161: SALE FINISHED GOODS | AZ161: 2.27 | BA161: 2.27 | BB161: 0 | BC161: 52BA0835 | BD161: 1511 | BE161: FG Loose 3WH | BF161: 5094124117 | BG161: 05.05.2026
A162: 1115 | B162: 1115 | C162: 10 | D162: 2 | E162: Three Wheelers | F162: F2 | G162: COMMERCIAL INVOICE | H162: 1526006139 | I162: 1000006410 | L162: 05.05.2026 | M162: 5100001924 | N162: ZSCH | O162: Normal Sales | P162: 4110055642 | Q162: 09.09.2024 | R162: 5000 | S162: BAJAJ AUTO LIMITED (WALUJ) | V162: 27340676530V | W162: 1502040313 | X162: 52BA0834 RE DOOR ASSLY RH YELLOW | Y162: =VLOOKUP(W162,Sheet4!$A$5:$B$71,2,0) -> Re Side Door | Z162: 87082900 | AA162: 120 | AB162: EA | AC162: 504.46 | AD162: INR | AE162: 60535.2 | AF162: 0 | AG162: 60535.2 | AH162: 0 | AI162: 0 | AJ162: 0 | AK162: 0 | AL162: 60535.2 | AM162: 0 | AN162: 0 | AO162: 0 | AP162: 0 | AQ162: 0 | AR162: 0 | AS162: 0 | AT162: 0 | AU162: 60535.2 | AV162: 0 | AW162: 0 | AX162: 311000 | AY162: SALE FINISHED GOODS | AZ162: 2.27 | BA162: 2.27 | BB162: 0 | BC162: 52BA0834 | BD162: 1511 | BE162: FG Loose 3WH | BF162: 5094124163 | BG162: 05.05.2026
A163: 1115 | B163: 1115 | C163: 10 | D163: 2 | E163: Three Wheelers | F163: F2 | G163: COMMERCIAL INVOICE | H163: 1526006138 | I163: 1000006409 | L163: 05.05.2026 | M163: 5100001666 | N163: ZSCH | O163: Normal Sales | P163: 4110027035 | Q163: 03.09.2020 | R163: 5000 | S163: BAJAJ AUTO LIMITED (WALUJ) | V163: 27340676530V | W163: 1502020105 | X163: 52AU0123 BODY ASSLY 4S PETROL | Y163: =VLOOKUP(W163,Sheet4!$A$5:$B$71,2,0) -> RE STYLING | Z163: 87082900 | AA163: 9 | AB163: EA | AC163: 6570.77 | AD163: INR | AE163: 59136.93 | AF163: 0 | AG163: 59136.93 | AH163: 0 | AI163: 0 | AJ163: 0 | AK163: 0 | AL163: 59136.93 | AM163: 0 | AN163: 0 | AO163: 0 | AP163: 0 | AQ163: 0 | AR163: 0 | AS163: 0 | AT163: 0 | AU163: 59136.93 | AV163: 0 | AW163: 0 | AX163: 311000 | AY163: SALE FINISHED GOODS | AZ163: 49.75 | BA163: 49.75 | BB163: 0 | BC163: 52AU0123 | BD163: 1509 | BE163: FG Body | BF163: 5094130919 | BG163: 06.05.2026
A164: 1115 | B164: 1115 | C164: 10 | D164: 2 | E164: Three Wheelers | F164: F2 | G164: COMMERCIAL INVOICE | H164: 1526006137 | I164: 1000006408 | L164: 05.05.2026 | M164: 5100001636 | N164: ZSCH | O164: Normal Sales | P164: 4110026445 | Q164: 23.07.2020 | R164: 5000 | S164: BAJAJ AUTO LIMITED (WALUJ) | V164: 27340676530V | W164: 1502020101 | X164: 52BA0852 ASSLY BODY COMPACT DIESEL | Y164: =VLOOKUP(W164,Sheet4!$A$5:$B$71,2,0) -> RE STYLING | Z164: 87082900 | AA164: 6 | AB164: EA | AC164: 6240.88 | AD164: INR | AE164: 37445.28 | AF164: 0 | AG164: 37445.28 | AH164: 0 | AI164: 0 | AJ164: 0 | AK164: 0 | AL164: 37445.28 | AM164: 0 | AN164: 0 | AO164: 0 | AP164: 0 | AQ164: 0 | AR164: 0 | AS164: 0 | AT164: 0 | AU164: 37445.28 | AV164: 0 | AW164: 0 | AX164: 311000 | AY164: SALE FINISHED GOODS | AZ164: 58 | BA164: 58 | BB164: 0 | BC164: 52BA0852 | BD164: 1509 | BE164: FG Body | BF164: 5094130747 | BG164: 06.05.2026
A165: 1115 | B165: 1115 | C165: 10 | D165: 2 | E165: Three Wheelers | F165: F2 | G165: COMMERCIAL INVOICE | H165: 1526006136 | I165: 1000006407 | L165: 05.05.2026 | M165: 5100001934 | N165: ZSCH | O165: Normal Sales | P165: 4110058649 | Q165: 10.02.2025 | R165: 5000 | S165: BAJAJ AUTO LIMITED (WALUJ) | V165: 27340676530V | W165: 1502040217 | X165: AH111571 MUDGUARD ASSEMBLY FORNT | Y165: =VLOOKUP(W165,Sheet4!$A$5:$B$71,2,0) -> FRONT MUDGARD GOGO | Z165: 87082900 | AA165: 70 | AB165: EA | AC165: 380.93 | AD165: INR | AE165: 26665.1 | AF165: 0 | AG165: 26665.1 | AH165: 0 | AI165: 0 | AJ165: 0 | AK165: 0 | AL165: 26665.1 | AM165: 0 | AN165: 0 | AO165: 0 | AP165: 0 | AQ165: 0 | AR165: 0 | AS165: 0 | AT165: 0 | AU165: 26665.1 | AV165: 0 | AW165: 0 | AX165: 311000 | AY165: SALE FINISHED GOODS | AZ165: 2.13 | BA165: 2.13 | BB165: 0 | BC165: AH111571 | BD165: 1511 | BE165: FG Loose 3WH | BF165: 5094122298 | BG165: 05.05.2026
A166: 1115 | B166: 1115 | C166: 10 | D166: 2 | E166: Three Wheelers | F166: F2 | G166: COMMERCIAL INVOICE | H166: 1526006135 | I166: 1000006406 | L166: 05.05.2026 | M166: 5100001603 | N166: ZSCH | O166: Normal Sales | P166: 4110025468 | Q166: 19.03.2020 | R166: 5000 | S166: BAJAJ AUTO LIMITED (WALUJ) | V166: 27340676530V | W166: 1502020102 | X166: 52BB0638 BODY ASSLY MAXIMA X WIDE | Y166: =VLOOKUP(W166,Sheet4!$A$5:$B$71,2,0) -> MAXIMA HD | Z166: 87082900 | AA166: 8 | AB166: EA | AC166: 8593.51 | AD166: INR | AE166: 68748.08 | AF166: 0 | AG166: 68748.08 | AH166: 0 | AI166: 0 | AJ166: 0 | AK166: 0 | AL166: 68748.08 | AM166: 0 | AN166: 0 | AO166: 0 | AP166: 0 | AQ166: 0 | AR166: 0 | AS166: 0 | AT166: 0 | AU166: 68748.08 | AV166: 0 | AW166: 0 | AX166: 311000 | AY166: SALE FINISHED GOODS | AZ166: 93.34 | BA166: 75.43 | BB166: 17.91 | BC166: 52BB0638 | BD166: 1509 | BE166: FG Body | BF166: PENDING | BG166: Pending
A167: 1115 | B167: 1115 | C167: 10 | D167: 2 | E167: Three Wheelers | F167: F2 | G167: COMMERCIAL INVOICE | H167: 1526006134 | I167: 1000006405 | L167: 05.05.2026 | M167: 5100001603 | N167: ZSCH | O167: Normal Sales | P167: 4110025468 | Q167: 19.03.2020 | R167: 5000 | S167: BAJAJ AUTO LIMITED (WALUJ) | V167: 27340676530V | W167: 1502020102 | X167: 52BB0638 BODY ASSLY MAXIMA X WIDE | Y167: =VLOOKUP(W167,Sheet4!$A$5:$B$71,2,0) -> MAXIMA HD | Z167: 87082900 | AA167: 8 | AB167: EA | AC167: 8593.51 | AD167: INR | AE167: 68748.08 | AF167: 0 | AG167: 68748.08 | AH167: 0 | AI167: 0 | AJ167: 0 | AK167: 0 | AL167: 68748.08 | AM167: 0 | AN167: 0 | AO167: 0 | AP167: 0 | AQ167: 0 | AR167: 0 | AS167: 0 | AT167: 0 | AU167: 68748.08 | AV167: 0 | AW167: 0 | AX167: 311000 | AY167: SALE FINISHED GOODS | AZ167: 93.34 | BA167: 75.43 | BB167: 17.91 | BC167: 52BB0638 | BD167: 1509 | BE167: FG Body | BF167: 5094126705 | BG167: 05.05.2026
A168: 1115 | B168: 1115 | C168: 10 | D168: 2 | E168: Three Wheelers | F168: F2 | G168: COMMERCIAL INVOICE | H168: 1526006133 | I168: 1000006404 | L168: 05.05.2026 | M168: 5100001603 | N168: ZSCH | O168: Normal Sales | P168: 4110025468 | Q168: 19.03.2020 | R168: 5000 | S168: BAJAJ AUTO LIMITED (WALUJ) | V168: 27340676530V | W168: 1502020102 | X168: 52BB0638 BODY ASSLY MAXIMA X WIDE | Y168: =VLOOKUP(W168,Sheet4!$A$5:$B$71,2,0) -> MAXIMA HD | Z168: 87082900 | AA168: 8 | AB168: EA | AC168: 8593.51 | AD168: INR | AE168: 68748.08 | AF168: 0 | AG168: 68748.08 | AH168: 0 | AI168: 0 | AJ168: 0 | AK168: 0 | AL168: 68748.08 | AM168: 0 | AN168: 0 | AO168: 0 | AP168: 0 | AQ168: 0 | AR168: 0 | AS168: 0 | AT168: 0 | AU168: 68748.08 | AV168: 0 | AW168: 0 | AX168: 311000 | AY168: SALE FINISHED GOODS | AZ168: 93.34 | BA168: 75.43 | BB168: 17.91 | BC168: 52BB0638 | BD168: 1509 | BE168: FG Body | BF168: 5094122335 | BG168: 05.05.2026
A169: 1115 | B169: 1115 | C169: 10 | D169: 2 | E169: Three Wheelers | F169: F2 | G169: COMMERCIAL INVOICE | H169: 1526006132 | I169: 1000006403 | L169: 05.05.2026 | M169: 5100001928 | N169: ZSCH | O169: Normal Sales | P169: 4110057393 | Q169: 28.11.2024 | R169: 5000 | S169: BAJAJ AUTO LIMITED (WALUJ) | V169: 27340676530V | W169: 1502020122 | X169: 52AH0692 BODY ASSLY MAXIMA Z EV | Y169: =VLOOKUP(W169,Sheet4!$A$5:$B$71,2,0) -> MAX UG NEW EV | Z169: 87082900 | AA169: 10 | AB169: EA | AC169: 9566.51 | AD169: INR | AE169: 95665.1 | AF169: 0 | AG169: 95665.1 | AH169: 0 | AI169: 0 | AJ169: 0 | AK169: 0 | AL169: 95665.1 | AM169: 0 | AN169: 0 | AO169: 0 | AP169: 0 | AQ169: 0 | AR169: 0 | AS169: 0 | AT169: 0 | AU169: 95665.1 | AV169: 0 | AW169: 0 | AX169: 311000 | AY169: SALE FINISHED GOODS | AZ169: 0 | BA169: 61 | BB169: -61 | BC169: 52AH0692 | BD169: 1509 | BE169: FG Body | BF169: 5094126089 | BG169: 05.05.2026
A170: 1115 | B170: 1115 | C170: 10 | D170: 2 | E170: Three Wheelers | F170: F2 | G170: COMMERCIAL INVOICE | H170: 1526006131 | I170: 1000006402 | L170: 05.05.2026 | M170: 5100001928 | N170: ZSCH | O170: Normal Sales | P170: 4110057393 | Q170: 28.11.2024 | R170: 5000 | S170: BAJAJ AUTO LIMITED (WALUJ) | V170: 27340676530V | W170: 1502020122 | X170: 52AH0692 BODY ASSLY MAXIMA Z EV | Y170: =VLOOKUP(W170,Sheet4!$A$5:$B$71,2,0) -> MAX UG NEW EV | Z170: 87082900 | AA170: 10 | AB170: EA | AC170: 9566.51 | AD170: INR | AE170: 95665.1 | AF170: 0 | AG170: 95665.1 | AH170: 0 | AI170: 0 | AJ170: 0 | AK170: 0 | AL170: 95665.1 | AM170: 0 | AN170: 0 | AO170: 0 | AP170: 0 | AQ170: 0 | AR170: 0 | AS170: 0 | AT170: 0 | AU170: 95665.1 | AV170: 0 | AW170: 0 | AX170: 311000 | AY170: SALE FINISHED GOODS | AZ170: 0 | BA170: 61 | BB170: -61 | BC170: 52AH0692 | BD170: 1509 | BE170: FG Body | BF170: 5094125960 | BG170: 05.05.2026
A171: 1115 | B171: 1115 | C171: 10 | D171: 2 | E171: Three Wheelers | F171: F2 | G171: COMMERCIAL INVOICE | H171: 1526006130 | I171: 1000006401 | L171: 05.05.2026 | M171: 5100001928 | N171: ZSCH | O171: Normal Sales | P171: 4110057393 | Q171: 28.11.2024 | R171: 5000 | S171: BAJAJ AUTO LIMITED (WALUJ) | V171: 27340676530V | W171: 1502020122 | X171: 52AH0692 BODY ASSLY MAXIMA Z EV | Y171: =VLOOKUP(W171,Sheet4!$A$5:$B$71,2,0) -> MAX UG NEW EV | Z171: 87082900 | AA171: 10 | AB171: EA | AC171: 9566.51 | AD171: INR | AE171: 95665.1 | AF171: 0 | AG171: 95665.1 | AH171: 0 | AI171: 0 | AJ171: 0 | AK171: 0 | AL171: 95665.1 | AM171: 0 | AN171: 0 | AO171: 0 | AP171: 0 | AQ171: 0 | AR171: 0 | AS171: 0 | AT171: 0 | AU171: 95665.1 | AV171: 0 | AW171: 0 | AX171: 311000 | AY171: SALE FINISHED GOODS | AZ171: 0 | BA171: 61 | BB171: -61 | BC171: 52AH0692 | BD171: 1509 | BE171: FG Body | BF171: 5094122405 | BG171: 05.05.2026
A172: 1115 | B172: 1115 | C172: 10 | D172: 2 | E172: Three Wheelers | F172: F2 | G172: COMMERCIAL INVOICE | H172: 1526006129 | I172: 1000006400 | L172: 05.05.2026 | M172: 5100001928 | N172: ZSCH | O172: Normal Sales | P172: 4110057393 | Q172: 28.11.2024 | R172: 5000 | S172: BAJAJ AUTO LIMITED (WALUJ) | V172: 27340676530V | W172: 1502020122 | X172: 52AH0692 BODY ASSLY MAXIMA Z EV | Y172: =VLOOKUP(W172,Sheet4!$A$5:$B$71,2,0) -> MAX UG NEW EV | Z172: 87082900 | AA172: 10 | AB172: EA | AC172: 9566.51 | AD172: INR | AE172: 95665.1 | AF172: 0 | AG172: 95665.1 | AH172: 0 | AI172: 0 | AJ172: 0 | AK172: 0 | AL172: 95665.1 | AM172: 0 | AN172: 0 | AO172: 0 | AP172: 0 | AQ172: 0 | AR172: 0 | AS172: 0 | AT172: 0 | AU172: 95665.1 | AV172: 0 | AW172: 0 | AX172: 311000 | AY172: SALE FINISHED GOODS | AZ172: 0 | BA172: 61 | BB172: -61 | BC172: 52AH0692 | BD172: 1509 | BE172: FG Body | BF172: 5094126703 | BG172: 05.05.2026
A173: 1115 | B173: 1115 | C173: 10 | D173: 2 | E173: Three Wheelers | F173: F2 | G173: COMMERCIAL INVOICE | H173: 1526006128 | I173: 1000006399 | L173: 05.05.2026 | M173: 5100001928 | N173: ZSCH | O173: Normal Sales | P173: 4110057393 | Q173: 28.11.2024 | R173: 5000 | S173: BAJAJ AUTO LIMITED (WALUJ) | V173: 27340676530V | W173: 1502020122 | X173: 52AH0692 BODY ASSLY MAXIMA Z EV | Y173: =VLOOKUP(W173,Sheet4!$A$5:$B$71,2,0) -> MAX UG NEW EV | Z173: 87082900 | AA173: 10 | AB173: EA | AC173: 9566.51 | AD173: INR | AE173: 95665.1 | AF173: 0 | AG173: 95665.1 | AH173: 0 | AI173: 0 | AJ173: 0 | AK173: 0 | AL173: 95665.1 | AM173: 0 | AN173: 0 | AO173: 0 | AP173: 0 | AQ173: 0 | AR173: 0 | AS173: 0 | AT173: 0 | AU173: 95665.1 | AV173: 0 | AW173: 0 | AX173: 311000 | AY173: SALE FINISHED GOODS | AZ173: 0 | BA173: 61 | BB173: -61 | BC173: 52AH0692 | BD173: 1509 | BE173: FG Body | BF173: 5094123178 | BG173: 05.05.2026
A174: 1115 | B174: 1115 | C174: 10 | D174: 2 | E174: Three Wheelers | F174: F2 | G174: COMMERCIAL INVOICE | H174: 1526006127 | I174: 1000006398 | L174: 05.05.2026 | M174: 5100001913 | N174: ZSCH | O174: Normal Sales | P174: 4110050475 | Q174: 12.04.2024 | R174: 5000 | S174: BAJAJ AUTO LIMITED (WALUJ) | V174: 27340676530V | W174: 1502040289 | X174: AF232042 TUBE ASSLY SUPPORT BACKREST | Y174: =VLOOKUP(W174,Sheet4!$A$5:$B$71,2,0) -> SUPPORT TOP | Z174: 87082900 | AA174: 480 | AB174: EA | AC174: 174.61 | AD174: INR | AE174: 83812.8 | AF174: 0 | AG174: 83812.8 | AH174: 0 | AI174: 0 | AJ174: 0 | AK174: 0 | AL174: 83812.8 | AM174: 0 | AN174: 0 | AO174: 0 | AP174: 0 | AQ174: 0 | AR174: 0 | AS174: 0 | AT174: 0 | AU174: 83812.8 | AV174: 0 | AW174: 0 | AX174: 311000 | AY174: SALE FINISHED GOODS | AZ174: 0 | BA174: 0 | BB174: 0 | BC174: AF232042 | BD174: 1511 | BE174: FG Loose 3WH | BF174: 5094123832 | BG174: 05.05.2026
A175: 1115 | B175: 1115 | C175: 10 | D175: 2 | E175: Three Wheelers | F175: F2 | G175: COMMERCIAL INVOICE | H175: 1526006124 | I175: 1000006395 | L175: 05.05.2026 | M175: 5100001949 | N175: ZSCH | O175: Normal Sales | P175: 4110063766 | Q175: 23.01.2026 | R175: 5000 | S175: BAJAJ AUTO LIMITED (WALUJ) | V175: 27340676530V | W175: 1502040322 | X175: AH115161 SUPPORT ASSLY DASHBOARD | Y175: =VLOOKUP(W175,Sheet4!$A$5:$B$71,2,0) -> DASH BOARD | Z175: 87082900 | AA175: 150 | AB175: EA | AC175: 291.28 | AD175: INR | AE175: 43692 | AF175: 0 | AG175: 43692 | AH175: 0 | AI175: 0 | AJ175: 0 | AK175: 0 | AL175: 43692 | AM175: 0 | AN175: 0 | AO175: 0 | AP175: 0 | AQ175: 0 | AR175: 0 | AS175: 0 | AT175: 0 | AU175: 43692 | AV175: 0 | AW175: 0 | AX175: 311000 | AY175: SALE FINISHED GOODS | AZ175: 2.37 | BA175: 2.37 | BB175: 0 | BC175: AH115161 | BD175: 1511 | BE175: FG Loose 3WH | BF175: 5094130724 | BG175: 06.05.2026
A176: 1115 | B176: 1115 | C176: 10 | D176: 2 | E176: Three Wheelers | F176: F2 | G176: COMMERCIAL INVOICE | H176: 1526006123 | I176: 1000006394 | L176: 05.05.2026 | M176: 5100001899 | N176: ZSCH | O176: Normal Sales | P176: 4110041854 | Q176: 03.03.2023 | R176: 5000 | S176: BAJAJ AUTO LIMITED (WALUJ) | V176: 27340676530V | W176: 1502040267 | X176: AZ111331_06 SUPPORT ASSLY DASHBOARD | Y176: =VLOOKUP(W176,Sheet4!$A$5:$B$71,2,0) -> DASH BOARD | Z176: 87082900 | AA176: 256 | AB176: EA | AC176: 290.9 | AD176: INR | AE176: 74470.4 | AF176: 0 | AG176: 74470.4 | AH176: 0 | AI176: 0 | AJ176: 0 | AK176: 0 | AL176: 74470.4 | AM176: 0 | AN176: 0 | AO176: 0 | AP176: 0 | AQ176: 0 | AR176: 0 | AS176: 0 | AT176: 0 | AU176: 74470.4 | AV176: 0 | AW176: 0 | AX176: 311000 | AY176: SALE FINISHED GOODS | AZ176: 4.5 | BA176: 4.5 | BB176: 0 | BC176: AZ111331 | BD176: 1511 | BE176: FG Loose 3WH | BF176: 5094130726 | BG176: 06.05.2026
A177: 1115 | B177: 1115 | C177: 10 | D177: 2 | E177: Three Wheelers | F177: F2 | G177: COMMERCIAL INVOICE | H177: 1526006121 | I177: 1000006392 | L177: 05.05.2026 | M177: 5100001099 | N177: ZSCH | O177: Normal Sales | P177: 4110004650 | Q177: 01.07.2017 | R177: 5000 | S177: BAJAJ AUTO LIMITED (WALUJ) | V177: 27340676530V | W177: 1502040133 | X177: 52BB0109 - COVER REAR RH FL YELLOW | Y177: =VLOOKUP(W177,Sheet4!$A$5:$B$71,2,0) -> REAR COVER | Z177: 87082900 | AA177: 55 | AB177: EA | AC177: 164.49 | AD177: INR | AE177: 9046.95 | AF177: 0 | AG177: 9046.95 | AH177: 0 | AI177: 0 | AJ177: 0 | AK177: 0 | AL177: 9046.95 | AM177: 0 | AN177: 0 | AO177: 0 | AP177: 0 | AQ177: 0 | AR177: 0 | AS177: 0 | AT177: 0 | AU177: 9046.95 | AV177: 0 | AW177: 0 | AX177: 311000 | AY177: SALE FINISHED GOODS | AZ177: 1.248 | BA177: 1.248 | BB177: 0 | BC177: 52BB0109 | BD177: 1511 | BE177: FG Loose 3WH | BF177: 5094124440 | BG177: 05.05.2026
A178: 1115 | B178: 1115 | C178: 10 | D178: 2 | E178: Three Wheelers | F178: F2 | G178: COMMERCIAL INVOICE | H178: 1526006120 | I178: 1000006391 | L178: 05.05.2026 | M178: 5100001588 | N178: ZSCH | O178: Normal Sales | P178: 4110025058 | Q178: 18.02.2020 | R178: 5000 | S178: BAJAJ AUTO LIMITED (WALUJ) | V178: 27340676530V | W178: 1502040235 | X178: AA102281_ASSLY HANDLE STARTING | Y178: =VLOOKUP(W178,Sheet4!$A$5:$B$71,2,0) -> STARTING HANDLE | Z178: 87082900 | AA178: 540 | AB178: EA | AC178: 217.33 | AD178: INR | AE178: 117358.2 | AF178: 0 | AG178: 117358.2 | AH178: 0 | AI178: 0 | AJ178: 0 | AK178: 0 | AL178: 117358.2 | AM178: 0 | AN178: 0 | AO178: 0 | AP178: 0 | AQ178: 0 | AR178: 0 | AS178: 0 | AT178: 0 | AU178: 117358.2 | AV178: 0 | AW178: 0 | AX178: 311000 | AY178: SALE FINISHED GOODS | AZ178: 1.19 | BA178: 1.19 | BB178: 0 | BC178: AA102281 | BD178: 1511 | BE178: FG Loose 3WH | BF178: 5094121130 | BG178: 05.05.2026
... A195: 1115 | B195: 1115 | C195: 10 | D195: 2 | E195: Three Wheelers | F195: F2 | G195: COMMERCIAL INVOICE | H195: 1526006096 | I195: 1000006367 | L195: 05.05.2026 | M195: 5100001928 | N195: ZSCH | O195: Normal Sales | P195: 4110057393 | Q195: 28.11.2024 | R195: 5000 | S195: BAJAJ AUTO LIMITED (WALUJ) | V195: 27340676530V | W195: 1502020122 | X195: 52AH0692 BODY ASSLY MAXIMA Z EV | Y195: =VLOOKUP(W195,Sheet4!$A$5:$B$71,2,0) -> MAX UG NEW EV | Z195: 87082900 | AA195: 10 | AB195: EA | AC195: 9566.51 | AD195: INR | AE195: 95665.1 | AF195: 0 | AG195: 95665.1 | AH195: 0 | AI195: 0 | AJ195: 0 | AK195: 0 | AL195: 95665.1 | AM195: 0 | AN195: 0 | AO195: 0 | AP195: 0 | AQ195: 0 | AR195: 0 | AS195: 0 | AT195: 0 | AU195: 95665.1 | AV195: 0 | AW195: 0 | AX195: 311000 | AY195: SALE FINISHED GOODS | AZ195: 0 | BA195: 61 | BB195: -61 | BC195: 52AH0692 | BD195: 1509 | BE195: FG Body | BF195: 5094121026 | BG195: 05.05.2026
A196: 1115 | B196: 1115 | C196: 10 | D196: 2 | E196: Three Wheelers | F196: F2 | G196: COMMERCIAL INVOICE | H196: 1526006094 | I196: 1000006365 | L196: 05.05.2026 | M196: 5100001666 | N196: ZSCH | O196: Normal Sales | P196: 4110027035 | Q196: 03.09.2020 | R196: 5000 | S196: BAJAJ AUTO LIMITED (WALUJ) | V196: 27340676530V | W196: 1502020105 | X196: 52AU0123 BODY ASSLY 4S PETROL | Y196: =VLOOKUP(W196,Sheet4!$A$5:$B$71,2,0) -> RE STYLING | Z196: 87082900 | AA196: 15 | AB196: EA | AC196: 6570.77 | AD196: INR | AE196: 98561.55 | AF196: 0 | AG196: 98561.55 | AH196: 0 | AI196: 0 | AJ196: 0 | AK196: 0 | AL196: 98561.55 | AM196: 0 | AN196: 0 | AO196: 0 | AP196: 0 | AQ196: 0 | AR196: 0 | AS196: 0 | AT196: 0 | AU196: 98561.55 | AV196: 0 | AW196: 0 | AX196: 311000 | AY196: SALE FINISHED GOODS | AZ196: 49.75 | BA196: 49.75 | BB196: 0 | BC196: 52AU0123 | BD196: 1509 | BE196: FG Body | BF196: PENDING | BG196: Pending
A197: 1115 | B197: 1115 | C197: 10 | D197: 2 | E197: Three Wheelers | F197: F2 | G197: COMMERCIAL INVOICE | H197: 1526006093 | I197: 1000006364 | L197: 05.05.2026 | M197: 5100001666 | N197: ZSCH | O197: Normal Sales | P197: 4110027035 | Q197: 03.09.2020 | R197: 5000 | S197: BAJAJ AUTO LIMITED (WALUJ) | V197: 27340676530V | W197: 1502020105 | X197: 52AU0123 BODY ASSLY 4S PETROL | Y197: =VLOOKUP(W197,Sheet4!$A$5:$B$71,2,0) -> RE STYLING | Z197: 87082900 | AA197: 15 | AB197: EA | AC197: 6570.77 | AD197: INR | AE197: 98561.55 | AF197: 0 | AG197: 98561.55 | AH197: 0 | AI197: 0 | AJ197: 0 | AK197: 0 | AL197: 98561.55 | AM197: 0 | AN197: 0 | AO197: 0 | AP197: 0 | AQ197: 0 | AR197: 0 | AS197: 0 | AT197: 0 | AU197: 98561.55 | AV197: 0 | AW197: 0 | AX197: 311000 | AY197: SALE FINISHED GOODS | AZ197: 49.75 | BA197: 49.75 | BB197: 0 | BC197: 52AU0123 | BD197: 1509 | BE197: FG Body | BF197: 5094126948 | BG197: 05.05.2026
A198: 1115 | B198: 1115 | C198: 10 | D198: 2 | E198: Three Wheelers | F198: F2 | G198: COMMERCIAL INVOICE | H198: 1526006092 | I198: 1000006363 | L198: 05.05.2026 | M198: 5100001924 | N198: ZSCH | O198: Normal Sales | P198: 4110055642 | Q198: 09.09.2024 | R198: 5000 | S198: BAJAJ AUTO LIMITED (WALUJ) | V198: 27340676530V | W198: 1502040314 | X198: 52BA0835 RE DOOR ASSLY LH YELLOW | Y198: =VLOOKUP(W198,Sheet4!$A$5:$B$71,2,0) -> Re Side Door | Z198: 87082900 | AA198: 120 | AB198: EA | AC198: 504.46 | AD198: INR | AE198: 60535.2 | AF198: 0 | AG198: 60535.2 | AH198: 0 | AI198: 0 | AJ198: 0 | AK198: 0 | AL198: 60535.2 | AM198: 0 | AN198: 0 | AO198: 0 | AP198: 0 | AQ198: 0 | AR198: 0 | AS198: 0 | AT198: 0 | AU198: 60535.2 | AV198: 0 | AW198: 0 | AX198: 311000 | AY198: SALE FINISHED GOODS | AZ198: 2.27 | BA198: 2.27 | BB198: 0 | BC198: 52BA0835 | BD198: 1511 | BE198: FG Loose 3WH | BF198: 5094124097 | BG198: 05.05.2026
A199: 1115 | B199: 1115 | C199: 10 | D199: 2 | E199: Three Wheelers | F199: F2 | G199: COMMERCIAL INVOICE | H199: 1526006144 | I199: 1000006414 | L199: 05.05.2026 | M199: 5100001407 | N199: ZSCH | O199: Normal Sales | P199: 4110019623 | Q199: 06.05.2019 | R199: 5000 | S199: BAJAJ AUTO LIMITED (WALUJ) | V199: 27340676530V | W199: 1502040216 | X199: AA161289_ ASSEMBLY MUDGUARD FRONT | Y199: =VLOOKUP(W199,Sheet4!$A$5:$B$71,2,0) -> FRONT MUDGAURD | Z199: 87082900 | AA199: 1280 | AB199: EA | AC199: 174.11 | AD199: INR | AE199: 222860.8 | AF199: 0 | AG199: 222860.8 | AH199: 0 | AI199: 0 | AJ199: 0 | AK199: 0 | AL199: 222860.8 | AM199: 0 | AN199: 0 | AO199: 0 | AP199: 0 | AQ199: 0 | AR199: 0 | AS199: 0 | AT199: 0 | AU199: 222860.8 | AV199: 0 | AW199: 0 | AX199: 311000 | AY199: SALE FINISHED GOODS | AZ199: 2.573 | BA199: 1.491 | BB199: 1.082 | BC199: AA161289 | BD199: 1511 | BE199: FG Loose 3WH | BF199: 5094130202 | BG199: 06.05.2026
A200: 1115 | B200: 1115 | C200: 10 | D200: 2 | E200: Three Wheelers | F200: F2 | G200: COMMERCIAL INVOICE | H200: 1526006185 | I200: 1000006453 | L200: 05.05.2026 | M200: 5100001227 | N200: ZSCH | O200: Normal Sales | P200: 4110011319 | Q200: 18.12.2017 | R200: 5000 | S200: BAJAJ AUTO LIMITED (WALUJ) | V200: 27340676530V | W200: 1502020074 | X200: 52AZ0184 BODY ASSLY MAX Z WTH REGU. HOOD | Y200: =VLOOKUP(W200,Sheet4!$A$5:$B$71,2,0) -> MAX UG NEW | Z200: 87082900 | AA200: 10 | AB200: EA | AC200: 9397.5 | AD200: INR | AE200: 93975 | AF200: 0 | AG200: 93975 | AH200: 0 | AI200: 0 | AJ200: 0 | AK200: 0 | AL200: 93975 | AM200: 0 | AN200: 0 | AO200: 0 | AP200: 0 | AQ200: 0 | AR200: 0 | AS200: 0 | AT200: 0 | AU200: 93975 | AV200: 0 | AW200: 0 | AX200: 311000 | AY200: SALE FINISHED GOODS | AZ200: 69.5 | BA200: 69.5 | BB200: 0 | BC200: 52AZ0184 | BD200: 1509 | BE200: FG Body | BF200: 5094131508 | BG200: 06.05.2026
A201: 1115 | B201: 1115 | C201: 10 | D201: 2 | E201: Three Wheelers | F201: F2 | G201: COMMERCIAL INVOICE | H201: 1526006184 | I201: 1000006452 | L201: 05.05.2026 | M201: 5100001227 | N201: ZSCH | O201: Normal Sales | P201: 4110011319 | Q201: 18.12.2017 | R201: 5000 | S201: BAJAJ AUTO LIMITED (WALUJ) | V201: 27340676530V | W201: 1502020074 | X201: 52AZ0184 BODY ASSLY MAX Z WTH REGU. HOOD | Y201: =VLOOKUP(W201,Sheet4!$A$5:$B$71,2,0) -> MAX UG NEW | Z201: 87082900 | AA201: 10 | AB201: EA | AC201: 9397.5 | AD201: INR | AE201: 93975 | AF201: 0 | AG201: 93975 | AH201: 0 | AI201: 0 | AJ201: 0 | AK201: 0 | AL201: 93975 | AM201: 0 | AN201: 0 | AO201: 0 | AP201: 0 | AQ201: 0 | AR201: 0 | AS201: 0 | AT201: 0 | AU201: 93975 | AV201: 0 | AW201: 0 | AX201: 311000 | AY201: SALE FINISHED GOODS | AZ201: 69.5 | BA201: 69.5 | BB201: 0 | BC201: 52AZ0184 | BD201: 1509 | BE201: FG Body | BF201: 5094131507 | BG201: 06.05.2026
A202: 1115 | B202: 1115 | C202: 10 | D202: 2 | E202: Three Wheelers | F202: F2 | G202: COMMERCIAL INVOICE | H202: 1526006183 | I202: 1000006451 | L202: 05.05.2026 | M202: 5100001227 | N202: ZSCH | O202: Normal Sales | P202: 4110011319 | Q202: 18.12.2017 | R202: 5000 | S202: BAJAJ AUTO LIMITED (WALUJ) | V202: 27340676530V | W202: 1502020074 | X202: 52AZ0184 BODY ASSLY MAX Z WTH REGU. HOOD | Y202: =VLOOKUP(W202,Sheet4!$A$5:$B$71,2,0) -> MAX UG NEW | Z202: 87082900 | AA202: 10 | AB202: EA | AC202: 9397.5 | AD202: INR | AE202: 93975 | AF202: 0 | AG202: 93975 | AH202: 0 | AI202: 0 | AJ202: 0 | AK202: 0 | AL202: 93975 | AM202: 0 | AN202: 0 | AO202: 0 | AP202: 0 | AQ202: 0 | AR202: 0 | AS202: 0 | AT202: 0 | AU202: 93975 | AV202: 0 | AW202: 0 | AX202: 311000 | AY202: SALE FINISHED GOODS | AZ202: 69.5 | BA202: 69.5 | BB202: 0 | BC202: 52AZ0184 | BD202: 1509 | BE202: FG Body | BF202: 5094131365 | BG202: 06.05.2026
A203: 1115 | B203: 1115 | C203: 10 | D203: 2 | E203: Three Wheelers | F203: F2 | G203: COMMERCIAL INVOICE | H203: 1526006182 | I203: 1000006450 | L203: 05.05.2026 | M203: 5100001227 | N203: ZSCH | O203: Normal Sales | P203: 4110011319 | Q203: 18.12.2017 | R203: 5000 | S203: BAJAJ AUTO LIMITED (WALUJ) | V203: 27340676530V | W203: 1502020074 | X203: 52AZ0184 BODY ASSLY MAX Z WTH REGU. HOOD | Y203: =VLOOKUP(W203,Sheet4!$A$5:$B$71,2,0) -> MAX UG NEW | Z203: 87082900 | AA203: 10 | AB203: EA | AC203: 9397.5 | AD203: INR | AE203: 93975 | AF203: 0 | AG203: 93975 | AH203: 0 | AI203: 0 | AJ203: 0 | AK203: 0 | AL203: 93975 | AM203: 0 | AN203: 0 | AO203: 0 | AP203: 0 | AQ203: 0 | AR203: 0 | AS203: 0 | AT203: 0 | AU203: 93975 | AV203: 0 | AW203: 0 | AX203: 311000 | AY203: SALE FINISHED GOODS | AZ203: 69.5 | BA203: 69.5 | BB203: 0 | BC203: 52AZ0184 | BD203: 1509 | BE203: FG Body | BF203: 5094131506 | BG203: 06.05.2026
A204: 1115 | B204: 1115 | C204: 10 | D204: 2 | E204: Three Wheelers | F204: F2 | G204: COMMERCIAL INVOICE | H204: 1526006181 | I204: 1000006449 | L204: 05.05.2026 | M204: 5100001934 | N204: ZSCH | O204: Normal Sales | P204: 4110058649 | Q204: 10.02.2025 | R204: 5000 | S204: BAJAJ AUTO LIMITED (WALUJ) | V204: 27340676530V | W204: 1502040217 | X204: AH111571 MUDGUARD ASSEMBLY FORNT | Y204: =VLOOKUP(W204,Sheet4!$A$5:$B$71,2,0) -> FRONT MUDGARD GOGO | Z204: 87082900 | AA204: 60 | AB204: EA | AC204: 380.93 | AD204: INR | AE204: 22855.8 | AF204: 0 | AG204: 22855.8 | AH204: 0 | AI204: 0 | AJ204: 0 | AK204: 0 | AL204: 22855.8 | AM204: 0 | AN204: 0 | AO204: 0 | AP204: 0 | AQ204: 0 | AR204: 0 | AS204: 0 | AT204: 0 | AU204: 22855.8 | AV204: 0 | AW204: 0 | AX204: 311000 | AY204: SALE FINISHED GOODS | AZ204: 2.13 | BA204: 2.13 | BB204: 0 | BC204: AH111571 | BD204: 1511 | BE204: FG Loose 3WH | BF204: 5094131864 | BG204: 06.05.2026
A205: 1115 | B205: 1115 | C205: 10 | D205: 2 | E205: Three Wheelers | F205: F2 | G205: COMMERCIAL INVOICE | H205: 1526006180 | I205: 1000006448 | L205: 05.05.2026 | M205: 5100001227 | N205: ZSCH | O205: Normal Sales | P205: 4110011319 | Q205: 18.12.2017 | R205: 5000 | S205: BAJAJ AUTO LIMITED (WALUJ) | V205: 27340676530V | W205: 1502020074 | X205: 52AZ0184 BODY ASSLY MAX Z WTH REGU. HOOD | Y205: =VLOOKUP(W205,Sheet4!$A$5:$B$71,2,0) -> MAX UG NEW | Z205: 87082900 | AA205: 10 | AB205: EA | AC205: 9397.5 | AD205: INR | AE205: 93975 | AF205: 0 | AG205: 93975 | AH205: 0 | AI205: 0 | AJ205: 0 | AK205: 0 | AL205: 93975 | AM205: 0 | AN205: 0 | AO205: 0 | AP205: 0 | AQ205: 0 | AR205: 0 | AS205: 0 | AT205: 0 | AU205: 93975 | AV205: 0 | AW205: 0 | AX205: 311000 | AY205: SALE FINISHED GOODS | AZ205: 69.5 | BA205: 69.5 | BB205: 0 | BC205: 52AZ0184 | BD205: 1509 | BE205: FG Body | BF205: PENDING | BG205: Pending
A206: 1115 | B206: 1115 | C206: 10 | D206: 2 | E206: Three Wheelers | F206: F2 | G206: COMMERCIAL INVOICE | H206: 1526006179 | I206: 1000006447 | L206: 05.05.2026 | M206: 5100001227 | N206: ZSCH | O206: Normal Sales | P206: 4110011319 | Q206: 18.12.2017 | R206: 5000 | S206: BAJAJ AUTO LIMITED (WALUJ) | V206: 27340676530V | W206: 1502020074 | X206: 52AZ0184 BODY ASSLY MAX Z WTH REGU. HOOD | Y206: =VLOOKUP(W206,Sheet4!$A$5:$B$71,2,0) -> MAX UG NEW | Z206: 87082900 | AA206: 10 | AB206: EA | AC206: 9397.5 | AD206: INR | AE206: 93975 | AF206: 0 | AG206: 93975 | AH206: 0 | AI206: 0 | AJ206: 0 | AK206: 0 | AL206: 93975 | AM206: 0 | AN206: 0 | AO206: 0 | AP206: 0 | AQ206: 0 | AR206: 0 | AS206: 0 | AT206: 0 | AU206: 93975 | AV206: 0 | AW206: 0 | AX206: 311000 | AY206: SALE FINISHED GOODS | AZ206: 69.5 | BA206: 69.5 | BB206: 0 | BC206: 52AZ0184 | BD206: 1509 | BE206: FG Body | BF206: 5094131666 | BG206: 06.05.2026
A207: 1115 | B207: 1115 | C207: 10 | D207: 2 | E207: Three Wheelers | F207: F2 | G207: COMMERCIAL INVOICE | H207: 1526006178 | I207: 1000006446 | L207: 05.05.2026 | M207: 5100001227 | N207: ZSCH | O207: Normal Sales | P207: 4110011319 | Q207: 18.12.2017 | R207: 5000 | S207: BAJAJ AUTO LIMITED (WALUJ) | V207: 27340676530V | W207: 1502020074 | X207: 52AZ0184 BODY ASSLY MAX Z WTH REGU. HOOD | Y207: =VLOOKUP(W207,Sheet4!$A$5:$B$71,2,0) -> MAX UG NEW | Z207: 87082900 | AA207: 10 | AB207: EA | AC207: 9397.5 | AD207: INR | AE207: 93975 | AF207: 0 | AG207: 93975 | AH207: 0 | AI207: 0 | AJ207: 0 | AK207: 0 | AL207: 93975 | AM207: 0 | AN207: 0 | AO207: 0 | AP207: 0 | AQ207: 0 | AR207: 0 | AS207: 0 | AT207: 0 | AU207: 93975 | AV207: 0 | AW207: 0 | AX207: 311000 | AY207: SALE FINISHED GOODS | AZ207: 69.5 | BA207: 69.5 | BB207: 0 | BC207: 52AZ0184 | BD207: 1509 | BE207: FG Body | BF207: 5094132176 | BG207: 06.05.2026
A208: 1115 | B208: 1115 | C208: 10 | D208: 2 | E208: Three Wheelers | F208: F2 | G208: COMMERCIAL INVOICE | H208: 1526006177 | I208: 1000006445 | L208: 05.05.2026 | M208: 5100001227 | N208: ZSCH | O208: Normal Sales | P208: 4110011319 | Q208: 18.12.2017 | R208: 5000 | S208: BAJAJ AUTO LIMITED (WALUJ) | V208: 27340676530V | W208: 1502020074 | X208: 52AZ0184 BODY ASSLY MAX Z WTH REGU. HOOD | Y208: =VLOOKUP(W208,Sheet4!$A$5:$B$71,2,0) -> MAX UG NEW | Z208: 87082900 | AA208: 10 | AB208: EA | AC208: 9397.5 | AD208: INR | AE208: 93975 | AF208: 0 | AG208: 93975 | AH208: 0 | AI208: 0 | AJ208: 0 | AK208: 0 | AL208: 93975 | AM208: 0 | AN208: 0 | AO208: 0 | AP208: 0 | AQ208: 0 | AR208: 0 | AS208: 0 | AT208: 0 | AU208: 93975 | AV208: 0 | AW208: 0 | AX208: 311000 | AY208: SALE FINISHED GOODS | AZ208: 69.5 | BA208: 69.5 | BB208: 0 | BC208: 52AZ0184 | BD208: 1509 | BE208: FG Body | BF208: 5094132175 | BG208: 06.05.2026
A209: 1115 | B209: 1115 | C209: 10 | D209: 2 | E209: Three Wheelers | F209: F2 | G209: COMMERCIAL INVOICE | H209: 1526006176 | I209: 1000006444 | L209: 05.05.2026 | M209: 5100001636 | N209: ZSCH | O209: Normal Sales | P209: 4110026445 | Q209: 23.07.2020 | R209: 5000 | S209: BAJAJ AUTO LIMITED (WALUJ) | V209: 27340676530V | W209: 1502020104 | X209: AA231532 BODY ASSLY PETROL | Y209: =VLOOKUP(W209,Sheet4!$A$5:$B$71,2,0) -> RE STYLING | Z209: 87082900 | AA209: 15 | AB209: EA | AC209: 6585.55 | AD209: INR | AE209: 98783.25 | AF209: 0 | AG209: 98783.25 | AH209: 0 | AI209: 0 | AJ209: 0 | AK209: 0 | AL209: 98783.25 | AM209: 0 | AN209: 0 | AO209: 0 | AP209: 0 | AQ209: 0 | AR209: 0 | AS209: 0 | AT209: 0 | AU209: 98783.25 | AV209: 0 | AW209: 0 | AX209: 311000 | AY209: SALE FINISHED GOODS | AZ209: 49.75 | BA209: 49.75 | BB209: 0 | BC209: AA231532 | BD209: 1509 | BE209: FG Body | BF209: 5094131588 | BG209: 06.05.2026
A210: 1115 | B210: 1115 | C210: 10 | D210: 2 | E210: Three Wheelers | F210: F2 | G210: COMMERCIAL INVOICE | H210: 1526006175 | I210: 1000006443 | L210: 05.05.2026 | M210: 5100001636 | N210: ZSCH | O210: Normal Sales | P210: 4110026445 | Q210: 23.07.2020 | R210: 5000 | S210: BAJAJ AUTO LIMITED (WALUJ) | V210: 27340676530V | W210: 1502020104 | X210: AA231532 BODY ASSLY PETROL | Y210: =VLOOKUP(W210,Sheet4!$A$5:$B$71,2,0) -> RE STYLING | Z210: 87082900 | AA210: 15 | AB210: EA | AC210: 6585.55 | AD210: INR | AE210: 98783.25 | AF210: 0 | AG210: 98783.25 | AH210: 0 | AI210: 0 | AJ210: 0 | AK210: 0 | AL210: 98783.25 | AM210: 0 | AN210: 0 | AO210: 0 | AP210: 0 | AQ210: 0 | AR210: 0 | AS210: 0 | AT210: 0 | AU210: 98783.25 | AV210: 0 | AW210: 0 | AX210: 311000 | AY210: SALE FINISHED GOODS | AZ210: 49.75 | BA210: 49.75 | BB210: 0 | BC210: AA231532 | BD210: 1509 | BE210: FG Body | BF210: 5094131582 | BG210: 06.05.2026
A211: 1115 | B211: 1115 | C211: 10 | D211: 2 | E211: Three Wheelers | F211: F2 | G211: COMMERCIAL INVOICE | H211: 1526006174 | I211: 1000006442 | L211: 05.05.2026 | M211: 5100001636 | N211: ZSCH | O211: Normal Sales | P211: 4110026445 | Q211: 23.07.2020 | R211: 5000 | S211: BAJAJ AUTO LIMITED (WALUJ) | V211: 27340676530V | W211: 1502020104 | X211: AA231532 BODY ASSLY PETROL | Y211: =VLOOKUP(W211,Sheet4!$A$5:$B$71,2,0) -> RE STYLING | Z211: 87082900 | AA211: 15 | AB211: EA | AC211: 6585.55 | AD211: INR | AE211: 98783.25 | AF211: 0 | AG211: 98783.25 | AH211: 0 | AI211: 0 | AJ211: 0 | AK211: 0 | AL211: 98783.25 | AM211: 0 | AN211: 0 | AO211: 0 | AP211: 0 | AQ211: 0 | AR211: 0 | AS211: 0 | AT211: 0 | AU211: 98783.25 | AV211: 0 | AW211: 0 | AX211: 311000 | AY211: SALE FINISHED GOODS | AZ211: 49.75 | BA211: 49.75 | BB211: 0 | BC211: AA231532 | BD211: 1509 | BE211: FG Body | BF211: 5094131565 | BG211: 06.05.2026
A212: 1115 | B212: 1115 | C212: 10 | D212: 2 | E212: Three Wheelers | F212: F2 | G212: COMMERCIAL INVOICE | H212: 1526006173 | I212: 1000006441 | L212: 05.05.2026 | M212: 5100001636 | N212: ZSCH | O212: Normal Sales | P212: 4110026445 | Q212: 23.07.2020 | R212: 5000 | S212: BAJAJ AUTO LIMITED (WALUJ) | V212: 27340676530V | W212: 1502020104 | X212: AA231532 BODY ASSLY PETROL | Y212: =VLOOKUP(W212,Sheet4!$A$5:$B$71,2,0) -> RE STYLING | Z212: 87082900 | AA212: 15 | AB212: EA | AC212: 6585.55 | AD212: INR | AE212: 98783.25 | AF212: 0 | AG212: 98783.25 | AH212: 0 | AI212: 0 | AJ212: 0 | AK212: 0 | AL212: 98783.25 | AM212: 0 | AN212: 0 | AO212: 0 | AP212: 0 | AQ212: 0 | AR212: 0 | AS212: 0 | AT212: 0 | AU212: 98783.25 | AV212: 0 | AW212: 0 | AX212: 311000 | AY212: SALE FINISHED GOODS | AZ212: 49.75 | BA212: 49.75 | BB212: 0 | BC212: AA231532 | BD212: 1509 | BE212: FG Body | BF212: 5094131611 | BG212: 06.05.2026
A213: 1115 | B213: 1115 | C213: 10 | D213: 2 | E213: Three Wheelers | F213: F2 | G213: COMMERCIAL INVOICE | H213: 1526006172 | I213: 1000006440 | L213: 05.05.2026 | M213: 5100001636 | N213: ZSCH | O213: Normal Sales | P213: 4110026445 | Q213: 23.07.2020 | R213: 5000 | S213: BAJAJ AUTO LIMITED (WALUJ) | V213: 27340676530V | W213: 1502020104 | X213: AA231532 BODY ASSLY PETROL | Y213: =VLOOKUP(W213,Sheet4!$A$5:$B$71,2,0) -> RE STYLING | Z213: 87082900 | AA213: 15 | AB213: EA | AC213: 6585.55 | AD213: INR | AE213: 98783.25 | AF213: 0 | AG213: 98783.25 | AH213: 0 | AI213: 0 | AJ213: 0 | AK213: 0 | AL213: 98783.25 | AM213: 0 | AN213: 0 | AO213: 0 | AP213: 0 | AQ213: 0 | AR213: 0 | AS213: 0 | AT213: 0 | AU213: 98783.25 | AV213: 0 | AW213: 0 | AX213: 311000 | AY213: SALE FINISHED GOODS | AZ213: 49.75 | BA213: 49.75 | BB213: 0 | BC213: AA231532 | BD213: 1509 | BE213: FG Body | BF213: 5094131564 | BG213: 06.05.2026
...
